Workbook

Sheet 10.1
A1: 2020 - 2016 ,udwdwA egcnirevurutwf iawaejcaWr cnutogegukwtumuawq : 10.1 ulwvWt
A2: Table 10.1 : FLOW OF TOURISTS BY NATIONALITY, 2016 - 2020
A4: Country of Nationality | F4: udwdwA egcnirevurutwf | P4: cniawtcaws ctogWviawfiheb | Z4: އިތުރުވި މިންވަރު | AE4: Wviawfevirevcnwzwv
F5: No. of Tourists | P5: Percentage Share | Z5: % change over previous year | AE5: cawtumuawq
B6: 2012 | C6: 2013 | D6: 2014 | E6: 2015 | F6: 2016 | G6: 2017 | H6: 2018 | I6: 2019 | J6: 2020 | L6: 2012 | M6: 2013 | N6: 2014 | O6: 2015 | P6: 2016 | Q6: 2017 | R6: 2018 | S6: 2019 | T6: 2020 | V6: 2012 | W6: 2013 | X6: 2014 | Y6: 2015 | Z6: 2016 | AA6: 2017 | AB6: 2018 | AC6: 2019 | AD6: 2020
A7: Total | B7: =B8+B35+B50+B53+B58+B62 -> 958025 | C7: =C8+C35+C50+C53+C58+C62+C68+C69 -> 1125202 | D7: =D8+D35+D50+D53+D58+D62+D68+D69 -> 1204857 | E7: =E8+E35+E50+E53+E58+E62+E68+E69 -> 1234248 | F7: =F8+F35+F50+F53+F58+F62+F68+F69 -> 1286135 | G7: =G8+G35+G50+G53+G58+G62+G68+G69 -> 1389542 | H7: =H8+H35+H50+H53+H58+H62+H68+H69 -> 1484274 | I7: =I8+I35+I50+I53+I58+I62+I68+I69 -> 1702887 | J7: =J8+J35+J50+J53+J58+J62+J68+J69 -> 555494 | L7: =B7/B$7*100 -> 100 | M7: =C7/C$7*100 -> 100 | N7: =D7/D$7*100 -> 100 | O7: =E7/E$7*100 -> 100 | P7: =F7/F$7*100 -> 100 | Q7: =G7/G$7*100 -> 100 | R7: =H7/H$7*100 -> 100 | S7: =I7/I$7*100 -> 100 | T7: =J7/J$7*100 -> 100 | V7: 2.8659996 | W7: =(C7-B7)/B7*100 -> 17.450171 | X7: =(D7-C7)/C7*100 -> 7.0791733 | Y7: =(E7-D7)/D7*100 -> 2.4393766 | Z7: =(F7-E7)/E7*100 -> 4.2039363 | AA7: =(G7-F7)/F7*100 -> 8.0401358 | AB7: =(H7-G7)/G7*100 -> 6.8174981 | AC7: =(I7-H7)/H7*100 -> 14.728615 | AD7: =(J7-I7)/I7*100 -> -67.37928 | AE7: ޖުމްލަ
A8: Europe | B8: =SUM(B9:B34) -> 517807 | C8: =SUM(C9:C34) -> 527274 | D8: =SUM(D9:D34) -> 529291 | E8: =SUM(E9:E34) -> 535962 | F8: =SUM(F9:F34) -> 575176 | G8: =SUM(G9:G34) -> 646343 | H8: =SUM(H9:H34) -> 726420 | I8: =SUM(I9:I34) -> 833939 | J8: =SUM(J9:J34) -> 348349 | L8: =B8/B$7*100 -> 54.049425 | M8: =C8/C$7*100 -> 46.860386 | N8: =D8/D$7*100 -> 43.929778 | O8: =E8/E$7*100 -> 43.424174 | P8: =F8/F$7*100 -> 44.721277 | Q8: =G8/G$7*100 -> 46.514823 | R8: =H8/H$7*100 -> 48.941098 | S8: =I8/I$7*100 -> 48.972069 | T8: =J8/J$7*100 -> 62.709768 | V8: -3.7098541 | W8: =(C8-B8)/B8*100 -> 1.8282874 | X8: =(D8-C8)/C8*100 -> 0.38253356 | Y8: =(E8-D8)/D8*100 -> 1.2603653 | Z8: =(F8-E8)/E8*100 -> 7.3165635 | AA8: =(G8-F8)/F8*100 -> 12.373082 | AB8: =(H8-G8)/G8*100 -> 12.389242 | AC8: =(I8-H8)/H8*100 -> 14.801217 | AD8: =(J8-I8)/I8*100 -> -58.22848 | AE8: ޔޫރަޕް
A9: Austria | B9: 18164 | C9: 18140 | D9: 18726 | E9: 18981 | F9: 17654 | G9: 19709 | H9: 20391 | I9: 21839 | J9: 8103 | L9: =B9/B$7*100 -> 1.8959839 | M9: =C9/C$7*100 -> 1.612155 | N9: =D9/D$7*100 -> 1.5542093 | O9: =E9/E$7*100 -> 1.5378595 | P9: =F9/F$7*100 -> 1.3726397 | Q9: =G9/G$7*100 -> 1.418381 | R9: =H9/H$7*100 -> 1.373803 | S9: =I9/I$7*100 -> 1.2824691 | T9: =J9/J$7*100 -> 1.4587016 | V9: 9.0603422 | W9: =(C9-B9)/B9*100 -> -0.13212949 | X9: =(D9-C9)/C9*100 -> 3.23043 | Y9: =(E9-D9)/D9*100 -> 1.361743 | Z9: =(F9-E9)/E9*100 -> -6.9912017 | AA9: =(G9-F9)/F9*100 -> 11.640421 | AB9: =(H9-G9)/G9*100 -> 3.4603481 | AC9: =(I9-H9)/H9*100 -> 7.1011721 | AD9: =(J9-I9)/I9*100 -> -62.896653 | AE9: އޮސްޓްރިއާ | BA9: 2016 | BB9: 2017 | BC9: 2018 | BD9: 2019 | BE9: 2020
A10: Belgium | B10: 1509 | C10: 5130 | D10: 5195 | E10: 5250 | F10: 5571 | G10: 5854 | H10: 6492 | I10: 7305 | J10: 2921 | L10: =B10/B$7*100 -> 0.15751155 | M10: =C10/C$7*100 -> 0.45591814 | N10: =D10/D$7*100 -> 0.4311715 | O10: =E10/E$7*100 -> 0.42536022 | P10: =F10/F$7*100 -> 0.43315826 | Q10: =G10/G$7*100 -> 0.42128989 | R10: =H10/H$7*100 -> 0.43738555 | S10: =I10/I$7*100 -> 0.42897738 | T10: =J10/J$7*100 -> 0.52583826 | V10: -73.701638 | W10: =(C10-B10)/B10*100 -> 239.96024 | X10: =(D10-C10)/C10*100 -> 1.2670565 | Y10: =(E10-D10)/D10*100 -> 1.0587103 | Z10: =(F10-E10)/E10*100 -> 6.1142857 | AA10: =(G10-F10)/F10*100 -> 5.0798779 | AB10: =(H10-G10)/G10*100 -> 10.898531 | AC10: =(I10-H10)/H10*100 -> 12.523105 | AD10: =(J10-I10)/I10*100 -> -60.013689 | AE10: ބެލްޖިއަމް | AY10: 1 | AZ10: India | BA10: 66955 | BB10: 83019 | BC10: 90474 | BD10: 166030 | BE10: 62960
A11: Czech Republic | B11: 5588 | C11: 6421 | D11: 6450 | E11: 8105 | F11: 10338 | G11: 11459 | H11: 13229 | I11: 13423 | J11: 7282 | L11: =B11/B$7*100 -> 0.58328332 | M11: =C11/C$7*100 -> 0.57065309 | N11: =D11/D$7*100 -> 0.53533324 | O11: =E11/E$7*100 -> 0.65667516 | P11: =F11/F$7*100 -> 0.80380364 | Q11: =G11/G$7*100 -> 0.82466021 | R11: =H11/H$7*100 -> 0.89127749 | S11: =I11/I$7*100 -> 0.7882496 | T11: =J11/J$7*100 -> 1.3109052 | V11: -13.645495 | W11: =(C11-B11)/B11*100 -> 14.906943 | X11: =(D11-C11)/C11*100 -> 0.45164305 | Y11: =(E11-D11)/D11*100 -> 25.658915 | Z11: =(F11-E11)/E11*100 -> 27.550895 | AA11: =(G11-F11)/F11*100 -> 10.84349 | AB11: =(H11-G11)/G11*100 -> 15.446374 | AC11: =(I11-H11)/H11*100 -> 1.4664752 | AD11: =(J11-I11)/I11*100 -> -45.749832 | AE11: ޗެކްރިޕަބްލިކް | AY11: 2 | AZ11: Russia | BA11: 46522 | BB11: 61931 | BC11: 70935 | BD11: 83369 | BE11: 61387
A12: Denmark | B12: 3493 | C12: 4055 | D12: 5008 | E12: 8418 | F12: 9747 | G12: 10629 | H12: 11133 | I12: 10621 | J12: 3938 | L12: =B12/B$7*100 -> 0.36460426 | M12: =C12/C$7*100 -> 0.36037974 | N12: =D12/D$7*100 -> 0.41565099 | O12: =E12/E$7*100 -> 0.68203473 | P12: =F12/F$7*100 -> 0.75785201 | Q12: =G12/G$7*100 -> 0.7649283 | R12: =H12/H$7*100 -> 0.75006367 | S12: =I12/I$7*100 -> 0.62370551 | T12: =J12/J$7*100 -> 0.70891855 | V12: 10.085093 | W12: =(C12-B12)/B12*100 -> 16.089322 | X12: =(D12-C12)/C12*100 -> 23.50185 | Y12: =(E12-D12)/D12*100 -> 68.091054 | Z12: =(F12-E12)/E12*100 -> 15.787598 | AA12: =(G12-F12)/F12*100 -> 9.0489381 | AB12: =(H12-G12)/G12*100 -> 4.7417443 | AC12: =(I12-H12)/H12*100 -> -4.5989401 | AD12: =(J12-I12)/I12*100 -> -62.922512 | AE12: ޑެންމާރކް | AY12: 3 | AZ12: United Kingdom | BA12: 101843 | BB12: 103977 | BC12: 114602 | BD12: 126199 | BE12: 52720
A13: Finland | B13: 1402 | C13: 1549 | D13: 5627 | E13: 2109 | F13: 2589 | G13: 3705 | H13: 5682 | I13: 5315 | J13: 2128 | L13: =B13/B$7*100 -> 0.14634274 | M13: =C13/C$7*100 -> 0.13766417 | N13: =D13/D$7*100 -> 0.46702638 | O13: =E13/E$7*100 -> 0.17087328 | P13: =F13/F$7*100 -> 0.2013008 | Q13: =G13/G$7*100 -> 0.26663462 | R13: =H13/H$7*100 -> 0.38281342 | S13: =I13/I$7*100 -> 0.31211701 | T13: =J13/J$7*100 -> 0.38308245 | V13: -8.6644951 | W13: =(C13-B13)/B13*100 -> 10.485021 | X13: =(D13-C13)/C13*100 -> 263.26662 | Y13: =(E13-D13)/D13*100 -> -62.519993 | Z13: =(F13-E13)/E13*100 -> 22.759602 | AA13: =(G13-F13)/F13*100 -> 43.105446 | AB13: =(H13-G13)/G13*100 -> 53.360324 | AC13: =(I13-H13)/H13*100 -> -6.4589933 | AD13: =(J13-I13)/I13*100 -> -59.962371 | AE13: ފިންލޭންޑް | AY13: 4 | AZ13: Italy | BA13: 71202 | BB13: 88848 | BC13: 105297 | BD13: 136343 | BE13: 46690
A14: France | B14: 56775 | C14: 54328 | D14: 50656 | E14: 42024 | F14: 40487 | G14: 42365 | H14: 50476 | I14: 59738 | J14: 28031 | L14: =B14/B$7*100 -> 5.9262545 | M14: =C14/C$7*100 -> 4.8282886 | N14: =D14/D$7*100 -> 4.2043164 | O14: =E14/E$7*100 -> 3.4048263 | P14: =F14/F$7*100 -> 3.1479588 | Q14: =G14/G$7*100 -> 3.0488463 | R14: =H14/H$7*100 -> 3.4007198 | S14: =I14/I$7*100 -> 3.5080425 | T14: =J14/J$7*100 -> 5.0461391 | V14: -4.8899387 | W14: =(C14-B14)/B14*100 -> -4.3099956 | X14: =(D14-C14)/C14*100 -> -6.7589457 | Y14: =(E14-D14)/D14*100 -> -17.04043 | Z14: =(F14-E14)/E14*100 -> -3.6574338 | AA14: =(G14-F14)/F14*100 -> 4.6385259 | AB14: =(H14-G14)/G14*100 -> 19.145521 | AC14: =(I14-H14)/H14*100 -> 18.349315 | AD14: =(J14-I14)/I14*100 -> -53.076769 | AE14: ފްރާންސް | AY14: 5 | AZ14: Germany | BA14: 106381 | BB14: 112109 | BC14: 117532 | BD14: 131561 | BE14: 36435
A15: Germany | B15: 98351 | C15: 93598 | D15: 98328 | E15: 105132 | F15: 106381 | G15: 112109 | H15: 117532 | I15: 131561 | J15: 36435 | L15: =B15/B$7*100 -> 10.266016 | M15: =C15/C$7*100 -> 8.3183286 | N15: =D15/D$7*100 -> 8.1609685 | O15: =E15/E$7*100 -> 8.5178992 | P15: =F15/F$7*100 -> 8.2713712 | Q15: =G15/G$7*100 -> 8.0680541 | R15: =H15/H$7*100 -> 7.9184841 | S15: =I15/I$7*100 -> 7.7257622 | T15: =J15/J$7*100 -> 6.5590267 | V15: 8.6547278 | W15: =(C15-B15)/B15*100 -> -4.8326911 | X15: =(D15-C15)/C15*100 -> 5.0535268 | Y15: =(E15-D15)/D15*100 -> 6.9196973 | Z15: =(F15-E15)/E15*100 -> 1.1880303 | AA15: =(G15-F15)/F15*100 -> 5.3844202 | AB15: =(H15-G15)/G15*100 -> 4.8372566 | AC15: =(I15-H15)/H15*100 -> 11.936324 | AD15: =(J15-I15)/I15*100 -> -72.305622 | AE15: ޖާމަނީ | AY15: 6 | AZ15: China | BA15: 324326 | BB15: 306530 | BC15: 283116 | BD15: 284029 | BE15: 34245
A16: Greece | B16: 2058 | C16: 1841 | D16: 1981 | E16: 1700 | F16: 2077 | G16: 2470 | H16: 2398 | I16: 2805 | J16: 871 | L16: =B16/B$7*100 -> 0.21481694 | M16: =C16/C$7*100 -> 0.16361507 | N16: =D16/D$7*100 -> 0.16441785 | O16: =E16/E$7*100 -> 0.13773569 | P16: =F16/F$7*100 -> 0.1614916 | Q16: =G16/G$7*100 -> 0.17775641 | R16: =H16/H$7*100 -> 0.16156047 | S16: =I16/I$7*100 -> 0.16472027 | T16: =J16/J$7*100 -> 0.15679737 | V16: -31.605184 | W16: =(C16-B16)/B16*100 -> -10.544218 | X16: =(D16-C16)/C16*100 -> 7.6045627 | Y16: =(E16-D16)/D16*100 -> -14.184755 | Z16: =(F16-E16)/E16*100 -> 22.176471 | AA16: =(G16-F16)/F16*100 -> 18.921521 | AB16: =(H16-G16)/G16*100 -> -2.9149798 | AC16: =(I16-H16)/H16*100 -> 16.972477 | AD16: =(J16-I16)/I16*100 -> -68.948307 | AE16: ގްރީސް | AY16: 7 | AZ16: France | BA16: 40487 | BB16: 42365 | BC16: 50476 | BD16: 59738 | BE16: 28031
A17: Hungary | B17: 2408 | C17: 2796 | D17: 3589 | E17: 4436 | F17: 5539 | G17: 6375 | H17: 7782 | I17: 10025 | J17: 5813 | L17: =B17/B$7*100 -> 0.25135043 | M17: =C17/C$7*100 -> 0.24848872 | N17: =D17/D$7*100 -> 0.29787767 | O17: =E17/E$7*100 -> 0.35940913 | P17: =F17/F$7*100 -> 0.43067019 | Q17: =G17/G$7*100 -> 0.45878426 | R17: =H17/H$7*100 -> 0.52429673 | S17: =I17/I$7*100 -> 0.58870612 | T17: =J17/J$7*100 -> 1.0464559 | V17: -7.2419106 | W17: =(C17-B17)/B17*100 -> 16.112957 | X17: =(D17-C17)/C17*100 -> 28.361946 | Y17: =(E17-D17)/D17*100 -> 23.599889 | Z17: =(F17-E17)/E17*100 -> 24.864743 | AA17: =(G17-F17)/F17*100 -> 15.092977 | AB17: =(H17-G17)/G17*100 -> 22.070588 | AC17: =(I17-H17)/H17*100 -> 28.822925 | AD17: =(J17-I17)/I17*100 -> -42.014963 | AE17: ހަންގްރީ | AY17: 8 | AZ17: U.S.A | BA17: 32589 | BB17: 39180 | BC17: 42901 | BD17: 54474 | BE17: 19759
A18: Ireland | B18: 2483 | C18: 2590 | D18: 2759 | E18: 2856 | F18: 3449 | G18: 3892 | H18: 4236 | I18: 4287 | J18: 1688 | L18: =B18/B$7*100 -> 0.25917904 | M18: =C18/C$7*100 -> 0.23018089 | N18: =D18/D$7*100 -> 0.22898983 | O18: =E18/E$7*100 -> 0.23139596 | P18: =F18/F$7*100 -> 0.26816781 | Q18: =G18/G$7*100 -> 0.28009229 | R18: =H18/H$7*100 -> 0.28539205 | S18: =I18/I$7*100 -> 0.25174894 | T18: =J18/J$7*100 -> 0.30387367 | V18: 1.5957447 | W18: =(C18-B18)/B18*100 -> 4.3093033 | X18: =(D18-C18)/C18*100 -> 6.5250965 | Y18: =(E18-D18)/D18*100 -> 3.5157666 | Z18: =(F18-E18)/E18*100 -> 20.763305 | AA18: =(G18-F18)/F18*100 -> 12.844303 | AB18: =(H18-G18)/G18*100 -> 8.8386434 | AC18: =(I18-H18)/H18*100 -> 1.203966 | AD18: =(J18-I18)/I18*100 -> -60.625146 | AE18: އަޔަރލޭންޑް | AY18: 9 | AZ18: Switzerland | BA18: 31678 | BB18: 32651 | BC18: 32984 | BD18: 33829 | BE18: 12517
A19: Israel | B19: 2569 | C19: 3253 | D19: 3299 | E19: 3567 | F19: 5072 | G19: 5949 | H19: 7748 | I19: 10424 | J19: 1782 | L19: =B19/B$7*100 -> 0.26815584 | M19: =C19/C$7*100 -> 0.28910365 | N19: =D19/D$7*100 -> 0.27380843 | O19: =E19/E$7*100 -> 0.28900189 | P19: =F19/F$7*100 -> 0.39435985 | Q19: =G19/G$7*100 -> 0.42812668 | R19: =H19/H$7*100 -> 0.52200604 | S19: =I19/I$7*100 -> 0.61213692 | T19: =J19/J$7*100 -> 0.32079554 | V19: 5.5898068 | W19: =(C19-B19)/B19*100 -> 26.625146 | X19: =(D19-C19)/C19*100 -> 1.4140793 | Y19: =(E19-D19)/D19*100 -> 8.1236738 | Z19: =(F19-E19)/E19*100 -> 42.192318 | AA19: =(G19-F19)/F19*100 -> 17.291009 | AB19: =(H19-G19)/G19*100 -> 30.240377 | AC19: =(I19-H19)/H19*100 -> 34.537945 | AD19: =(J19-I19)/I19*100 -> -82.904835 | AE19: އިޒްރޭލް | AY19: 10 | AZ19: Ukraine | BA19: 7599 | BB19: 9722 | BC19: 11430 | BD19: 13253 | BE19: 10343
A20: Italy | B20: 62782 | C20: 57854 | D20: 57862 | E20: 65616 | F20: 71202 | G20: 88848 | H20: 105297 | I20: 136343 | J20: 46690 | L20: =B20/B$7*100 -> 6.5532737 | M20: =C20/C$7*100 -> 5.1416546 | N20: =D20/D$7*100 -> 4.8023956 | O20: =E20/E$7*100 -> 5.3162736 | P20: =F20/F$7*100 -> 5.5361218 | Q20: =G20/G$7*100 -> 6.3940493 | R20: =H20/H$7*100 -> 7.0941753 | S20: =I20/I$7*100 -> 8.0065794 | T20: =J20/J$7*100 -> 8.4051313 | V20: -24.439149 | W20: =(C20-B20)/B20*100 -> -7.8493836 | X20: =(D20-C20)/C20*100 -> 0.013827912 | Y20: =(E20-D20)/D20*100 -> 13.40085 | Z20: =(F20-E20)/E20*100 -> 8.5131675 | AA20: =(G20-F20)/F20*100 -> 24.783012 | AB20: =(H20-G20)/G20*100 -> 18.513641 | AC20: =(I20-H20)/H20*100 -> 29.484221 | AD20: =(J20-I20)/I20*100 -> -65.755484 | AE20: އިޓަލީ
A21: Netherlands | B21: 6077 | C21: 6453 | D21: 7936 | E21: 9640 | F21: 10372 | G21: 12438 | H21: 13845 | I21: 12261 | J21: 3258 | L21: =B21/B$7*100 -> 0.63432583 | M21: =C21/C$7*100 -> 0.57349703 | N21: =D21/D$7*100 -> 0.65866738 | O21: =E21/E$7*100 -> 0.78104238 | P21: =F21/F$7*100 -> 0.80644722 | Q21: =G21/G$7*100 -> 0.89511508 | R21: =H21/H$7*100 -> 0.93277926 | S21: =I21/I$7*100 -> 0.72001254 | T21: =J21/J$7*100 -> 0.58650498 | V21: 6.7451256 | W21: =(C21-B21)/B21*100 -> 6.1872635 | X21: =(D21-C21)/C21*100 -> 22.981559 | Y21: =(E21-D21)/D21*100 -> 21.471774 | Z21: =(F21-E21)/E21*100 -> 7.593361 | AA21: =(G21-F21)/F21*100 -> 19.919013 | AB21: =(H21-G21)/G21*100 -> 11.312108 | AC21: =(I21-H21)/H21*100 -> -11.440953 | AD21: =(J21-I21)/I21*100 -> -73.427942 | AE21: ނެދަރލޭންޑްސް
A22: Norway | B22: 2902 | C22: 3281 | D22: 3882 | E22: 4153 | F22: 3971 | G22: 5006 | H22: 5585 | I22: 5641 | J22: 1624 | L22: =B22/B$7*100 -> 0.30291485 | M22: =C22/C$7*100 -> 0.29159209 | N22: =D22/D$7*100 -> 0.32219591 | O22: =E22/E$7*100 -> 0.33648019 | P22: =F22/F$7*100 -> 0.30875452 | Q22: =G22/G$7*100 -> 0.36026259 | R22: =H22/H$7*100 -> 0.37627823 | S22: =I22/I$7*100 -> 0.33126097 | T22: =J22/J$7*100 -> 0.29235239 | V22: 4.5765766 | W22: =(C22-B22)/B22*100 -> 13.059959 | X22: =(D22-C22)/C22*100 -> 18.317586 | Y22: =(E22-D22)/D22*100 -> 6.9809377 | Z22: =(F22-E22)/E22*100 -> -4.3823742 | AA22: =(G22-F22)/F22*100 -> 26.063964 | AB22: =(H22-G22)/G22*100 -> 11.566121 | AC22: =(I22-H22)/H22*100 -> 1.0026858 | AD22: =(J22-I22)/I22*100 -> -71.210778 | AE22: ނޯރވޭ
A23: Poland | B23: 3918 | C23: 6668 | D23: 6182 | E23: 6879 | F23: 8976 | G23: 8699 | H23: 12025 | I23: 20961 | J23: 7108 | L23: =B23/B$7*100 -> 0.40896636 | M23: =C23/C$7*100 -> 0.59260471 | N23: =D23/D$7*100 -> 0.51308994 | O23: =E23/E$7*100 -> 0.55734342 | P23: =F23/F$7*100 -> 0.69790496 | Q23: =G23/G$7*100 -> 0.62603361 | R23: =H23/H$7*100 -> 0.81016039 | S23: =I23/I$7*100 -> 1.2309096 | T23: =J23/J$7*100 -> 1.2795818 | V23: -5.7720058 | W23: =(C23-B23)/B23*100 -> 70.188872 | X23: =(D23-C23)/C23*100 -> -7.2885423 | Y23: =(E23-D23)/D23*100 -> 11.274668 | Z23: =(F23-E23)/E23*100 -> 30.484082 | AA23: =(G23-F23)/F23*100 -> -3.0860071 | AB23: =(H23-G23)/G23*100 -> 38.23428 | AC23: =(I23-H23)/H23*100 -> 74.31185 | AD23: =(J23-I23)/I23*100 -> -66.089404 | AE23: ޕޮލޭންޑް
A24: Portugal | B24: 3660 | C24: 4617 | D24: 4916 | E24: 5057 | F24: 6259 | G24: 6882 | H24: 8342 | I24: 11428 | J24: 3206 | L24: =B24/B$7*100 -> 0.38203596 | M24: =C24/C$7*100 -> 0.41032632 | N24: =D24/D$7*100 -> 0.40801523 | O24: =E24/E$7*100 -> 0.40972317 | P24: =F24/F$7*100 -> 0.48665187 | Q24: =G24/G$7*100 -> 0.4952711 | R24: =H24/H$7*100 -> 0.56202561 | S24: =I24/I$7*100 -> 0.67109562 | T24: =J24/J$7*100 -> 0.57714395 | V24: -17.456022 | W24: =(C24-B24)/B24*100 -> 26.147541 | X24: =(D24-C24)/C24*100 -> 6.4760667 | Y24: =(E24-D24)/D24*100 -> 2.8681855 | Z24: =(F24-E24)/E24*100 -> 23.769033 | AA24: =(G24-F24)/F24*100 -> 9.9536667 | AB24: =(H24-G24)/G24*100 -> 21.214763 | AC24: =(I24-H24)/H24*100 -> 36.993527 | AD24: =(J24-I24)/I24*100 -> -71.946097 | AE24: ޕޯޗުގަލް
A25: Russia | B25: 66378 | C25: 76479 | D25: 66308 | E25: 44323 | F25: 46522 | G25: 61931 | H25: 70935 | I25: 83369 | J25: 61387 | L25: =B25/B$7*100 -> 6.9286292 | M25: =C25/C$7*100 -> 6.7969129 | N25: =D25/D$7*100 -> 5.5033917 | O25: =E25/E$7*100 -> 3.5910935 | P25: =F25/F$7*100 -> 3.6171942 | Q25: =G25/G$7*100 -> 4.4569362 | R25: =H25/H$7*100 -> 4.7791041 | S25: =I25/I$7*100 -> 4.8957447 | T25: =J25/J$7*100 -> 11.050884 | V25: 3.8194444 | W25: =(C25-B25)/B25*100 -> 15.217391 | X25: =(D25-C25)/C25*100 -> -13.299076 | Y25: =(E25-D25)/D25*100 -> -33.155879 | Z25: =(F25-E25)/E25*100 -> 4.9613068 | AA25: =(G25-F25)/F25*100 -> 33.121964 | AB25: =(H25-G25)/G25*100 -> 14.538761 | AC25: =(I25-H25)/H25*100 -> 17.528723 | AD25: =(J25-I25)/I25*100 -> -26.367115 | AE25: ރަޝިއާ
A26: Slovakia | B26: 2636 | C26: 2758 | D26: 3262 | E26: 4286 | F26: 4957 | G26: 6079 | H26: 6584 | I26: 6910 | J26: 4498 | L26: =B26/B$7*100 -> 0.2751494 | M26: =C26/C$7*100 -> 0.24511154 | N26: =D26/D$7*100 -> 0.27073752 | O26: =E26/E$7*100 -> 0.34725598 | P26: =F26/F$7*100 -> 0.38541833 | Q26: =G26/G$7*100 -> 0.43748228 | R26: =H26/H$7*100 -> 0.44358387 | S26: =I26/I$7*100 -> 0.40578148 | T26: =J26/J$7*100 -> 0.80972972 | V26: -6.5910702 | W26: =(C26-B26)/B26*100 -> 4.6282246 | X26: =(D26-C26)/C26*100 -> 18.274112 | Y26: =(E26-D26)/D26*100 -> 31.391784 | Z26: =(F26-E26)/E26*100 -> 15.655623 | AA26: =(G26-F26)/F26*100 -> 22.634658 | AB26: =(H26-G26)/G26*100 -> 8.3072874 | AC26: =(I26-H26)/H26*100 -> 4.9513973 | AD26: =(J26-I26)/I26*100 -> -34.905933 | AE26: ސްލޮވޭކިއާ
A27: Slovenia | B27: 1295 | C27: 1243 | D27: 1319 | E27: 1470 | F27: 1548 | G27: 2100 | H27: 3167 | I27: 3693 | J27: 1561 | L27: =B27/B$7*100 -> 0.13517393 | M27: =C27/C$7*100 -> 0.11046905 | N27: =D27/D$7*100 -> 0.10947357 | O27: =E27/E$7*100 -> 0.11910086 | P27: =F27/F$7*100 -> 0.12036062 | Q27: =G27/G$7*100 -> 0.15112893 | R27: =H27/H$7*100 -> 0.21337031 | S27: =I27/I$7*100 -> 0.216867 | T27: =J27/J$7*100 -> 0.28101114 | V27: -19.515227 | W27: =(C27-B27)/B27*100 -> -4.015444 | X27: =(D27-C27)/C27*100 -> 6.1142397 | Y27: =(E27-D27)/D27*100 -> 11.448067 | Z27: =(F27-E27)/E27*100 -> 5.3061224 | AA27: =(G27-F27)/F27*100 -> 35.658915 | AB27: =(H27-G27)/G27*100 -> 50.809524 | AC27: =(I27-H27)/H27*100 -> 16.608778 | AD27: =(J27-I27)/I27*100 -> -57.730842 | AE27: ސްލްވީނިއާ
A28: Spain | B28: 8824 | C28: 11040 | D28: 15230 | E28: 17816 | F28: 23393 | G28: 25843 | H28: 31780 | I28: 36064 | J28: 6778 | L28: =B28/B$7*100 -> 0.92106156 | M28: =C28/C$7*100 -> 0.98115716 | N28: =D28/D$7*100 -> 1.2640504 | O28: =E28/E$7*100 -> 1.44347 | P28: =F28/F$7*100 -> 1.8188604 | Q28: =G28/G$7*100 -> 1.8598214 | R28: =H28/H$7*100 -> 2.1411141 | S28: =I28/I$7*100 -> 2.1178152 | T28: =J28/J$7*100 -> 1.2201752 | V28: -9.1246138 | W28: =(C28-B28)/B28*100 -> 25.113327 | X28: =(D28-C28)/C28*100 -> 37.952899 | Y28: =(E28-D28)/D28*100 -> 16.979645 | Z28: =(F28-E28)/E28*100 -> 31.303323 | AA28: =(G28-F28)/F28*100 -> 10.473218 | AB28: =(H28-G28)/G28*100 -> 22.973339 | AC28: =(I28-H28)/H28*100 -> 13.480176 | AD28: =(J28-I28)/I28*100 -> -81.205634 | AE28: ސްޕެއިން
A29: Sweden | B29: 5230 | C29: 5694 | D29: 7163 | E29: 9138 | F29: 10918 | G29: 13127 | H29: 14988 | I29: 13245 | J29: 5613 | L29: =B29/B$7*100 -> 0.54591477 | M29: =C29/C$7*100 -> 0.50604247 | N29: =D29/D$7*100 -> 0.59451039 | O29: =E29/E$7*100 -> 0.74036984 | P29: =F29/F$7*100 -> 0.8489 | Q29: =G29/G$7*100 -> 0.94469976 | R29: =H29/H$7*100 -> 1.0097866 | S29: =I29/I$7*100 -> 0.77779677 | T29: =J29/J$7*100 -> 1.010452 | V29: 6.8218954 | W29: =(C29-B29)/B29*100 -> 8.8718929 | X29: =(D29-C29)/C29*100 -> 25.799087 | Y29: =(E29-D29)/D29*100 -> 27.572246 | Z29: =(F29-E29)/E29*100 -> 19.479098 | AA29: =(G29-F29)/F29*100 -> 20.232643 | AB29: =(H29-G29)/G29*100 -> 14.176887 | AC29: =(I29-H29)/H29*100 -> -11.629303 | AD29: =(J29-I29)/I29*100 -> -57.621744 | AE29: ސްވިޑްން
A30: Switzerland | B30: 35457 | C30: 34102 | D30: 31497 | E30: 31923 | F30: 31678 | G30: 32651 | H30: 32984 | I30: 33829 | J30: 12517 | L30: =B30/B$7*100 -> 3.7010516 | M30: =C30/C$7*100 -> 3.0307447 | N30: =D30/D$7*100 -> 2.6141692 | O30: =E30/E$7*100 -> 2.5864332 | P30: =F30/F$7*100 -> 2.4630385 | Q30: =G30/G$7*100 -> 2.349767 | R30: =H30/H$7*100 -> 2.2222312 | S30: =I30/I$7*100 -> 1.9865675 | T30: =J30/J$7*100 -> 2.2533097 | V30: 9.0850357 | W30: =(C30-B30)/B30*100 -> -3.8215303 | X30: =(D30-C30)/C30*100 -> -7.6388482 | Y30: =(E30-D30)/D30*100 -> 1.3525098 | Z30: =(F30-E30)/E30*100 -> -0.76747173 | AA30: =(G30-F30)/F30*100 -> 3.0715323 | AB30: =(H30-G30)/G30*100 -> 1.0198769 | AC30: =(I30-H30)/H30*100 -> 2.5618482 | AD30: =(J30-I30)/I30*100 -> -62.999202 | AE30: ސްވިޓްޒަރލޭންޑް
A31: Turkey | B31: 5416 | C31: 9117 | D31: 8668 | E31: 10200 | F31: 10091 | G31: 11168 | H31: 10129 | I31: 9976 | J31: 3164 | L31: =B31/B$7*100 -> 0.56532971 | M31: =C31/C$7*100 -> 0.81025451 | N31: =D31/D$7*100 -> 0.71942147 | O31: =E31/E$7*100 -> 0.82641414 | P31: =F31/F$7*100 -> 0.78459882 | Q31: =G31/G$7*100 -> 0.80371806 | R31: =H31/H$7*100 -> 0.68242117 | S31: =I31/I$7*100 -> 0.58582865 | T31: =J31/J$7*100 -> 0.56958311 | V31: 19.242624 | W31: =(C31-B31)/B31*100 -> 68.334564 | X31: =(D31-C31)/C31*100 -> -4.9248656 | Y31: =(E31-D31)/D31*100 -> 17.674204 | Z31: =(F31-E31)/E31*100 -> -1.0686275 | AA31: =(G31-F31)/F31*100 -> 10.672877 | AB31: =(H31-G31)/G31*100 -> -9.3033668 | AC31: =(I31-H31)/H31*100 -> -1.5105144 | AD31: =(J31-I31)/I31*100 -> -68.283881 | AE31: ޓަރކީ
... A34: Other Europe | B34: 18612 | C34: 18036 | D34: 17044 | E34: 23361 | F34: 26943 | G34: 33356 | H34: 37628 | I34: 43424 | J34: 28890 | L34: =B34/B$7*100 -> 1.9427468 | M34: =C34/C$7*100 -> 1.6029122 | N34: =D34/D$7*100 -> 1.4146077 | O34: =E34/E$7*100 -> 1.8927314 | P34: =F34/F$7*100 -> 2.0948812 | Q34: =G34/G$7*100 -> 2.4005032 | R34: =H34/H$7*100 -> 2.5351114 | S34: =I34/I$7*100 -> 2.5500224 | T34: =J34/J$7*100 -> 5.2007762 | V34: 53.97088 | W34: =(C34-B34)/B34*100 -> -3.0947776 | X34: =(D34-C34)/C34*100 -> -5.5001109 | Y34: =(E34-D34)/D34*100 -> 37.062896 | Z34: =(F34-E34)/E34*100 -> 15.333248 | AA34: =(G34-F34)/F34*100 -> 23.802101 | AB34: =(H34-G34)/G34*100 -> 12.807291 | AC34: =(I34-H34)/H34*100 -> 15.403423 | AD34: =(J34-I34)/I34*100 -> -33.469971 | AE34: އެހެނިހެން
A35: Asia | B35: =SUM(B36:B49) -> 367680 | C35: =SUM(C36:C49) -> 505753 | D35: =SUM(D36:D49) -> 568031 | E35: =SUM(E36:E49) -> 578322 | F35: =SUM(F36:F49) -> 572336 | G35: =SUM(G36:G49) -> 586791 | H35: =SUM(H36:H49) -> 580928 | I35: =SUM(I36:I49) -> 661000 | J35: =SUM(J36:J49) -> 134279 | L35: =B35/B$7*100 -> 38.378957 | M35: =C35/C$7*100 -> 44.947752 | N35: =D35/D$7*100 -> 47.145097 | O35: =E35/E$7*100 -> 46.856223 | P35: =F35/F$7*100 -> 44.500461 | Q35: =G35/G$7*100 -> 42.229094 | R35: =H35/H$7*100 -> 39.138865 | S35: =I35/I$7*100 -> 38.816434 | T35: =J35/J$7*100 -> 24.172898 | V35: 9.856226 | W35: =(C35-B35)/B35*100 -> 37.552491 | X35: =(D35-C35)/C35*100 -> 12.313916 | Y35: =(E35-D35)/D35*100 -> 1.8116969 | Z35: =(F35-E35)/E35*100 -> -1.0350635 | AA35: =(G35-F35)/F35*100 -> 2.5256143 | AB35: =(H35-G35)/G35*100 -> -0.99916325 | AC35: =(I35-H35)/H35*100 -> 13.783464 | AD35: =(J35-I35)/I35*100 -> -79.685477 | AE35: އޭޝިއާ
A36: Bangladesh | B36: 1221 | C36: 1906 | D36: 2231 | E36: 4431 | F36: 6018 | G36: 4714 | H36: 3644 | I36: 3918 | J36: 1108 | L36: =B36/B$7*100 -> 0.1274497 | M36: =C36/C$7*100 -> 0.16939181 | N36: =D36/D$7*100 -> 0.1851672 | O36: =E36/E$7*100 -> 0.35900403 | P36: =F36/F$7*100 -> 0.46791355 | Q36: =G36/G$7*100 -> 0.33924847 | R36: =H36/H$7*100 -> 0.24550723 | S36: =I36/I$7*100 -> 0.23007986 | T36: =J36/J$7*100 -> 0.1994621 | V36: -18.382353 | W36: =(C36-B36)/B36*100 -> 56.101556 | X36: =(D36-C36)/C36*100 -> 17.051417 | Y36: =(E36-D36)/D36*100 -> 98.610489 | Z36: =(F36-E36)/E36*100 -> 35.815843 | AA36: =(G36-F36)/F36*100 -> -21.668328 | AB36: =(H36-G36)/G36*100 -> -22.698345 | AC36: =(I36-H36)/H36*100 -> 7.5192097 | AD36: =(J36-I36)/I36*100 -> -71.720265 | AE36: ބަންގްލަދޭޝް
A37: China | B37: 229551 | C37: 331719 | D37: 363626 | E37: 359514 | F37: 324326 | G37: 306530 | H37: 283116 | I37: 284029 | J37: 34245 | L37: =B37/B$7*100 -> 23.960857 | M37: =C37/C$7*100 -> 29.48084 | N37: =D37/D$7*100 -> 30.180013 | O37: =E37/E$7*100 -> 29.128182 | P37: =F37/F$7*100 -> 25.217104 | Q37: =G37/G$7*100 -> 22.059787 | R37: =H37/H$7*100 -> 19.074376 | S37: =I37/I$7*100 -> 16.679263 | T37: =J37/J$7*100 -> 6.1647831 | V37: 15.552591 | W37: =(C37-B37)/B37*100 -> 44.507756 | X37: =(D37-C37)/C37*100 -> 9.6186833 | Y37: =(E37-D37)/D37*100 -> -1.1308322 | Z37: =(F37-E37)/E37*100 -> -9.7876578 | AA37: =(G37-F37)/F37*100 -> -5.4870717 | AB37: =(H37-G37)/G37*100 -> -7.6384041 | AC37: =(I37-H37)/H37*100 -> 0.32248266 | AD37: =(J37-I37)/I37*100 -> -87.943133 | AE37: ޗައިނާ
A38: India | B38: 31721 | C38: 38014 | D38: 45587 | E38: 52368 | F38: 66955 | G38: 83019 | H38: 90474 | I38: 166030 | J38: 62960 | L38: =B38/B$7*100 -> 3.3110827 | M38: =C38/C$7*100 -> 3.3784156 | N38: =D38/D$7*100 -> 3.7836025 | O38: =E38/E$7*100 -> 4.2429074 | P38: =F38/F$7*100 -> 5.2059076 | Q38: =G38/G$7*100 -> 5.9745585 | R38: =H38/H$7*100 -> 6.0955053 | S38: =I38/I$7*100 -> 9.7499129 | T38: =J38/J$7*100 -> 11.334056 | V38: 2.3984763 | W38: =(C38-B38)/B38*100 -> 19.838593 | X38: =(D38-C38)/C38*100 -> 19.921608 | Y38: =(E38-D38)/D38*100 -> 14.874855 | Z38: =(F38-E38)/E38*100 -> 27.854797 | AA38: =(G38-F38)/F38*100 -> 23.992234 | AB38: =(H38-G38)/G38*100 -> 8.9798721 | AC38: =(I38-H38)/H38*100 -> 83.511285 | AD38: =(J38-I38)/I38*100 -> -62.079142 | AE38: އިންޑިއާ
A39: Indonesia | B39: 1772 | C39: 2511 | D39: 3333 | E39: 3452 | F39: 4886 | G39: 5375 | H39: 5885 | I39: 4646 | J39: 857 | L39: =B39/B$7*100 -> 0.18496386 | M39: =C39/C$7*100 -> 0.22315993 | N39: =D39/D$7*100 -> 0.27663034 | O39: =E39/E$7*100 -> 0.27968447 | P39: =F39/F$7*100 -> 0.37989791 | Q39: =G39/G$7*100 -> 0.3868181 | R39: =H39/H$7*100 -> 0.39649014 | S39: =I39/I$7*100 -> 0.27283079 | T39: =J39/J$7*100 -> 0.15427709 | V39: 38.113796 | W39: =(C39-B39)/B39*100 -> 41.704289 | X39: =(D39-C39)/C39*100 -> 32.735962 | Y39: =(E39-D39)/D39*100 -> 3.570357 | Z39: =(F39-E39)/E39*100 -> 41.541136 | AA39: =(G39-F39)/F39*100 -> 10.008187 | AB39: =(H39-G39)/G39*100 -> 9.4883721 | AC39: =(I39-H39)/H39*100 -> -21.053526 | AD39: =(J39-I39)/I39*100 -> -81.554025 | AE39: އިންޑޮނޭޝިއާ
A40: Japan | B40: 36438 | C40: 39463 | D40: 38817 | E40: 39244 | F40: 39894 | G40: 41133 | H40: 42304 | I40: 44251 | J40: 8479 | L40: =B40/B$7*100 -> 3.8034498 | M40: =C40/C$7*100 -> 3.5071925 | N40: =D40/D$7*100 -> 3.2217101 | O40: =E40/E$7*100 -> 3.1795879 | P40: =F40/F$7*100 -> 3.1018517 | Q40: =G40/G$7*100 -> 2.960184 | R40: =H40/H$7*100 -> 2.8501476 | S40: =I40/I$7*100 -> 2.598587 | T40: =J40/J$7*100 -> 1.5263891 | V40: 1.833324 | W40: =(C40-B40)/B40*100 -> 8.3017729 | X40: =(D40-C40)/C40*100 -> -1.6369764 | Y40: =(E40-D40)/D40*100 -> 1.1000335 | Z40: =(F40-E40)/E40*100 -> 1.6563041 | AA40: =(G40-F40)/F40*100 -> 3.1057302 | AB40: =(H40-G40)/G40*100 -> 2.8468626 | AC40: =(I40-H40)/H40*100 -> 4.6024017 | AD40: =(J40-I40)/I40*100 -> -80.838851 | AE40: ޖަޕާން
A41: Korea | B41: 23933 | C41: 30306 | D41: 34896 | E41: 33001 | F41: 29580 | G41: 34808 | H41: 34400 | I41: 37073 | J41: 5895 | L41: =B41/B$7*100 -> 2.4981603 | M41: =C41/C$7*100 -> 2.6933831 | N41: =D41/D$7*100 -> 2.8962773 | O41: =E41/E$7*100 -> 2.6737738 | P41: =F41/F$7*100 -> 2.2999141 | Q41: =G41/G$7*100 -> 2.504998 | R41: =H41/H$7*100 -> 2.3176314 | S41: =I41/I$7*100 -> 2.1770675 | T41: =J41/J$7*100 -> 1.0612176 | V41: -5.3470437 | W41: =(C41-B41)/B41*100 -> 26.628505 | X41: =(D41-C41)/C41*100 -> 15.145516 | Y41: =(E41-D41)/D41*100 -> -5.4304218 | Z41: =(F41-E41)/E41*100 -> -10.366353 | AA41: =(G41-F41)/F41*100 -> 17.674104 | AB41: =(H41-G41)/G41*100 -> -1.1721443 | AC41: =(I41-H41)/H41*100 -> 7.7703488 | AD41: =(J41-I41)/I41*100 -> -84.09894 | AE41: ކޮރެއާ
A42: Malaysia | B42: 6766 | C42: 10875 | D42: 13457 | E42: 12575 | F42: 16185 | G42: 19092 | H42: 22202 | I42: 21605 | J42: 2946 | L42: =B42/B$7*100 -> 0.70624462 | M42: =C42/C$7*100 -> 0.96649313 | N42: =D42/D$7*100 -> 1.116896 | O42: =E42/E$7*100 -> 1.018839 | P42: =F42/F$7*100 -> 1.2584215 | Q42: =G42/G$7*100 -> 1.3739779 | R42: =H42/H$7*100 -> 1.4958155 | S42: =I42/I$7*100 -> 1.2687278 | T42: =J42/J$7*100 -> 0.53033876 | V42: 11.742362 | W42: =(C42-B42)/B42*100 -> 60.730121 | X42: =(D42-C42)/C42*100 -> 23.742529 | Y42: =(E42-D42)/D42*100 -> -6.5542097 | Z42: =(F42-E42)/E42*100 -> 28.707753 | AA42: =(G42-F42)/F42*100 -> 17.961075 | AB42: =(H42-G42)/G42*100 -> 16.289545 | AC42: =(I42-H42)/H42*100 -> -2.6889469 | AD42: =(J42-I42)/I42*100 -> -86.364268 | AE42: މެލޭޝިއާ
A43: Pakistan | B43: 1857 | C43: 2693 | D43: 3105 | E43: 3987 | F43: 6251 | G43: 6241 | H43: 5340 | I43: 6095 | J43: 2882 | L43: =B43/B$7*100 -> 0.19383628 | M43: =C43/C$7*100 -> 0.2393348 | N43: =D43/D$7*100 -> 0.25770693 | O43: =E43/E$7*100 -> 0.3230307 | P43: =F43/F$7*100 -> 0.48602985 | Q43: =G43/G$7*100 -> 0.4491408 | R43: =H43/H$7*100 -> 0.35977185 | S43: =I43/I$7*100 -> 0.35792158 | T43: =J43/J$7*100 -> 0.51881748 | V43: 0.81433225 | W43: =(C43-B43)/B43*100 -> 45.018848 | X43: =(D43-C43)/C43*100 -> 15.298923 | Y43: =(E43-D43)/D43*100 -> 28.405797 | Z43: =(F43-E43)/E43*100 -> 56.78455 | AA43: =(G43-F43)/F43*100 -> -0.1599744 | AB43: =(H43-G43)/G43*100 -> -14.436789 | AC43: =(I43-H43)/H43*100 -> 14.138577 | AD43: =(J43-I43)/I43*100 -> -52.71534 | AE43: ޕާކިސްތާން
A44: Philippines | B44: 2265 | C44: 3040 | D44: 5406 | E44: 6907 | F44: 9551 | G44: 10532 | H44: 11035 | I44: 8461 | J44: 1756 | L44: =B44/B$7*100 -> 0.23642389 | M44: =C44/C$7*100 -> 0.27017371 | N44: =D44/D$7*100 -> 0.44868395 | O44: =E44/E$7*100 -> 0.55961201 | P44: =F44/F$7*100 -> 0.74261256 | Q44: =G44/G$7*100 -> 0.75794758 | R44: =H44/H$7*100 -> 0.74346111 | S44: =I44/I$7*100 -> 0.49686209 | T44: =J44/J$7*100 -> 0.31611503 | V44: 37.106538 | W44: =(C44-B44)/B44*100 -> 34.216336 | X44: =(D44-C44)/C44*100 -> 77.828947 | Y44: =(E44-D44)/D44*100 -> 27.765446 | Z44: =(F44-E44)/E44*100 -> 38.280006 | AA44: =(G44-F44)/F44*100 -> 10.271176 | AB44: =(H44-G44)/G44*100 -> 4.775921 | AC44: =(I44-H44)/H44*100 -> -23.325782 | AD44: =(J44-I44)/I44*100 -> -79.245952 | AE44: ފިލިޕީންސް
A45: Singapore | B45: 9625 | C45: 11143 | D45: 18638 | E45: 15881 | F45: 14782 | G45: 14502 | H45: 13877 | I45: 14990 | J45: 2117 | L45: =B45/B$7*100 -> 1.0046711 | M45: =C45/C$7*100 -> 0.99031107 | N45: =D45/D$7*100 -> 1.5469056 | O45: =E45/E$7*100 -> 1.2866944 | P45: =F45/F$7*100 -> 1.149335 | Q45: =G45/G$7*100 -> 1.0436532 | R45: =H45/H$7*100 -> 0.93493519 | S45: =I45/I$7*100 -> 0.8802698 | T45: =J45/J$7*100 -> 0.38110223 | V45: 20.463079 | W45: =(C45-B45)/B45*100 -> 15.771429 | X45: =(D45-C45)/C45*100 -> 67.261958 | Y45: =(E45-D45)/D45*100 -> -14.79236 | Z45: =(F45-E45)/E45*100 -> -6.9202191 | AA45: =(G45-F45)/F45*100 -> -1.8941956 | AB45: =(H45-G45)/G45*100 -> -4.3097504 | AC45: =(I45-H45)/H45*100 -> 8.0204655 | AD45: =(J45-I45)/I45*100 -> -85.877252 | AE45: ސިންގަޕޯރ
A46: Sri Lanka | B46: 8860 | C46: 12400 | D46: 13753 | E46: 14153 | F46: 17927 | G46: 14070 | H46: 12792 | I46: 13623 | J46: 2271 | L46: =B46/B$7*100 -> 0.92481929 | M46: =C46/C$7*100 -> 1.1020243 | N46: =D46/D$7*100 -> 1.1414633 | O46: =E46/E$7*100 -> 1.1466901 | P46: =F46/F$7*100 -> 1.3938661 | Q46: =G46/G$7*100 -> 1.0125639 | R46: =H46/H$7*100 -> 0.86183548 | S46: =I46/I$7*100 -> 0.79999436 | T46: =J46/J$7*100 -> 0.4088253 | V46: -8.3764219 | W46: =(C46-B46)/B46*100 -> 39.954853 | X46: =(D46-C46)/C46*100 -> 10.91129 | Y46: =(E46-D46)/D46*100 -> 2.9084563 | Z46: =(F46-E46)/E46*100 -> 26.665725 | AA46: =(G46-F46)/F46*100 -> -21.515033 | AB46: =(H46-G46)/G46*100 -> -9.0831557 | AC46: =(I46-H46)/H46*100 -> 6.4962477 | AD46: =(J46-I46)/I46*100 -> -83.329663 | AE46: ސްރީލަންކާ
A47: Taiwan | B47: 4430 | C47: 6522 | D47: 7341 | E47: 9177 | F47: 9505 | G47: 10326 | H47: 12439 | I47: 14972 | J47: 2628 | L47: =B47/B$7*100 -> 0.46240964 | M47: =C47/C$7*100 -> 0.57962926 | N47: =D47/D$7*100 -> 0.60928392 | O47: =E47/E$7*100 -> 0.74352966 | P47: =F47/F$7*100 -> 0.73903595 | Q47: =G47/G$7*100 -> 0.74312255 | R47: =H47/H$7*100 -> 0.83805281 | S47: =I47/I$7*100 -> 0.87921277 | T47: =J47/J$7*100 -> 0.47309242 | V47: -16.493874 | W47: =(C47-B47)/B47*100 -> 47.223476 | X47: =(D47-C47)/C47*100 -> 12.557498 | Y47: =(E47-D47)/D47*100 -> 25.010217 | Z47: =(F47-E47)/E47*100 -> 3.5741528 | AA47: =(G47-F47)/F47*100 -> 8.6375592 | AB47: =(H47-G47)/G47*100 -> 20.462909 | AC47: =(I47-H47)/H47*100 -> 20.363373 | AD47: =(J47-I47)/I47*100 -> -82.447235 | AE47: ޓައިވާން
... A49: Other Asia | B49: 2345 | C49: 3456 | D49: 5560 | E49: 7722 | F49: 10025 | G49: 10412 | H49: 10984 | I49: 12096 | J49: 2667 | L49: =B49/B$7*100 -> 0.24477441 | M49: =C49/C$7*100 -> 0.30714485 | N49: =D49/D$7*100 -> 0.46146555 | O49: =E49/E$7*100 -> 0.62564412 | P49: =F49/F$7*100 -> 0.77946716 | Q49: =G49/G$7*100 -> 0.74931164 | R49: =H49/H$7*100 -> 0.74002509 | S49: =I49/I$7*100 -> 0.71032312 | T49: =J49/J$7*100 -> 0.4801132 | V49: -5.6338028 | W49: =(C49-B49)/B49*100 -> 47.377399 | X49: =(D49-C49)/C49*100 -> 60.87963 | Y49: =(E49-D49)/D49*100 -> 38.884892 | Z49: =(F49-E49)/E49*100 -> 29.82388 | AA49: =(G49-F49)/F49*100 -> 3.8603491 | AB49: =(H49-G49)/G49*100 -> 5.4936612 | AC49: =(I49-H49)/H49*100 -> 10.123816 | AD49: =(J49-I49)/I49*100 -> -77.951389 | AE49: އެހެނިހެން
A50: Africa | B50: =SUM(B51:B52) -> 7095 | C50: =SUM(C51:C52) -> 8271 | D50: =SUM(D51:D52) -> 8149 | E50: =SUM(E51:E52) -> 9276 | F50: =SUM(F51:F52) -> 10752 | G50: =SUM(G51:G52) -> 14674 | H50: =SUM(H51:H52) -> 15354 | I50: =SUM(I51:I52) -> 18695 | J50: =SUM(J51:J52) -> 6458 | L50: =B50/B$7*100 -> 0.7405861 | M50: =C50/C$7*100 -> 0.73506801 | N50: =D50/D$7*100 -> 0.67634582 | O50: =E50/E$7*100 -> 0.75155074 | P50: =F50/F$7*100 -> 0.83599311 | Q50: =G50/G$7*100 -> 1.0560314 | R50: =H50/H$7*100 -> 1.0344451 | S50: =I50/I$7*100 -> 1.0978415 | T50: =J50/J$7*100 -> 1.1625688 | V50: 9.7447796 | W50: =(C50-B50)/B50*100 -> 16.575053 | X50: =(D50-C50)/C50*100 -> -1.4750332 | Y50: =(E50-D50)/D50*100 -> 13.829918 | Z50: =(F50-E50)/E50*100 -> 15.912031 | AA50: =(G50-F50)/F50*100 -> 36.476935 | AB50: =(H50-G50)/G50*100 -> 4.6340466 | AC50: =(I50-H50)/H50*100 -> 21.759802 | AD50: =(J50-I50)/I50*100 -> -65.456004 | AE50: އެފްރިކާ
A51: South Africa | B51: 3967 | C51: 4503 | D51: 3699 | E51: 4170 | F51: 4656 | G51: 7050 | H51: 7751 | I51: 9545 | J51: 2685 | L51: =B51/B$7*100 -> 0.41408105 | M51: =C51/C$7*100 -> 0.40019481 | N51: =D51/D$7*100 -> 0.30700739 | O51: =E51/E$7*100 -> 0.33785755 | P51: =F51/F$7*100 -> 0.36201487 | Q51: =G51/G$7*100 -> 0.50736142 | R51: =H51/H$7*100 -> 0.52220816 | S51: =I51/I$7*100 -> 0.5605187 | T51: =J51/J$7*100 -> 0.48335356 | V51: 7.6818675 | W51: =(C51-B51)/B51*100 -> 13.51147 | X51: =(D51-C51)/C51*100 -> -17.854763 | Y51: =(E51-D51)/D51*100 -> 12.733171 | Z51: =(F51-E51)/E51*100 -> 11.654676 | AA51: =(G51-F51)/F51*100 -> 51.417526 | AB51: =(H51-G51)/G51*100 -> 9.9432624 | AC51: =(I51-H51)/H51*100 -> 23.145401 | AD51: =(J51-I51)/I51*100 -> -71.870089 | AE51: ސައުތު އެފްރިކާ
A52: Other Africa | B52: 3128 | C52: 3768 | D52: 4450 | E52: 5106 | F52: 6096 | G52: 7624 | H52: 7603 | I52: 9150 | J52: 3773 | L52: =B52/B$7*100 -> 0.32650505 | M52: =C52/C$7*100 -> 0.3348732 | N52: =D52/D$7*100 -> 0.36933844 | O52: =E52/E$7*100 -> 0.4136932 | P52: =F52/F$7*100 -> 0.47397824 | Q52: =G52/G$7*100 -> 0.54866999 | R52: =H52/H$7*100 -> 0.51223696 | S52: =I52/I$7*100 -> 0.53732279 | T52: =J52/J$7*100 -> 0.67921526 | V52: 12.477526 | W52: =(C52-B52)/B52*100 -> 20.460358 | X52: =(D52-C52)/C52*100 -> 18.099788 | Y52: =(E52-D52)/D52*100 -> 14.741573 | Z52: =(F52-E52)/E52*100 -> 19.388954 | AA52: =(G52-F52)/F52*100 -> 25.065617 | AB52: =(H52-G52)/G52*100 -> -0.27544596 | AC52: =(I52-H52)/H52*100 -> 20.347231 | AD52: =(J52-I52)/I52*100 -> -58.765027 | AE52: އެހެނިހެން
A53: Americas | B53: =SUM(B54:B57) -> 26774 | C53: =SUM(C54:C57) -> 32970 | D53: =SUM(D54:D57) -> 41044 | E53: =SUM(E54:E57) -> 46602 | F53: =SUM(F54:F57) -> 50458 | G53: =SUM(G54:G57) -> 61973 | H53: =SUM(H54:H57) -> 68764 | I53: =SUM(I54:I57) -> 84794 | J53: =SUM(J54:J57) -> 32060 | L53: =B53/B$7*100 -> 2.7947079 | M53: =C53/C$7*100 -> 2.9301405 | N53: =D53/D$7*100 -> 3.4065453 | O53: =E53/E$7*100 -> 3.7757404 | P53: =F53/F$7*100 -> 3.9232273 | Q53: =G53/G$7*100 -> 4.4599587 | R53: =H53/H$7*100 -> 4.6328373 | S53: =I53/I$7*100 -> 4.9794261 | T53: =J53/J$7*100 -> 5.7714395 | V53: 13.190158 | W53: =(C53-B53)/B53*100 -> 23.141854 | X53: =(D53-C53)/C53*100 -> 24.488929 | Y53: =(E53-D53)/D53*100 -> 13.541565 | Z53: =(F53-E53)/E53*100 -> 8.274323 | AA53: =(G53-F53)/F53*100 -> 22.82096 | AB53: =(H53-G53)/G53*100 -> 10.957998 | AC53: =(I53-H53)/H53*100 -> 23.311617 | AD53: =(J53-I53)/I53*100 -> -62.190721 | AE53: އެމެރިކާސް
A54: Brazil | B54: 3061 | C54: 3675 | D54: 4321 | E54: 5082 | F54: 5015 | G54: 7064 | H54: 7702 | I54: 9868 | J54: 5497 | L54: =B54/B$7*100 -> 0.3195115 | M54: =C54/C$7*100 -> 0.32660802 | N54: =D54/D$7*100 -> 0.35863177 | O54: =E54/E$7*100 -> 0.41174869 | P54: =F54/F$7*100 -> 0.38992796 | Q54: =G54/G$7*100 -> 0.50836894 | R54: =H54/H$7*100 -> 0.51890689 | S54: =I54/I$7*100 -> 0.57948648 | T54: =J54/J$7*100 -> 0.98956964 | V54: 30.700256 | W54: =(C54-B54)/B54*100 -> 20.058804 | X54: =(D54-C54)/C54*100 -> 17.578231 | Y54: =(E54-D54)/D54*100 -> 17.611664 | Z54: =(F54-E54)/E54*100 -> -1.3183786 | AA54: =(G54-F54)/F54*100 -> 40.857428 | AB54: =(H54-G54)/G54*100 -> 9.0317101 | AC54: =(I54-H54)/H54*100 -> 28.122566 | AD54: =(J54-I54)/I54*100 -> -44.29469 | AE54: ބްރެޒީލް
A55: Canada | B55: 5070 | C55: 6098 | D55: 7435 | E55: 7537 | F55: 7628 | G55: 8994 | H55: 9540 | I55: 11473 | J55: 3872 | L55: =B55/B$7*100 -> 0.52921375 | M55: =C55/C$7*100 -> 0.54194713 | N55: =D55/D$7*100 -> 0.61708568 | O55: =E55/E$7*100 -> 0.61065523 | P55: =F55/F$7*100 -> 0.59309482 | Q55: =G55/G$7*100 -> 0.64726363 | R55: =H55/H$7*100 -> 0.64273847 | S55: =I55/I$7*100 -> 0.67373819 | T55: =J55/J$7*100 -> 0.69703723 | V55: 8.1023454 | W55: =(C55-B55)/B55*100 -> 20.276134 | X55: =(D55-C55)/C55*100 -> 21.925221 | Y55: =(E55-D55)/D55*100 -> 1.3718897 | Z55: =(F55-E55)/E55*100 -> 1.2073769 | AA55: =(G55-F55)/F55*100 -> 17.907708 | AB55: =(H55-G55)/G55*100 -> 6.0707138 | AC55: =(I55-H55)/H55*100 -> 20.262055 | AD55: =(J55-I55)/I55*100 -> -66.251198 | AE55: ކެނެޑާ
A56: U.S.A | B56: 16049 | C56: 20034 | D56: 25641 | E56: 29308 | F56: 32589 | G56: 39180 | H56: 42901 | I56: 54474 | J56: 19759 | L56: =B56/B$7*100 -> 1.6752172 | M56: =C56/C$7*100 -> 1.7804803 | N56: =D56/D$7*100 -> 2.1281364 | O56: =E56/E$7*100 -> 2.3745633 | P56: =F56/F$7*100 -> 2.5338709 | Q56: =G56/G$7*100 -> 2.8196341 | R56: =H56/H$7*100 -> 2.8903693 | S56: =I56/I$7*100 -> 3.1989204 | T56: =J56/J$7*100 -> 3.5570141 | V56: 10.759144 | W56: =(C56-B56)/B56*100 -> 24.830207 | X56: =(D56-C56)/C56*100 -> 27.987421 | Y56: =(E56-D56)/D56*100 -> 14.301314 | Z56: =(F56-E56)/E56*100 -> 11.194896 | AA56: =(G56-F56)/F56*100 -> 20.224616 | AB56: =(H56-G56)/G56*100 -> 9.4971924 | AC56: =(I56-H56)/H56*100 -> 26.976061 | AD56: =(J56-I56)/I56*100 -> -63.72765 | AE56: ޔޫ.އެސް.އޭ
A57: Other Americas | B57: 2594 | C57: 3163 | D57: 3647 | E57: 4675 | F57: 5226 | G57: 6735 | H57: 8621 | I57: 8979 | J57: 2932 | L57: =B57/B$7*100 -> 0.27076538 | M57: =C57/C$7*100 -> 0.28110508 | N57: =D57/D$7*100 -> 0.30269152 | O57: =E57/E$7*100 -> 0.37877315 | P57: =F57/F$7*100 -> 0.40633371 | Q57: =G57/G$7*100 -> 0.48469208 | R57: =H57/H$7*100 -> 0.58082268 | S57: =I57/I$7*100 -> 0.52728102 | T57: =J57/J$7*100 -> 0.52781848 | V57: 21.669794 | W57: =(C57-B57)/B57*100 -> 21.935235 | X57: =(D57-C57)/C57*100 -> 15.301929 | Y57: =(E57-D57)/D57*100 -> 28.187551 | Z57: =(F57-E57)/E57*100 -> 11.786096 | AA57: =(G57-F57)/F57*100 -> 28.874856 | AB57: =(H57-G57)/G57*100 -> 28.00297 | AC57: =(I57-H57)/H57*100 -> 4.1526505 | AD57: =(J57-I57)/I57*100 -> -67.34603 | AE57: އެހެނިހެން
A58: Oceania | B58: =SUM(B59:B61) -> 16826 | C58: =SUM(C59:C61) -> 18761 | D58: =SUM(D59:D61) -> 20814 | E58: =SUM(E59:E61) -> 21777 | F58: =SUM(F59:F61) -> 25708 | G58: =SUM(G59:G61) -> 30332 | H58: =SUM(H59:H61) -> 40510 | I58: =SUM(I59:I61) -> 44140 | J58: =SUM(J59:J61) -> 7964 | L58: =B58/B$7*100 -> 1.7563216 | M58: =C58/C$7*100 -> 1.6673451 | N58: =D58/D$7*100 -> 1.7275079 | O58: =E58/E$7*100 -> 1.7643942 | P58: =F58/F$7*100 -> 1.998857 | Q58: =G58/G$7*100 -> 2.1828775 | R58: =H58/H$7*100 -> 2.7292804 | S58: =I58/I$7*100 -> 2.5920686 | T58: =J58/J$7*100 -> 1.4336789 | V58: 18.534695 | W58: =(C58-B58)/B58*100 -> 11.500059 | X58: =(D58-C58)/C58*100 -> 10.942913 | Y58: =(E58-D58)/D58*100 -> 4.6266936 | Z58: =(F58-E58)/E58*100 -> 18.051155 | AA58: =(G58-F58)/F58*100 -> 17.986619 | AB58: =(H58-G58)/G58*100 -> 33.555321 | AC58: =(I58-H58)/H58*100 -> 8.9607504 | AD58: =(J58-I58)/I58*100 -> -81.957408 | AE58: އޯޝޭނިއާ
A59: Australia | B59: 15208 | C59: 16915 | D59: 18872 | E59: 19733 | F59: 23584 | G59: 27360 | H59: 37254 | I59: 39928 | J59: 7220 | L59: =B59/B$7*100 -> 1.5874325 | M59: =C59/C$7*100 -> 1.5032856 | N59: =D59/D$7*100 -> 1.566327 | O59: =E59/E$7*100 -> 1.5987873 | P59: =F59/F$7*100 -> 1.8337111 | Q59: =G59/G$7*100 -> 1.9689941 | R59: =H59/H$7*100 -> 2.5099139 | S59: =I59/I$7*100 -> 2.344724 | T59: =J59/J$7*100 -> 1.299744 | V59: 19.017061 | W59: =(C59-B59)/B59*100 -> 11.224356 | X59: =(D59-C59)/C59*100 -> 11.569613 | Y59: =(E59-D59)/D59*100 -> 4.5623145 | Z59: =(F59-E59)/E59*100 -> 19.515532 | AA59: =(G59-F59)/F59*100 -> 16.010855 | AB59: =(H59-G59)/G59*100 -> 36.162281 | AC59: =(I59-H59)/H59*100 -> 7.1777527 | AD59: =(J59-I59)/I59*100 -> -81.917451 | AE59: އޮސްޓްރޭލިއާ
A60: New Zealand | B60: 1579 | C60: 1791 | D60: 1916 | E60: 1978 | F60: 2087 | G60: 2877 | H60: 3200 | I60: 4082 | J60: 719 | L60: =B60/B$7*100 -> 0.16481825 | M60: =C60/C$7*100 -> 0.15917142 | N60: =D60/D$7*100 -> 0.15902302 | O60: =E60/E$7*100 -> 0.16025953 | P60: =F60/F$7*100 -> 0.16226912 | Q60: =G60/G$7*100 -> 0.20704664 | R60: =H60/H$7*100 -> 0.21559362 | S60: =I60/I$7*100 -> 0.23971056 | T60: =J60/J$7*100 -> 0.12943434 | V60: 13.597122 | W60: =(C60-B60)/B60*100 -> 13.426219 | X60: =(D60-C60)/C60*100 -> 6.9793412 | Y60: =(E60-D60)/D60*100 -> 3.2359081 | Z60: =(F60-E60)/E60*100 -> 5.5106168 | AA60: =(G60-F60)/F60*100 -> 37.853378 | AB60: =(H60-G60)/G60*100 -> 11.226973 | AC60: =(I60-H60)/H60*100 -> 27.5625 | AD60: =(J60-I60)/I60*100 -> -82.386085 | AE60: ނިއުޒީލޭންޑް
A61: Other Oceania | B61: 39 | C61: 55 | D61: 26 | E61: 66 | F61: 37 | G61: 95 | H61: 56 | I61: 130 | J61: 25 | L61: =B61/B$7*100 -> 0.004070875 | M61: =C61/C$7*100 -> 0.0048880112 | N61: =D61/D$7*100 -> 0.0021579324 | O61: =E61/E$7*100 -> 0.0053473856 | P61: =F61/F$7*100 -> 0.0028768364 | Q61: =G61/G$7*100 -> 0.0068367851 | R61: =H61/H$7*100 -> 0.0037728883 | S61: =I61/I$7*100 -> 0.0076340943 | T61: =J61/J$7*100 -> 0.0045004987 | V61: 44.444444 | W61: =(C61-B61)/B61*100 -> 41.025641 | X61: =(D61-C61)/C61*100 -> -52.727273 | Y61: =(E61-D61)/D61*100 -> 153.84615 | Z61: =(F61-E61)/E61*100 -> -43.939394 | AA61: =(G61-F61)/F61*100 -> 156.75676 | AB61: =(H61-G61)/G61*100 -> -41.052632 | AC61: =(I61-H61)/H61*100 -> 132.14286 | AD61: =(J61-I61)/I61*100 -> -80.769231 | AE61: އެހެނިހެން
A62: Middle East | B62: =SUM(B63:B67) -> 21843 | C62: =SUM(C63:C67) -> 32050 | D62: =SUM(D63:D67) -> 37201 | E62: =SUM(E63:E67) -> 41976 | F62: =SUM(F63:F67) -> 51330 | G62: =SUM(G63:G67) -> 49193 | H62: =SUM(H63:H67) -> 52114 | I62: =SUM(I63:I67) -> 60003 | J62: =SUM(J63:J67) -> 26288 | L62: =B62/B$7*100 -> 2.2800031 | M62: =C62/C$7*100 -> 2.8483774 | N62: =D62/D$7*100 -> 3.0875863 | O62: =E62/E$7*100 -> 3.4009373 | P62: =F62/F$7*100 -> 3.9910274 | Q62: =G62/G$7*100 -> 3.5402312 | R62: =H62/H$7*100 -> 3.5110768 | S62: =I62/I$7*100 -> 3.5236043 | T62: =J62/J$7*100 -> 4.7323643 | V62: 49.917639 | W62: =(C62-B62)/B62*100 -> 46.728929 | X62: =(D62-C62)/C62*100 -> 16.071763 | Y62: =(E62-D62)/D62*100 -> 12.835676 | Z62: =(F62-E62)/E62*100 -> 22.284162 | AA62: =(G62-F62)/F62*100 -> -4.1632574 | AB62: =(H62-G62)/G62*100 -> 5.9378367 | AC62: =(I62-H62)/H62*100 -> 15.137967 | AD62: =(J62-I62)/I62*100 -> -56.188857 | AE62: މިޑްލް އީސްޓް
A63: Kuwait | B63: 2987 | C63: 4622 | D63: 5248 | E63: 4491 | F63: 4215 | G63: 4576 | H63: 4559 | I63: 5420 | J63: 2816 | L63: =B63/B$7*100 -> 0.31178727 | M63: =C63/C$7*100 -> 0.41077069 | N63: =D63/D$7*100 -> 0.43557036 | O63: =E63/E$7*100 -> 0.36386528 | P63: =F63/F$7*100 -> 0.32772609 | Q63: =G63/G$7*100 -> 0.32931714 | R63: =H63/H$7*100 -> 0.30715353 | S63: =I63/I$7*100 -> 0.31828301 | T63: =J63/J$7*100 -> 0.50693617 | V63: 66.22148 | W63: =(C63-B63)/B63*100 -> 54.737195 | X63: =(D63-C63)/C63*100 -> 13.54392 | Y63: =(E63-D63)/D63*100 -> -14.424543 | Z63: =(F63-E63)/E63*100 -> -6.1456246 | AA63: =(G63-F63)/F63*100 -> 8.5646501 | AB63: =(H63-G63)/G63*100 -> -0.3715035 | AC63: =(I63-H63)/H63*100 -> 18.885721 | AD63: =(J63-I63)/I63*100 -> -48.04428 | AE63: ކުވެއިތު | AR63: 2008 | AS63: 2009 | AT63: 2010 | AU63: 2011 | AV63: 2012 | AW63: 2013 | AX63: 2014 | AY63: 2015 | AZ63: 2016 | BA63: 2017 | BB63: 2018 | BC63: 2019 | BF63: Total | BG63: 555494
A64: Lebanon | B64: 1666 | C64: 1817 | D64: 1949 | E64: 2185 | F64: 2258 | G64: 2444 | H64: 1898 | I64: 1940 | J64: 1049 | L64: =B64/B$7*100 -> 0.17389943 | M64: =C64/C$7*100 -> 0.16148212 | N64: =D64/D$7*100 -> 0.16176194 | O64: =E64/E$7*100 -> 0.17703087 | P64: =F64/F$7*100 -> 0.17556477 | Q64: =G64/G$7*100 -> 0.17588529 | R64: =H64/H$7*100 -> 0.12787396 | S64: =I64/I$7*100 -> 0.11392418 | T64: =J64/J$7*100 -> 0.18884092 | V64: 23.774146 | W64: =(C64-B64)/B64*100 -> 9.0636255 | X64: =(D64-C64)/C64*100 -> 7.2647221 | Y64: =(E64-D64)/D64*100 -> 12.108774 | Z64: =(F64-E64)/E64*100 -> 3.3409611 | AA64: =(G64-F64)/F64*100 -> 8.2373782 | AB64: =(H64-G64)/G64*100 -> -22.340426 | AC64: =(I64-H64)/H64*100 -> 2.2128556 | AD64: =(J64-I64)/I64*100 -> -45.927835 | AE64: ލެބެނަން | AQ64: China | AR64: =AR65/1000 -> 41.511 | AS64: =AS65/1000 -> 60.666 | AT64: =AT65/1000 -> 118.961 | AU64: =AU65/1000 -> 198.655 | AV64: =AV65/1000 -> 229.551 | AW64: =AW65/1000 -> 331.719 | AX64: =AX65/1000 -> 363.626 | AY64: =AY65/1000 -> 359.514 | ... BC64: =BC65/1000 -> 284.029 | BI64: Europe | BJ64: 348349
A65: Saudi Arabia | B65: 7263 | C65: 10477 | D65: 12405 | E65: 15749 | F65: 21964 | G65: 19546 | H65: 23540 | I65: 25865 | J65: 7578 | L65: =B65/B$7*100 -> 0.75812218 | M65: =C65/C$7*100 -> 0.9311217 | N65: =D65/D$7*100 -> 1.0295828 | O65: =E65/E$7*100 -> 1.2759996 | P65: =F65/F$7*100 -> 1.7077523 | Q65: =G65/G$7*100 -> 1.4066505 | R65: =H65/H$7*100 -> 1.5859605 | S65: =I65/I$7*100 -> 1.5188912 | T65: =J65/J$7*100 -> 1.3641912 | V65: 45.114885 | W65: =(C65-B65)/B65*100 -> 44.251687 | X65: =(D65-C65)/C65*100 -> 18.402214 | Y65: =(E65-D65)/D65*100 -> 26.956872 | Z65: =(F65-E65)/E65*100 -> 39.462823 | AA65: =(G65-F65)/F65*100 -> -11.008924 | AB65: =(H65-G65)/G65*100 -> 20.433848 | AC65: =(I65-H65)/H65*100 -> 9.8768054 | AD65: =(J65-I65)/I65*100 -> -70.70172 | AE65: ސައުދީއެރޭބިއާ | AQ65: China | AR65: 41511 | AS65: 60666 | AT65: 118961 | AU65: 198655 | AV65: 229551 | AW65: 331719 | AX65: 363626 | AY65: 359514 | AZ65: 324326 | BA65: 306530 | BB65: =H37 -> 283116 | BC65: =I37 -> 284029 | BI65: Asia | BJ65: 134279
A66: United Arab Emirates | B66: 4047 | C66: 5936 | D66: 7008 | E66: 7322 | F66: 8045 | G66: 10485 | H66: 9018 | I66: 10493 | J66: 7368 | L66: =B66/B$7*100 -> 0.42243156 | M66: =C66/C$7*100 -> 0.52754972 | N66: =D66/D$7*100 -> 0.58164579 | O66: =E66/E$7*100 -> 0.59323572 | P66: =F66/F$7*100 -> 0.62551754 | Q66: =G66/G$7*100 -> 0.75456517 | R66: =H66/H$7*100 -> 0.60756976 | S66: =I66/I$7*100 -> 0.61618886 | T66: =J66/J$7*100 -> 1.326387 | V66: 76.570681 | W66: =(C66-B66)/B66*100 -> 46.676551 | X66: =(D66-C66)/C66*100 -> 18.059299 | Y66: =(E66-D66)/D66*100 -> 4.4805936 | Z66: =(F66-E66)/E66*100 -> 9.8743513 | AA66: =(G66-F66)/F66*100 -> 30.329397 | AB66: =(H66-G66)/G66*100 -> -13.991416 | AC66: =(I66-H66)/H66*100 -> 16.356177 | AD66: =(J66-I66)/I66*100 -> -29.781759 | AE66: ޔުނައިޓެޑް އެރެބް އެމިރޭޓްސް | BE66: 1 | BF66: India | BG66: 62960 | BI66: Americas | BJ66: 32060
A67: Other Middle East | B67: 5880 | C67: 9198 | D67: 10591 | E67: 12229 | F67: 14848 | G67: 12142 | H67: 13099 | I67: 16285 | J67: 7477 | L67: =B67/B$7*100 -> 0.61376269 | M67: =C67/C$7*100 -> 0.81745322 | N67: =D67/D$7*100 -> 0.87902548 | O67: =E67/E$7*100 -> 0.99080574 | P67: =F67/F$7*100 -> 1.1544667 | Q67: =G67/G$7*100 -> 0.8738131 | R67: =H67/H$7*100 -> 0.882519 | S67: =I67/I$7*100 -> 0.95631712 | T67: =J67/J$7*100 -> 1.3460091 | V67: 42.372881 | W67: =(C67-B67)/B67*100 -> 56.428571 | X67: =(D67-C67)/C67*100 -> 15.144597 | Y67: =(E67-D67)/D67*100 -> 15.465962 | Z67: =(F67-E67)/E67*100 -> 21.416306 | AA67: =(G67-F67)/F67*100 -> -18.224677 | AB67: =(H67-G67)/G67*100 -> 7.8817328 | AC67: =(I67-H67)/H67*100 -> 24.322467 | AD67: =(J67-I67)/I67*100 -> -54.086583 | AE67: އެހެނިހެން | BE67: 2 | BF67: Russia | BG67: 61387 | BI67: Middle East | BJ67: 26288
A68: UN Passport Holders | B68: - | C68: 90 | D68: 189 | E68: 181 | F68: 228 | G68: 95 | H68: 63 | I68: 138 | J68: 33 | L68: - | M68: =C68/C$7*100 -> 0.0079985638 | N68: =D68/D$7*100 -> 0.015686509 | O68: =E68/E$7*100 -> 0.0146648 | P68: =F68/F$7*100 -> 0.017727532 | Q68: =G68/G$7*100 -> 0.0068367851 | R68: =H68/H$7*100 -> 0.0042444993 | S68: =I68/I$7*100 -> 0.0081038848 | T68: =J68/J$7*100 -> 0.0059406582 | V68: - | W68: 0 | X68: 0 | Y68: 0 | Z68: 0 | AA68: 0 | AB68: 0 | AC68: 0 | AD68: 0 | AE68: ޔޫ.އެން ޕާސްޕޯޓް ހޯލްޑަރ | BE68: 3 | BF68: United Kingdom | BG68: 52720 | BJ68: Other Europe | BK68: 28890
A69: Not Stated | B69: - | C69: 33 | D69: 138 | E69: 152 | F69: 147 | G69: 141 | H69: 121 | I69: 178 | J69: 63 | L69: - | M69: =C69/C$7*100 -> 0.0029328067 | N69: =D69/D$7*100 -> 0.011453641 | O69: =E69/E$7*100 -> 0.012315191 | P69: =F69/F$7*100 -> 0.011429593 | Q69: =G69/G$7*100 -> 0.010147228 | R69: =H69/H$7*100 -> 0.0081521336 | S69: =I69/I$7*100 -> 0.010452837 | T69: =J69/J$7*100 -> 0.011341257 | V69: - | W69: 0 | X69: 0 | Y69: 0 | Z69: 0 | AA69: 0 | AB69: 0 | AC69: 0 | AD69: 0 | AE69: ބަޔާންނުކުރާ | BE69: 4 | BF69: Italy | BG69: 46690
A70: Source: Ministry of Tourism | AE70: cmwzirUT cfoa IrcTcsinim :ctWrwf ivcaed utWmUluAwm | BE70: 5 | BF70: Germany | BG70: 36435
A71: Note: Maldives border was closed for international visitirs on 27th March 2020 due to global COVID-19 outbreak and was re-opened on 15th July 2020 | BE71: 6 | BF71: China | BG71: 34245
A72: Due to COVIC-19 pandamic, some tourists were unable to travel back to their home country. | BE72: 7 | BF72: France | BG72: 28031
BE74: 8 | BF74: U.S.A | BG74: 19759
BE75: 9 | BF75: Switzerland | BG75: 12517
BE76: 10 | BF76: Ukraine | BG76: 10343
BF79: Japan | BG79: 8479
BF80: Austria | BG80: 8103
BF81: Oceania | BG81: 7964
BF82: Saudi Arabia | BG82: 7578
BF83: Other Middle East | BG83: 7477
BF84: United Arab Emirates | BG84: 7368
BF85: Czech Republic | BG85: 7282
BF86: Australia | BG86: 7220
BF87: Poland | BG87: 7108
BF88: Spain | BG88: 6778
BF89: Africa | BG89: 6458
BF90: Korea | BG90: 5895
... BF125: Other Oceania | BG125: 25

Sheet 10.2
A1: 2020- 2012 ,udwdwA egunwt iaWawlcmuj egiawgWj egudnea WviawfcSokIrwTcsijwr cnutwvWb egunwtcnwt Wviawfihejwmwh cmWzitcnia egumubit cnirevurutwf : 10.2 ulwvWt
A2: Table 10.2 : TOTAL REGISTERED BED CAPACITY AND NUMBER OF ACCOMMODATION ESTABLISHMENTS, BY TYPE, 2012 - 2020 (end year)
A3: Type | B3: 2002 | C3: 2005 | D3: 2006 | F3: 2007 | H3: 2008 | J3: 2009 | K3: 2010 | L3: 2011 | M3: 2012 | N3: 2013 | O3: 2014 | P3: 2015 | Q3: 2016 | R3: 2017 | S3: 2018 | T3: 2019 | U3: 2020 | V3: ctwvWbegunwt
A5: Number of Beds (Registered) | V5: wgWj egudnea WviawfcSok IrcTcsijwr
A6: Total | B6: 18827 | C6: =SUM(C7:C10) -> 20198 | D6: =SUM(D7:D10) -> 20505 | F6: =SUM(F7:F10) -> 22187 | H6: =SUM(H7:H10) -> 23464 | J6: =SUM(J7:J10) -> 24978 | K6: =SUM(K7:K10) -> 25709 | L6: =SUM(L7:L10) -> 26896 | M6: =SUM(M7:M10) -> 28120 | N6: =SUM(N7:N10) -> 29829 | O6: =SUM(O7:O10) -> 31673 | P6: =SUM(P7:P10) -> 34085 | Q6: =SUM(Q7:Q10) -> 37374 | ... U6: =SUM(U7:U10) -> 52341.083 | V6: wlcmuj
A7: Resorts (including Marinas) | B7: 16400 | C7: 17348 | D7: 17802 | F7: 19028 | H7: 19860 | J7: 20942 | K7: 21350 | L7: 22120 | M7: 22889 | N7: 23487 | O7: 24031 | P7: 24877 | Q7: 26933 | R7: 29977 | S7: 31971 | T7: 37004 | U7: 37566.333 | V7: ރިސޯޓްތައް (މެރީނާއާއި އެކު)
A8: Hotels | B8: 670 | C8: 636 | D8: 713 | F8: 836 | H8: 1110 | J8: 1368 | K8: 1449 | L8: 1603 | M8: 1627 | N8: 1708 | O8: 1704 | P8: 1648 | Q8: 1713 | R8: 1456 | S8: 1862 | T8: 1642 | U8: 1698 | V8: cawtWToh
A9: Guest Houses | B9: 282 | C9: 425 | D9: 391 | F9: 400 | H9: 400 | J9: 462 | K9: 476 | L9: 659 | M9: 1101 | N9: 1918 | O9: 3199 | P9: 4621 | Q9: 6034 | R9: 7304 | S9: 8563 | T9: 9753 | U9: 10154.333 | V9: cawtegIluk
A10: Safari Vessels | B10: 1475 | C10: 1789 | D10: 1599 | F10: 1923 | H10: 2094 | J10: 2206 | K10: 2434 | L10: 2514 | M10: 2503 | N10: 2716 | O10: 2739 | P10: 2939 | Q10: 2694 | R10: 2518 | S10: 2758 | T10: 2963 | U10: 2922.4167 | V10: cawtudnwLua
A11: No. of Beds in operation 1_/ | V11: ބޭނުންކުރެވުނު އެނދުގެ އަދަދު
A12: Total | B12: 18827 | C12: =SUM(C13:C16) -> 20198 | D12: =SUM(D13:D16) -> 20505 | F12: =SUM(F13:F16) -> 22187 | H12: - | J12: - | K12: - | L12: - | M12: =SUM(M13:M16) -> 26798.167 | N12: =SUM(N13:N16) -> 27997.917 | O12: =SUM(O13:O16) -> 29515.25 | P12: =SUM(P13:P16) -> 31423.917 | Q12: =SUM(Q13:Q16) -> 33802.25 | R12: =SUM(R13:R16) -> 38592.333 | S12: =SUM(S13:S16) -> 41886.667 | T12: =SUM(T13:T16) -> 47268.5 | U12: =SUM(U13:U16) -> 27744.667 | V12: wlcmuj
A13: Resorts (including Marinas) | B13: 16400 | C13: 17348 | D13: 17802 | F13: 19028 | H13: - | J13: - | K13: - | L13: - | M13: 21887.833 | N13: 22511.833 | O13: 22986.167 | P13: 23348.417 | Q13: 24567.667 | R13: 27685.917 | S13: 29399.667 | T13: 33439.75 | U13: 21445.667 | V13: ރިސޯޓްތައް (މެރީނާއާއި އެކު)
A14: Hotels | B14: 670 | C14: 636 | D14: 713 | F14: 836 | H14: - | J14: - | K14: - | L14: - | M14: 1591.3333 | N14: 1540.0833 | O14: 1435.25 | P14: 1456.1667 | Q14: 1465.5 | R14: 1496.8333 | S14: 1759 | T14: 1723 | U14: 1032.5 | V14: cawtWToh
A15: Guest Houses | B15: 282 | C15: 425 | D15: 391 | F15: 400 | H15: - | J15: - | K15: - | L15: - | M15: 844.5 | N15: 1401.5833 | O15: 2477.25 | P15: 3831.1667 | Q15: 5248.9167 | R15: 6728.8333 | S15: 8000 | T15: 9200.1667 | U15: 3615.0833 | V15: cawtegIluk
A16: Safari Vessels | B16: 1475 | C16: 1789 | D16: 1599 | F16: 1923 | H16: - | J16: - | K16: - | L16: - | M16: 2474.5 | N16: 2544.4167 | O16: 2616.5833 | P16: 2788.1667 | Q16: 2520.1667 | R16: 2680.75 | S16: 2728 | T16: 2905.5833 | U16: 1651.4167 | V16: cawtudnwLua
A17: No. of Establishments (Registered) | V17: ރެޖިސްޓްރީ ކުރެވިފައިވާ ތަންތަނުގެ އަދަދު
A18: Total | B18: 208 | C18: =SUM(C19:C22) -> 245 | D18: =SUM(D19:D22) -> 235 | F18: =SUM(F19:F22) -> 260 | H18: =SUM(H19:H22) -> 274 | I18: =SUM(I19:I22) -> 0 | J18: =SUM(J19:J22) -> 278 | K18: =SUM(K19:K22) -> 295 | L18: =SUM(L19:L22) -> 315 | M18: =SUM(M19:M22) -> 353 | N18: =SUM(N19:N22) -> 429 | O18: =SUM(O19:O22) -> 511 | ... U18: =SUM(U19:U22) -> 952 | V18: wlcmuj
A19: Resorts (including Marinas) | B19: 87 | C19: 88 | D19: 89 | F19: 92 | H19: 94 | J19: 97 | K19: 97 | L19: 101 | M19: 105 | N19: 110 | O19: 111 | P19: 115 | Q19: 126 | R19: 135 | S19: 145 | T19: 164 | U19: 159 | V19: ރިސޯޓްތައް (މެރީނާއާއި އެކު)
A20: Hotels | B20: 8 | C20: 8 | D20: 9 | F20: 11 | H20: 13 | J20: 14 | K20: 17 | L20: 19 | M20: 19 | N20: 20 | O20: 19 | P20: 17 | Q20: 16 | R20: 10 | S20: 12 | T20: 12 | U20: 13 | V20: cawtWToh
A21: Guest Houses | B21: 17 | C21: 28 | D21: 21 | F21: 24 | H21: 24 | J21: 22 | K21: 25 | L21: 38 | M21: 75 | N21: 136 | O21: 220 | P21: 313 | Q21: 393 | R21: 458 | S21: 521 | T21: 605 | U21: 638 | V21: cawtegIluk
A22: Safari Vessels | B22: 96 | C22: 121 | D22: 116 | F22: 133 | H22: 143 | J22: 145 | K22: 156 | L22: 157 | M22: 154 | N22: 163 | O22: 161 | P22: 170 | Q22: 144 | R22: 133 | S22: 147 | T22: 157 | U22: 142 | V22: cawtudnwLua
A23: No. Establishmentss in operation | V23: ބޭނުންކުރެވުނު ތަންތަނުގެ އަދަދު
A24: Total | B24: 18827 | C24: =SUM(C25:C28) -> 20198 | D24: =SUM(D25:D28) -> 20505 | F24: =SUM(F25:F28) -> 22187 | H24: - | J24: - | K24: - | L24: - | M24: =SUM(M25:M28) -> 323.08333 | N24: =SUM(N25:N28) -> 370.33333 | O24: =SUM(O25:O28) -> 448.16667 | P24: =SUM(P25:P28) -> 540.33333 | Q24: =SUM(Q25:Q28) -> 611.41667 | R24: =SUM(R25:R28) -> 713.41667 | S24: =SUM(S25:S28) -> 777 | T24: =SUM(T25:T28) -> 872.16667 | U24: =SUM(U25:U28) -> 550 | V24: wlcmuj
A25: Resorts (including Marinas) | B25: 16400 | C25: 17348 | D25: 17802 | F25: 19028 | H25: - | J25: - | K25: - | L25: - | M25: 97.666667 | N25: 101.08333 | O25: 104.41667 | P25: 104.83333 | Q25: 111.08333 | R25: 124.08333 | S25: 130 | T25: 146 | U25: 140 | V25: ރިސޯޓްތައް (މެރީނާއާއި އެކު)
A26: Hotels | B26: 670 | C26: 636 | D26: 713 | F26: 836 | H26: - | J26: - | K26: - | L26: - | M26: 18.583333 | N26: 17.333333 | O26: 15.583333 | P26: 14.333333 | Q26: 12.666667 | R26: 11.916667 | S26: 12 | T26: 11.416667 | U26: 11 | V26: cawtWToh
A27: Guest Houses | B27: 282 | C27: 425 | D27: 391 | F27: 400 | H27: - | J27: - | K27: - | L27: - | M27: 54.333333 | N27: 98.833333 | O27: 172.91667 | P27: 261.66667 | Q27: 353.5 | R27: 433.58333 | S27: 490 | T27: 561 | U27: 268 | V27: cawtegIluk
A28: Safari Vessels | B28: 1475 | C28: 1789 | D28: 1599 | F28: 1923 | H28: - | J28: - | K28: - | L28: - | M28: 152.5 | N28: 153.08333 | O28: 155.25 | P28: 159.5 | Q28: 134.16667 | R28: 143.83333 | S28: 145 | T28: 153.75 | U28: 131 | V28: cawtudnwLua
A29: Bed capacity utilization rate (%) | V29: އެނދުގެ ޖާގައިން ބޭނުންކުރެވުނު މިންވަރު %
A30: Resorts (including Marinas) | B30: 87 | C30: 88 | D30: 89 | F30: 92 | H30: - | J30: - | K30: - | L30: - | M30: 86.68877 | N30: 88.595127 | O30: 81.856214 | P30: 76.220607 | Q30: 73.996437 | R30: 72.738666 | S30: 74.6 | T30: 74.139743 | U30: 28.978641 | V30: ރިސޯޓްތައް (މެރީނާއާއި އެކު)
A31: Hotels | B31: 8 | C31: 8 | D31: 9 | F31: 11 | H31: - | J31: - | K31: - | L31: - | M31: 36.663245 | N31: 37.491387 | O31: 42.621856 | P31: 38.453286 | Q31: 40.343423 | R31: 44.192331 | S31: 40.4 | T31: 45.412557 | U31: 17.074462 | V31: cawtWToh
A32: Guest Houses | B32: 17 | C32: 28 | D32: 21 | F32: 24 | H32: - | J32: - | K32: - | L32: - | M32: 18.438427 | N32: 23.215801 | O32: 18.290859 | P32: 23.754187 | Q32: 33.51556 | R32: 30.768032 | S32: 32.6 | T32: 33.867677 | U32: 18.371216 | V32: cawtegIluk
A33: Safari Vessels | B33: 96 | C33: 121 | D33: 116 | F33: 133 | H33: - | J33: - | K33: - | L33: - | M33: 41.030047 | N33: 46.93881 | O33: 26.948089 | P33: 29.175364 | Q33: 28.964643 | R33: 26.385018 | S33: 28.1 | T33: 26.15365 | U33: 12.572499 | V33: cawtudnwLua
A34: Note:1_/: 2018 data revised | V34: ނޯޓް: /_1: 2018 ގެ މަޢުލޫމާތު އިސްލާޙުކުރެވިފައި
A35: Source: Ministry of Tourism | V35: cmwzirUT cfoa IrcTcsinim :ctWrwf ivcaed utWmUluAwm
AE37: Resorts (including Marinas) | AF37: =T7/$T$6*100 -> 72.045481
AE38: Hotels | AF38: =T8/$T$6*100 -> 3.196916
AE39: Guest Houses | AF39: =T9/$T$6*100 -> 18.988747
AE40: Safari Vessels | AF40: =T10/$T$6*100 -> 5.7688564
AE44: Resorts (including Marinas) | AF44: =T19/$T$18 -> 0.17484009
AE45: Hotels | AF45: =T20/$T$18 -> 0.012793177
AE46: Guest Houses | AF46: =T21/$T$18 -> 0.64498934
AE47: Safari Vessels | AF47: =T22/$T$18 -> 0.1673774

Sheet 10.3
A1: 2020 - 2019 ,urwvcnim unuverukcnunEb wgWjegudnea iaWa wgWj egudnea uhwmcswmikea : 10.3 ulwvWt
A2: Table 10.3: BED CAPACITY AND UTILIZATION BY MONTH, 2019 - 2020
A3: Month | B3: 2014 1_/ | H3: 2015 1_/ | N3: 20161_/ | T3: 2017 | Z3: 2018 | AG3: 2019 | AM3: 2020
B4: އެނދުގެ ޖާގަ | C4: ބޭނުންކުރެވުނު އެނދުގެ އަދަދު | D4: އެނދުގެ ޖާގައިން ބޭނުންކުރެވުނު މިންވަރު % | E4: އެނދުގެ ޖާގަ ބޭނުންކުރި މިންވަރު % | F4: ފަތުރުވެރިން ހޭދަކޮށްފައިވާ ރޭގެ އަދަދު | G4: ފަތުރުވެރިން އެވަރެޖްކޮށް ހޭދަކޮށްފައިވާ މުއްދަތު | H4: އެނދުގެ ޖާގަ | I4: ބޭނުންކުރެވުނު އެނދުގެ އަދަދު | J4: އެނދުގެ ޖާގައިން ބޭނުންކުރެވުނު މިންވަރު % | K4: އެނދުގެ ޖާގަ ބޭނުންކުރި މިންވަރު % | L4: ފަތުރުވެރިން ހޭދަކޮށްފައިވާ ރޭގެ އަދަދު | M4: ފަތުރުވެރިން އެވަރެޖްކޮށް ހޭދަކޮށްފައިވާ މުއްދަތު | N4: އެނދުގެ ޖާގަ | O4: ބޭނުންކުރެވުނު އެނދުގެ އަދަދު | P4: އެނދުގެ ޖާގައިން ބޭނުންކުރެވުނު މިންވަރު % | Q4: އެނދުގެ ޖާގަ ބޭނުންކުރި މިންވަރު % | R4: ފަތުރުވެރިން ހޭދަކޮށްފައިވާ ރޭގެ އަދަދު | S4: ފަތުރުވެރިން އެވަރެޖްކޮށް ހޭދަކޮށްފައިވާ މުއްދަތު | T4: އެނދުގެ ޖާގަ | U4: ބޭނުންކުރެވުނު އެނދުގެ އަދަދު | V4: އެނދުގެ ޖާގައިން ބޭނުންކުރެވުނު މިންވަރު % | W4: އެނދުގެ ޖާގަ ބޭނުންކުރި މިންވަރު % | X4: ފަތުރުވެރިން ހޭދަކޮށްފައިވާ ރޭގެ އަދަދު | Y4: ފަތުރުވެރިން އެވަރެޖްކޮށް ހޭދަކޮށްފައިވާ މުއްދަތު | Z4: އެނދުގެ ޖާގަ | AA4: ބޭނުންކުރެވުނު އެނދުގެ އަދަދު | AB4: އެނދުގެ ޖާގައިން ބޭނުންކުރެވުނު މިންވަރު % | AC4: އެނދުގެ ޖާގަ ބޭނުންކުރި މިންވަރު % | AD4: ފަތުރުވެރިން ހޭދަކޮށްފައިވާ ރޭގެ އަދަދު | AE4: ފަތުރުވެރިން އެވަރެޖްކޮށް ހޭދަކޮށްފައިވާ މުއްދަތު | AG4: އެނދުގެ ޖާގަ | AH4: ބޭނުންކުރެވުނު އެނދުގެ އަދަދު | AI4: އެނދުގެ ޖާގައިން ބޭނުންކުރެވުނު މިންވަރު % | AJ4: އެނދުގެ ޖާގަ ބޭނުންކުރި މިންވަރު % | AK4: ފަތުރުވެރިން ހޭދަކޮށްފައިވާ ރޭގެ އަދަދު | AL4: ފަތުރުވެރިން އެވަރެޖްކޮށް ހޭދަކޮށްފައިވާ މުއްދަތު | AM4: އެނދުގެ ޖާގަ | AN4: ބޭނުންކުރެވުނު އެނދުގެ އަދަދު | AO4: އެނދުގެ ޖާގައިން ބޭނުންކުރެވުނު މިންވަރު % | AP4: އެނދުގެ ޖާގަ ބޭނުންކުރި މިންވަރު % | AQ4: ފަތުރުވެރިން ހޭދަކޮށްފައިވާ ރޭގެ އަދަދު | AR4: ފަތުރުވެރިން އެވަރެޖްކޮށް ހޭދަކޮށްފައިވާ މުއްދަތު
B5: Registered Bed Capacity * | C5: Beds in operation | D5: % share of registered beds in operation | E5: Bed Capacity Utilization Rate % | F5: Tourist Bednights | G5: Average Duration of stay (days) | H5: Registered Bed Capacity | I5: Beds in operation | J5: % share of registered beds in operation | K5: Bed Capacity Utilization Rate % | L5: Tourist Bednights | M5: Average Duration of stay (days) | N5: Registered Bed Capacity | O5: Beds in operation | P5: % share of registered beds in operation | Q5: Bed Capacity Utilization Rate % | R5: Tourist Bednights | S5: Average Duration of stay (days) | T5: Registered Bed Capacity | U5: Beds in operation | V5: % share of registered beds in operation | W5: Bed Capacity Utilization Rate % | X5: Tourist Bednights | Y5: Average Duration of stay (days) | Z5: Registered Bed Capacity 1_/ | AA5: Beds in operation1_/ | AB5: % share of registered beds in operation | AC5: Bed Capacity Utilization Rate % | AD5: Tourist Bednights | AE5: Average Duration of stay (days) | AG5: Registered Bed Capacity | AH5: Beds in operation | AI5: % share of registered beds in operation | AJ5: Bed Capacity Utilization Rate % | AK5: Tourist Bednights | AL5: Average Duration of stay (days) | AM5: Registered Bed Capacity | AN5: Beds in operation | AO5: % share of registered beds in operation | AP5: Bed Capacity Utilization Rate % | AQ5: Tourist Bednights | AR5: Average Duration of stay (days)
A6: Annual Average | B6: =AVERAGE(B7:B18) -> 30586.667 | C6: =AVERAGE(C7:C18) -> 29515.25 | D6: =AVERAGE(D7:D18) -> 96.506881 | E6: =AVERAGE(E7:E18) -> 69.743726 | F6: =SUM(F7:F18) -> 7505622.3 | G6: =AVERAGE(G7:G18) -> 6.056923 | H6: =AVERAGE(H7:H18) -> 32835.25 | I6: =AVERAGE(I7:I18) -> 31423.917 | J6: =AVERAGE(J7:J18) -> 95.7103 | K6: =AVERAGE(K7:K18) -> 63.947493 | L6: =SUM(L7:L18) -> 7322683.1 | M6: =AVERAGE(M7:M18) -> 5.6623346 | N6: =AVERAGE(N7:N18) -> 35352.583 | O6: =AVERAGE(O7:O18) -> 33802.25 | P6: =AVERAGE(P7:P18) -> 95.601944 | Q6: =AVERAGE(Q7:Q18) -> 62.896552 | R6: =SUM(R7:R18) -> 7770922.6 | S6: =AVERAGE(S7:S18) -> 6.025 | T6: =AVERAGE(T7:T18) -> 39535.833 | U6: =AVERAGE(U7:U18) -> 38592.333 | V6: =AVERAGE(V7:V18) -> 97.601595 | W6: =AVERAGE(W7:W18) -> 61.105983 | X6: =SUM(X7:X18) -> 8593283.6 | Y6: =AVERAGE(Y7:Y18) -> 6.175 | Z6: =AVERAGE(Z7:Z18) -> 43050.083 | AA6: =AVERAGE(AA7:AA18) -> 41886.5 | AB6: =AVERAGE(AB7:AB18) -> 97.299233 | AC6: =AVERAGE(AC7:AC18) -> 62.132135 | AD6: =SUM(AD7:AD18) -> 9478093.9 | AE6: =AVERAGE(AE7:AE18) -> 6.3666667 | AG6: =AVERAGE(AG7:AG18) -> 48904.417 | AH6: =AVERAGE(AH7:AH18) -> 47268.5 | AI6: =AVERAGE(AI7:AI18) -> 96.656968 | AJ6: =AVERAGE(AJ7:AJ18) -> 62.27169 | AK6: =SUM(AK7:AK18) -> 10688387 | AL6: =AVERAGE(AL7:AL18) -> 6.2969106 | AM6: =AVERAGE(AM7:AM18) -> 52341.083 | AN6: =AVERAGE(AN7:AN18) -> 27744.667 | AO6: =AVERAGE(AO7:AO18) -> 53.023494 | AP6: =AVERAGE(AP7:AP18) -> 25.684781 | AQ6: =SUM(AQ7:AQ18) -> 3984712.4 | AR6: 7.1732772
A7: January | B7: 29815 | C7: 29074 | D7: =C7/B7*100 -> 97.514674 | E7: 77.894365 | F7: 702057.24 | G7: 6.4975118 | H7: 32031 | I7: 31029 | J7: =I7/H7*100 -> 96.87178 | K7: 68.982454 | L7: 663541.54 | M7: 6.4986144 | N7: 34012 | O7: 32548 | P7: =O7/N7*100 -> 95.695637 | Q7: 65.312077 | R7: 658991.02 | S7: 6.1 | T7: 37575 | U7: 36225 | V7: 96.407186 | W7: 71.250594 | X7: 800126.36 | Y7: 6.4 | Z7: 41602 | AA7: 40943 | AB7: 98.415942 | AC7: 74.178416 | AD7: 941496.94 | AE7: 6.6 | AG7: 45565 | AH7: 44266 | AI7: 97.149128 | AJ7: 72.760799 | AK7: 998457.16 | AL7: 6.588215 | AM7: 52016 | AN7: 50679 | AO7: 97.429637 | AP7: 72.736012 | AQ7: 1142718.4 | AR7: 6.5920863
A8: February | B8: 29885 | C8: 29183 | D8: =C8/B8*100 -> 97.650995 | E8: 85.89086 | F8: 701834.83 | G8: 6.1376541 | H8: 32122 | I8: 31068 | J8: =I8/H8*100 -> 96.71876 | K8: 82.039189 | L8: 713662.18 | M8: 5.6647325 | N8: 34152 | O8: 32741 | P8: =O8/N8*100 -> 95.86847 | Q8: 78.932965 | R8: 749459.82 | S8: 6.2 | T8: 38146 | U8: 37133 | V8: 97.344414 | W8: 74.290195 | X8: 772412.99 | Y8: 6.4 | Z8: 41710 | AA8: 40807 | AB8: 97.835052 | AC8: 81.007215 | AD8: 925585.2 | AE8: 6.4 | AG8: 46073 | AH8: 44680 | AI8: 96.976537 | AJ8: 81.503171 | AK8: 1019637.3 | AL8: 6.0482805 | AM8: 52263 | AN8: 50926 | AO8: 97.441785 | AP8: 69.086698 | AQ8: 1020309.7 | AR8: 6.8118281
A9: March | B9: 30271 | C9: 29445 | D9: =C9/B9*100 -> 97.271316 | E9: 77.392769 | F9: 706437.32 | G9: 6.4923551 | H9: 32345 | I9: 31307 | J9: =I9/H9*100 -> 96.790849 | K9: 71.391083 | L9: 692862.6 | M9: 5.837121 | N9: 34364 | O9: 32874 | P9: =O9/N9*100 -> 95.664067 | Q9: 73.258061 | R9: 746568.5 | S9: 6.5 | T9: 38719 | U9: 37773 | V9: 97.556755 | W9: 64.086718 | X9: 750431.76 | Y9: 6.7 | Z9: 42050 | AA9: 41137 | AB9: 97.828775 | AC9: 68.514513 | AD9: 873729.27 | AE9: 6.5 | AG9: 47107 | AH9: 45216 | AI9: 95.985735 | AJ9: 71.825154 | AK9: 1006770.3 | AL9: 6.1824598 | AM9: 52319 | AN9: 51001 | AO9: 97.480839 | AP9: 35.56554 | AQ9: 562302.21 | AR9: 9.4298542
A10: April | B10: 30368 | C10: 29540 | D10: =C10/B10*100 -> 97.273446 | E10: 75.977205 | F10: 673309.99 | G10: 6.1507943 | H10: 32443 | I10: 31212 | J10: =I10/H10*100 -> 96.205653 | K10: 68.405485 | L10: 640521.6 | M10: 5.8961777 | N10: 34548 | O10: 33188 | P10: =O10/N10*100 -> 96.063448 | Q10: 65.879424 | R10: 655921.9 | S10: 6.3 | T10: 39070 | U10: 37817 | V10: 96.792936 | W10: 65.446547 | X10: 742497.62 | Y10: 6.2 | Z10: 42688 | AA10: 41835 | AB10: 98.00178 | AC10: 63.490693 | AD10: 796839.94 | AE10: 6.7 | AG10: 47351 | AH10: 45936 | AI10: 97.011679 | AJ10: 71.241824 | AK10: 981769.33 | AL10: 6.0189152 | AM10: 52319 | AN10: 7690 | AO10: 14.698293 | AP10: 3.8335588 | AQ10: 8844.0203 | AR10: 9.428593
A11: May | B11: 30348 | C11: 29266 | D11: =C11/B11*100 -> 96.434691 | E11: 63.656332 | F11: 577519.53 | G11: 6.1992749 | H11: 32614 | I11: 31301 | J11: =I11/H11*100 -> 95.974122 | K11: 59.290817 | L11: 575317.18 | M11: 5.8370252 | N11: 34912 | O11: 33284 | P11: =O11/N11*100 -> 95.336847 | Q11: 55.5789 | R11: 573465.31 | S11: 6.2 | T11: 39505 | U11: 38264 | V11: 96.858625 | W11: 50.708521 | X11: 601496.37 | Y11: 6.4 | Z11: 42736 | AA11: 41513 | AB11: 97.138244 | AC11: 49.851767 | AD11: 641543.89 | AE11: 6.9 | AG11: 48603 | AH11: 47196 | AI11: 97.105117 | AJ11: 49.074134 | AK11: 717991.88 | AL11: 6.9693064 | AM11: 52319 | AN11: 2978 | AO11: 5.6920048 | AP11: 5.1740951 | AQ11: 4776.6212 | AR11: 86.847657
A12: June | B12: 30488 | C12: 28938 | D12: =C12/B12*100 -> 94.916033 | E12: 54.447089 | F12: 472676.96 | G12: 5.5955943 | H12: 32694 | I12: 31089 | J12: =I12/H12*100 -> 95.090842 | K12: 48.021539 | L12: 447882.49 | M12: 5.3335092 | N12: 35086 | O12: 33160 | P12: =O12/N12*100 -> 94.510631 | Q12: 44.625767 | R12: 443937.13 | S12: 5.6 | T12: 39570 | U12: 38648 | V12: 97.669952 | W12: 41.476026 | X12: 480889.64 | Y12: 5.6 | Z12: 42822 | AA12: 41503 | AB12: 96.919808 | AC12: 43.735771 | AD12: 544549.71 | AE12: 5.8 | AG12: 48873 | AH12: 47477 | AI12: 97.143617 | AJ12: 50.172152 | AK12: 714606.98 | AL12: 6.2974839 | AM12: 52287 | AN12: 3078 | AO12: 5.8867405 | AP12: 2.5187364 | AQ12: 2325.8012 | AR12: 42.287294
A13: July | B13: 30658 | C13: 29684 | D13: =C13/B13*100 -> 96.823015 | E13: 62.667044 | F13: 576664.65 | G13: 5.7481211 | H13: 32740 | I13: 31138 | J13: =I13/H13*100 -> 95.106903 | K13: 59.092551 | L13: 570407.4 | M13: 5.2416292 | N13: 35517 | O13: 33581 | P13: =O13/N13*100 -> 94.549089 | Q13: 60.453462 | R13: 629327.19 | S13: 5.7 | T13: 39799 | U13: 38979 | V13: 97.939647 | W13: 56.938909 | X13: 688020.73 | Y13: 6.1 | Z13: 42929 | AA13: 41534 | AB13: 96.750448 | AC13: 57.746224 | AD13: 743513.82 | AE13: 6.1 | AG13: 49189 | AH13: 47174 | AI13: 95.903556 | AJ13: 53.112087 | AK13: 776707.97 | AL13: 5.8777392 | AM13: 52236 | AN13: 9821 | AO13: 18.80121 | AP13: 8.1042351 | AQ13: 24673.425 | AR13: 14.083005
A14: August | B14: 30696 | C14: 29652 | D14: =C14/B14*100 -> 96.598905 | E14: 70.103727 | F14: 644401.87 | G14: 6.0467913 | H14: 32902 | I14: 31274 | J14: =I14/H14*100 -> 95.051973 | K14: 65.484146 | L14: 634864.87 | M14: 5.5166509 | N14: 35681 | O14: 33745 | P14: =O14/N14*100 -> 94.574143 | Q14: 64.919557 | R14: 679120.24 | S14: 6 | T14: 39937 | U14: 39074 | V14: 97.839097 | W14: 61.63806 | X14: 746618.12 | Y14: 6.2 | Z14: 43099 | AA14: 41780 | AB14: 96.939604 | AC14: 63.537355 | AD14: 822923.11 | AE14: 6.6 | AG14: 49740 | AH14: 47102 | AI14: 94.696421 | AJ14: 62.365862 | AK14: 910642.62 | AL14: 6.5354937 | AM14: 52361 | AN14: 19263 | AO14: 36.788831 | AP14: 11.951827 | AQ14: 71370.695 | AR14: 9.3485538
A15: September | B15: 30803 | C15: 29703 | D15: =C15/B15*100 -> 96.428919 | E15: 61.818035 | F15: 550854.33 | G15: 5.6810669 | H15: 33041 | I15: 31477 | J15: =I15/H15*100 -> 95.266487 | K15: 57.723156 | L15: 545085.54 | M15: 5.4870643 | N15: 35809 | O15: 33967 | P15: =O15/N15*100 -> 94.856042 | Q15: 57.880754 | R15: 589810.67 | S15: 5.8 | T15: 39991 | U15: 39262 | V15: 98.17709 | W15: 51.294326 | X15: 604175.35 | Y15: 5.7 | Z15: 43660 | AA15: 42355 | AB15: 97.010994 | AC15: 51.029853 | AD15: 648410.82 | AE15: 6 | AG15: 50802 | AH15: 49213 | AI15: 96.87217 | AJ15: 48.011841 | AK15: 708842.02 | AL15: 6.0265945 | AM15: 52311 | AN15: 25328 | AO15: 48.418115 | AP15: 9.9189122 | AQ15: 75367.862 | AR15: 9.4824196 | CB15: Registered Bed Capacity | CC15: Beds in operation
A16: October | B16: 30812 | C16: 29625 | D16: =C16/B16*100 -> 96.147605 | E16: 74.500473 | F16: 684193.72 | G16: 6.0237286 | H16: 33415 | I16: 31406 | J16: =I16/H16*100 -> 93.98773 | K16: 65.599745 | L16: 638669.93 | M16: 5.7831712 | N16: 36062 | O16: 34114 | P16: =O16/N16*100 -> 94.598192 | Q16: 66.797619 | R16: 706407.53 | S16: 6 | T16: 40169 | U16: 39545 | V16: 98.446563 | W16: 64.726132 | X16: 793474.42 | Y16: 6.2 | Z16: 43806 | AA16: 42501 | AB16: 97.020956 | AC16: 62.289752 | AD16: 820686.79 | AE16: 6.4 | AG16: 51039 | AH16: 49450 | AI16: 96.886694 | AJ16: 59.780902 | AK16: 916411.33 | AL16: 6.4568749 | AM16: 52867 | AN16: 32600 | AO16: 61.664176 | AP16: 16.792903 | AQ16: 169709.08 | AR16: 9.615996 | CA16: Jan | CB16: =AM7 -> 52016 | CC16: =AN7 -> 50679
A17: November | B17: 31223 | C17: 29815 | D17: =C17/B17*100 -> 95.490504 | E17: 64.058213 | F17: 572968.69 | G17: 6.156085 | H17: 33591 | I17: 32138 | J17: =I17/H17*100 -> 95.674437 | K17: 58.808084 | L17: 566992.27 | M17: 5.9014498 | N17: 36714 | O17: 35807 | P17: =O17/N17*100 -> 97.529553 | Q17: 60.691939 | R17: 651958.88 | S17: 6.2 | T17: 40694 | U17: 39816 | V17: 97.842434 | W17: 62.79321 | X17: 750052.33 | Y17: 6.2 | Z17: 44345 | AA17: 42960 | AB17: 96.876762 | AC17: 62.784267 | AD17: 809163.63 | AE17: 6.4 | AG17: 51149 | AH17: 49658 | AI17: 97.084987 | AJ17: 59.543682 | AK17: 887046.05 | AL17: 6.4315518 | AM17: 52968 | AN17: 37378 | AO17: 70.567135 | AP17: 24.883647 | AQ17: 279030.28 | AR17: 8.8770985 | CA17: Feb | CB17: =AM8 -> 52263 | CC17: =AN8 -> 50926
A18: December | B18: 31673 | C18: 30258 | D18: =C18/B18*100 -> 95.532472 | E18: 68.518604 | F18: 642703.14 | G18: 5.9540986 | H18: 34085 | I18: 32648 | J18: =I18/H18*100 -> 95.784069 | K18: 62.531665 | L18: 632875.48 | M18: 4.95087 | N18: 37374 | O18: 36618 | P18: =O18/N18*100 -> 97.977203 | Q18: 60.428102 | R18: 685954.43 | S18: 5.7 | T18: 41255 | U18: 40572 | V18: 98.344443 | W18: 68.622562 | X18: 863087.93 | Y18: 6 | Z18: 45154 | AA18: 43770 | AB18: 96.85243 | AC18: 67.419799 | AD18: 909650.78 | AE18: 6 | AG18: 51362 | AH18: 49854 | AI18: 97.067973 | AJ18: 67.868666 | AK18: 1049504.2 | AL18: 6.1300122 | AM18: 51827 | AN18: 42194 | AO18: 81.413163 | AP18: 47.651202 | AQ18: 623284.4 | AR18: 9.1055877 | CA18: Mar | CB18: =AM9 -> 52319 | CC18: =AN9 -> 51001
A19: Note: Maldives border was closed for international visitirs on 27th March 2020 due to global COVID-19 outbreak and was re-opened on 15th July 2020 | AR19: cmwzirUT cfoa IrcTcsinim :ctWrwf ivcaed utWmUluAwm | CA19: Apr | CB19: =AM10 -> 52319 | CC19: =AN10 -> 7690
A20: May, June and July 2020, Average Duration of Stay is based on estimated number of tourists in the Maldives. | CA20: May | CB20: =AM11 -> 52319 | CC20: =AN11 -> 2978
A21: Due to COVIC-19 pandamic, some tourists were unable to travel back to their home country. | CA21: Jun | CB21: =AM12 -> 52287 | CC21: =AN12 -> 3078
A22: Source: Ministry of Tourism | CA22: Jul | CB22: =AM13 -> 52236 | CC22: =AN13 -> 9821
CA23: Aug | CB23: =AM14 -> 52361 | CC23: =AN14 -> 19263
CA24: Sep | CB24: =AM15 -> 52311 | CC24: =AN15 -> 25328
BN25: 41640 | BO25: =G7 -> 6.4975118 | CA25: Oct | CB25: =AM16 -> 52867 | CC25: =AN16 -> 32600
BN26: February | BO26: =G8 -> 6.1376541 | CA26: Nov | CB26: =AM17 -> 52968 | CC26: =AN17 -> 37378
BN27: March | BO27: =G9 -> 6.4923551 | CA27: Dec | CB27: =AM18 -> 51827 | CC27: =AN18 -> 42194
BN28: April | BO28: =G10 -> 6.1507943
BN29: May | BO29: =G11 -> 6.1992749
BN30: June | BO30: =G12 -> 5.5955943
BN31: July | BO31: =G13 -> 5.7481211
BN32: August | BO32: =G14 -> 6.0467913
BN33: September | BO33: =G15 -> 5.6810669
BN34: October | BO34: =G16 -> 6.0237286
BN35: November | BO35: =G17 -> 6.156085
BN36: December | BO36: =G18 -> 5.9540986
BN37: 42005 | BO37: 6.4986144
BN38: February | BO38: 5.6647325
BN39: March | BO39: 5.837121
BN40: April | BO40: 5.8961777
BN41: May | BO41: 5.8370252
BN42: June | BO42: 5.3335092
BN43: July | BO43: 5.2416292
BN44: August | BO44: 5.5166509
BN45: September | BO45: 5.4870643
BN46: October | BO46: 5.7831712
BN47: November | BO47: 5.9014498
BN48: December | BO48: 4.95087
BN49: 42370 | BO49: =S7 -> 6.1
BN50: Feb | BO50: =S8 -> 6.2
BN51: Mar | BO51: =S9 -> 6.5
BN52: Apr | BO52: =S10 -> 6.3
BN53: May | BO53: =S11 -> 6.2
BN54: Jun | BO54: =S12 -> 5.6
BN55: Jul | BO55: =S13 -> 5.7
BN56: Aug | BO56: =S14 -> 6
BN57: Sep | BO57: =S15 -> 5.8
BN58: Oct | BO58: =S16 -> 6
BN59: Nov | BO59: =S17 -> 6.2
BN60: Dec | BO60: =S18 -> 5.7
BN61: 42736 | BO61: =Y7 -> 6.4
BN62: Feb | BO62: =Y8 -> 6.4
BN63: Mar | BO63: =Y9 -> 6.7
BN64: Apr | BO64: =Y10 -> 6.2
BN65: May | BO65: =Y11 -> 6.4
BN66: Jun | BO66: =Y12 -> 5.6
BN67: Jul | BO67: =Y13 -> 6.1
BN68: Aug | BO68: =Y14 -> 6.2
BN69: Sep | BO69: =Y15 -> 5.7
BN70: Oct | BO70: =Y16 -> 6.2
BN71: Nov | BO71: =Y17 -> 6.2
BN72: Dec | BO72: =Y18 -> 6
BN73: 43101 | BO73: =AE7 -> 6.6
BN74: Feb | BO74: =AE8 -> 6.4
BN75: Mar | BO75: =AE9 -> 6.5
BN76: Apr | BO76: =AE10 -> 6.7
BN77: May | BO77: =AE11 -> 6.9
BN78: Jun | BO78: =AE12 -> 5.8
BN79: Jul | BO79: =AE13 -> 6.1
BN80: Aug | BO80: =AE14 -> 6.6
BN81: Sep | BO81: =AE15 -> 6
BN82: Oct | BO82: =AE16 -> 6.4
BN83: Nov | BO83: =AE17 -> 6.4
BN84: Dec | BO84: =AE18 -> 6
BN85: 43466 | BO85: =AL7 -> 6.588215
BN86: Feb | BO86: =AL8 -> 6.0482805
BN87: Mar | BO87: =AL9 -> 6.1824598
BN88: Apr | BO88: =AL10 -> 6.0189152
BN89: May | BO89: =AL11 -> 6.9693064
BN90: Jun | BO90: =AL12 -> 6.2974839
BN91: Jul | BO91: =AL13 -> 5.8777392
BN92: Aug | BO92: =AL14 -> 6.5354937
BN93: Sep | BO93: =AL15 -> 6.0265945
BN94: Oct | BO94: =AL16 -> 6.4568749
BN95: Nov | BO95: =AL17 -> 6.4315518
BN96: Dec | BO96: =AL18 -> 6.1300122
BN97: 43831 | BO97: =AR7 -> 6.5920863
BN98: Feb | BO98: =AR8 -> 6.8118281
BN99: Mar | BO99: =AR9 -> 9.4298542
BN100: Apr | BO100: =AR10 -> 9.428593
...

Sheet 10.4
A1: 2020 - 2019 ,urwvcnim unuverukcnunEb wgWjegudnea iaWa wgWj egudnea egukwtuTOsir uhwmcswmikea : 10.4 ulwvWt
A2: Table 10.4: BED CAPACITY AND UTILIZATION OF RESORTS BY MONTH, 2019 - 2020
A4: Month | B4: 2014 | G4: 2015 | L4: 2016 | Q4: 2017 | V4: 2018 | AA4: 2019 | AF4: 2020
B5: އެނދުގެ ޖާގަ | C5: ބޭނުންކުރެވުނު އެނދުގެ އަދަދު | D5: އެނދުގެ ޖާގައިން ބޭނުންކުރެވުނު މިންވަރު % | E5: އެނދުގެ ޖާގަ ބޭނުންކުރި މިންވަރު % | F5: ފަތުރުވެރިން ހޭދަކޮށްފައިވާ ރޭގެ އަދަދު | G5: އެނދުގެ ޖާގަ | H5: ބޭނުންކުރެވުނު އެނދުގެ އަދަދު | I5: އެނދުގެ ޖާގައިން ބޭނުންކުރެވުނު މިންވަރު % | J5: އެނދުގެ ޖާގަ ބޭނުންކުރި މިންވަރު % | K5: ފަތުރުވެރިން ހޭދަކޮށްފައިވާ ރޭގެ އަދަދު | L5: އެނދުގެ ޖާގަ | M5: ބޭނުންކުރެވުނު އެނދުގެ އަދަދު | N5: އެނދުގެ ޖާގައިން ބޭނުންކުރެވުނު މިންވަރު % | O5: އެނދުގެ ޖާގަ ބޭނުންކުރި މިންވަރު % | P5: ފަތުރުވެރިން ހޭދަކޮށްފައިވާ ރޭގެ އަދަދު | Q5: އެނދުގެ ޖާގަ | R5: ބޭނުންކުރެވުނު އެނދުގެ އަދަދު | S5: އެނދުގެ ޖާގައިން ބޭނުންކުރެވުނު މިންވަރު % | T5: އެނދުގެ ޖާގަ ބޭނުންކުރި މިންވަރު % | U5: ފަތުރުވެރިން ހޭދަކޮށްފައިވާ ރޭގެ އަދަދު | V5: އެނދުގެ ޖާގަ | W5: ބޭނުންކުރެވުނު އެނދުގެ އަދަދު | X5: އެނދުގެ ޖާގައިން ބޭނުންކުރެވުނު މިންވަރު % | Y5: އެނދުގެ ޖާގަ ބޭނުންކުރި މިންވަރު % | Z5: ފަތުރުވެރިން ހޭދަކޮށްފައިވާ ރޭގެ އަދަދު | AA5: އެނދުގެ ޖާގަ | AB5: ބޭނުންކުރެވުނު އެނދުގެ އަދަދު | AC5: އެނދުގެ ޖާގައިން ބޭނުންކުރެވުނު މިންވަރު % | AD5: އެނދުގެ ޖާގަ ބޭނުންކުރި މިންވަރު % | AE5: ފަތުރުވެރިން ހޭދަކޮށްފައިވާ ރޭގެ އަދަދު | AF5: އެނދުގެ ޖާގަ | AG5: ބޭނުންކުރެވުނު އެނދުގެ އަދަދު | AH5: އެނދުގެ ޖާގައިން ބޭނުންކުރެވުނު މިންވަރު % | AI5: އެނދުގެ ޖާގަ ބޭނުންކުރި މިންވަރު % | AJ5: ފަތުރުވެރިން ހޭދަކޮށްފައިވާ ރޭގެ އަދަދު
B6: Registered Bed Capacity | C6: Beds in operation | D6: % share of registered beds in operation | E6: Bed Capacity Utilization Rate % | F6: Tourist Bednights | G6: Registered Bed Capacity | H6: Beds in operation | I6: % share of registered beds in operation | J6: Bed Capacity Utilization Rate % | K6: Tourist Bednights | L6: Registered Bed Capacity | M6: Beds in operation | N6: % share of registered beds in operation | O6: Bed Capacity Utilization Rate % | P6: Tourist Bednights | Q6: Registered Bed Capacity | R6: Beds in operation | S6: % share of registered beds in operation | T6: Bed Capacity Utilization Rate % | U6: Tourist Bednights | V6: Registered Bed Capacity 1_/ | W6: Beds in operation1_/ | X6: % share of registered beds in operation | Y6: Bed Capacity Utilization Rate % | Z6: Tourist Bednights | AA6: Registered Bed Capacity | AB6: Beds in operation | AC6: % share of registered beds in operation | AD6: Bed Capacity Utilization Rate % | AE6: Tourist Bednights | AF6: Registered Bed Capacity | AG6: Beds in operation | AH6: % share of registered beds in operation | AI6: Bed Capacity Utilization Rate % | AJ6: Tourist Bednights
A7: Annual Average | B7: =AVERAGE(B8:B19) -> 23749 | C7: =AVERAGE(C8:C19) -> 22986.167 | D7: =AVERAGE(D8:D19) -> 96.791549 | E7: =AVERAGE(E8:E19) -> 81.856214 | F7: =SUM(F8:F19) -> 6864861 | G7: =AVERAGE(G8:G19) -> 24277.167 | H7: =AVERAGE(H8:H19) -> 23348.417 | I7: =AVERAGE(I8:I19) -> 96.178937 | J7: =AVERAGE(J8:J19) -> 76.220607 | K7: =SUM(K8:K19) -> 6489783.4 | L7: =AVERAGE(L8:L19) -> 25685.333 | M7: =AVERAGE(M8:M19) -> 24567.667 | N7: =AVERAGE(N8:N19) -> 95.634598 | O7: =AVERAGE(O8:O19) -> 73.996437 | P7: =SUM(P8:P19) -> 6645765 | Q7: =AVERAGE(Q8:Q19) -> 28447.333 | R7: =AVERAGE(R8:R19) -> 27685.917 | S7: =AVERAGE(S8:S19) -> 97.31832 | T7: =AVERAGE(T8:T19) -> 72.738666 | U7: =SUM(U8:U19) -> 7343577.1 | V7: =AVERAGE(V8:V19) -> 30544.833 | W7: =AVERAGE(W8:W19) -> 29399.667 | X7: =AVERAGE(X8:X19) -> 96.256585 | Y7: =AVERAGE(Y8:Y19) -> 74.635417 | Z7: =SUM(Z8:Z19) -> 8000462.8 | AA7: =AVERAGE(AA8:AA19) -> 35016.083 | AB7: =AVERAGE(AB8:AB19) -> 33439.75 | AC7: =AVERAGE(AC8:AC19) -> 95.496713 | AD7: =AVERAGE(AD8:AD19) -> 74.139743 | AE7: =SUM(AE8:AE19) -> 8997786.6 | AF7: =AVERAGE(AF8:AF19) -> 37566.333 | AG7: =AVERAGE(AG8:AG19) -> 21445.667 | AH7: =AVERAGE(AH8:AH19) -> 57.094233 | AI7: =AVERAGE(AI8:AI19) -> 28.978641 | AJ7: =SUM(AJ8:AJ19) -> 3357345.2
A8: January | B8: 23487 | C8: 22987 | D8: =C8/B8*100 -> 97.871163 | E8: 90.256765 | F8: 643167 | G8: 24047 | H8: 23447 | I8: =H8/G8*100 -> 97.504886 | J8: 80.14809 | K8: 582562 | L8: 25047 | M8: 23986 | N8: =M8/L8*100 -> 95.763964 | O8: 75.39788 | P8: 560633 | Q8: 27083 | R8: 26302 | S8: =R8/Q8*100 -> 97.116272 | T8: 83.731194 | U8: 682712.34 | V8: 30063 | W8: 29404 | X8: =W8/V8*100 -> 97.807937 | Y8: 86.115794 | Z8: 784966.13 | AA8: 32213 | AB8: 30938 | AC8: 96.041971 | AD8: 84.878364 | AE8: 814049.72 | AF8: 37394 | AG8: 36094 | AH8: 96.523506 | AI8: 83.21671 | AJ8: 931123.42
A9: February | B9: 23487 | C9: 22987 | D9: =C9/B9*100 -> 97.871163 | E9: 98.0099 | F9: 630827 | G9: 24107 | H9: 23507 | I9: =H9/G9*100 -> 97.511096 | J9: 95.221788 | K9: 626746 | L9: 25079 | M9: 24076 | N9: =M9/L9*100 -> 96.000638 | O9: 91.065792 | P9: 635825 | Q9: 27497 | R9: 26726 | S9: =R9/Q9*100 -> 97.196058 | T9: 86.162898 | U9: 644781.09 | V9: 30063 | W9: 29160 | X9: =W9/V9*100 -> 96.996308 | Y9: 94.025822 | Z9: 767702.03 | AA9: 32437 | AB9: 31068 | AC9: 95.779511 | AD9: 94.565353 | AE9: 822627.79 | AF9: 37522 | AG9: 36222 | AH9: 96.535366 | AI9: 79.284758 | AJ9: 832837.22
A10: March | B10: 23715 | C10: 23023 | D10: =C10/B10*100 -> 97.082016 | E10: 87.894013 | F10: 627311 | G10: 24123 | H10: 23527 | I10: =H10/G10*100 -> 97.529329 | J10: 82.752418 | K10: 603544 | L10: 25079 | M10: 24086 | N10: =M10/L10*100 -> 96.040512 | O10: 84.819853 | P10: 633321 | Q10: 27973 | R10: 27202 | S10: =R10/Q10*100 -> 97.243771 | T10: 73.328085 | U10: 618347.88 | V10: 30181 | W10: 29268 | X10: =W10/V10*100 -> 96.974918 | Y10: 80.002029 | Z10: 725864.81 | AA10: 33355 | AB10: 31488 | AC10: 94.402638 | AD10: 83.700141 | AE10: 817020.51 | AF10: 37522 | AG10: 36222 | AH10: 96.535366 | AI10: 41.804754 | AJ10: 469418.05
A11: April | B11: 23715 | C11: 23243 | D11: =C11/B11*100 -> 98.009699 | E11: 87.080698 | F11: 607205 | G11: 24123 | H11: 23415 | I11: =H11/G11*100 -> 97.065042 | J11: 79.978361 | K11: 561808 | L11: 25153 | M11: 24182 | N11: =M11/L11*100 -> 96.139625 | O11: 76.867091 | P11: 557640 | Q11: 28291 | R11: 27202 | S11: =R11/Q11*100 -> 96.150719 | T11: 77.118214 | U11: 629330.9 | V11: 30187 | W11: 29334 | X11: =W11/V11*100 -> 97.17428 | Y11: 76.225942 | Z11: 670803.54 | AA11: 33509 | AB11: 32118 | AC11: 95.848876 | AD11: 84.445085 | AE11: 813662.17 | AF11: 37522 | AG11: 7064 | AH11: 18.826289 | AI11: 3.8354191 | AJ11: 8128.0203
A12: May | B12: 23715 | C12: 22905 | D12: =C12/B12*100 -> 96.58444 | E12: 75.539219 | F12: 536370 | G12: 24123 | H12: 23321 | I12: =H12/G12*100 -> 96.675372 | J12: 72.083724 | K12: 521130 | L12: 25425 | M12: 24182 | N12: =M12/L12*100 -> 95.111111 | O12: 67.042402 | P12: 502578 | Q12: 28549 | R12: 27472 | S12: =R12/Q12*100 -> 96.227539 | T12: 61.332135 | U12: 522324.09 | V12: 30187 | W12: 28964 | X12: =W12/V12*100 -> 95.948587 | Y12: 61.569198 | Z12: 552819.98 | AA12: 34735 | AB12: 33352 | AC12: 96.018425 | AD12: 59.108571 | AE12: 611130.61 | AF12: 37522 | AG12: 2904 | AH12: 7.7394595 | AI12: 5.1859739 | AJ12: 4668.6212
A13: June | B13: 23801 | C13: 22589 | D13: =C13/B13*100 -> 94.907777 | E13: 65.391857 | F13: 443141 | G13: 24233 | H13: 23090 | I13: =H13/G13*100 -> 95.283291 | J13: 59.618016 | K13: 412974 | L13: 25425 | M13: 24060 | N13: =M13/L13*100 -> 94.631268 | O13: 54.676088 | P13: 394652 | Q13: 28549 | R13: 27722 | S13: =R13/Q13*100 -> 97.103226 | T13: 51.167892 | U13: 425542.89 | V13: 30207 | W13: 28910 | X13: =W13/V13*100 -> 95.706293 | Y13: 53.753416 | Z13: 466203.38 | AA13: 34953 | AB13: 33581 | AC13: 96.074729 | AD13: 62.184863 | AE13: 626468.96 | AF13: 37522 | AG13: 3004 | AH13: 8.0059698 | AI13: 2.5042179 | AJ13: 2256.8012
A14: July | B14: 23801 | C14: 23117 | D14: =C14/B14*100 -> 97.126171 | E14: 75.655536 | F14: 542168 | G14: 24233 | H14: 23162 | I14: =H14/G14*100 -> 95.580407 | J14: 73.059232 | K14: 524581.36 | L14: 25783 | M14: 24244 | N14: =M14/L14*100 -> 94.030951 | O14: 73.919719 | P14: 555554 | Q14: 28549 | R14: 27842 | S14: =R14/Q14*100 -> 97.523556 | T14: 68.194649 | U14: 588589.38 | V14: 30207 | W14: 28820 | X14: =W14/V14*100 -> 95.408349 | Y14: 71.676325 | Z14: 640370.63 | AA14: 35195 | AB14: 33302 | AC14: 94.621395 | AD14: 65.926352 | AE14: 680598.61 | AF14: 37522 | AG14: 9180 | AH14: 24.465647 | AI14: 8.4663099 | AJ14: 24093.425
A15: August | B15: 23781 | C15: 23027 | D15: =C15/B15*100 -> 96.829402 | E15: 83.523409 | F15: 596221 | G15: 24233 | H15: 23110 | I15: =H15/G15*100 -> 95.365823 | J15: 79.296353 | K15: 568087 | L15: 25811 | M15: 24408 | N15: =M15/L15*100 -> 94.564333 | O15: 77.690947 | P15: 587847 | Q15: 28629 | R15: 27978 | S15: =R15/Q15*100 -> 97.726082 | T15: 73.756761 | U15: 639705.66 | V15: 30341 | W15: 29044 | X15: =W15/V15*100 -> 95.725256 | Y15: 77.881493 | Z15: 701216.92 | AA15: 35931 | AB15: 33422 | AC15: 93.017172 | AD15: 74.983347 | AE15: 776888.96 | AF15: 37614 | AG15: 16222 | AH15: 43.127559 | AI15: 12.458847 | AJ15: 62653.3
A16: September | B16: 23821 | C16: 23027 | D16: =C16/B16*100 -> 96.666807 | E16: 74.063491 | F16: 511638 | G16: 24233 | H16: 23162 | I16: =H16/G16*100 -> 95.580407 | J16: 70.561264 | K16: 490302 | L16: 25891 | M16: 24436 | N16: =M16/L16*100 -> 94.380287 | O16: 68.733972 | P16: 503875 | Q16: 28629 | R16: 28045 | S16: =R16/Q16*100 -> 97.96011 | T16: 62.450662 | U16: 525428.64 | V16: 30823 | W16: 29526 | X16: =W16/V16*100 -> 95.792103 | Y16: 61.593879 | Z16: 545586.26 | AA16: 36887 | AB16: 35427 | AC16: 96.041966 | AD16: 56.707958 | AE16: 602697.85 | AF16: 37622 | AG16: 20922 | AH16: 55.611079 | AI16: 10.303128 | AJ16: 64668.615
A17: October | B17: 23817 | C17: 22951 | D17: =C17/B17*100 -> 96.363942 | E17: 88.745307 | F17: 631406 | G17: 24483 | H17: 22962 | I17: =H17/G17*100 -> 93.787526 | J17: 79.945548 | K17: 569070 | L17: 26089 | M17: 24516 | N17: =M17/L17*100 -> 93.970639 | O17: 79.563182 | P17: 604677 | Q17: 28647 | R17: 28155 | S17: =R17/Q17*100 -> 98.282543 | T17: 79.174362 | U17: 691037.79 | V17: 30885 | W17: 29588 | X17: =W17/V17*100 -> 95.80055 | Y17: 77.156576 | Z17: 707701.72 | AA17: 36987 | AB17: 35527 | AC17: 96.052667 | AD17: 72.482897 | AE17: 798280.96 | AF17: 37900 | AG17: 26580 | AH17: 70.131926 | AI17: 18.153539 | AJ17: 149581.53
A18: November | B18: 23817 | C18: 22951 | D18: =C18/B18*100 -> 96.363942 | E18: 75.058894 | F18: 516803 | G18: 24511 | H18: 23542 | I18: =H18/G18*100 -> 96.046673 | J18: 68.670461 | K18: 484992 | L18: 26509 | M18: 26079 | N18: =M18/L18*100 -> 98.377909 | O18: 69.515958 | P18: 543872 | Q18: 28995 | R18: 28259 | S18: =R18/Q18*100 -> 97.461631 | T18: 75.801975 | U18: 642626.4 | V18: 31423 | W18: 30082 | X18: =W18/V18*100 -> 95.732425 | Y18: 75.906749 | Z18: 685028.05 | AA18: 36987 | AB18: 35527 | AC18: 96.052667 | AD18: 71.180039 | AE18: 758643.97 | AF18: 38000 | AG18: 30136 | AH18: 79.305263 | AI18: 27.692679 | AJ18: 250363.97
A19: December | B19: 24031 | C19: 23027 | D19: =C19/B19*100 -> 95.822063 | E19: 81.055479 | F19: 578604 | G19: 24877 | H19: 23936 | I19: =H19/G19*100 -> 96.21739 | J19: 73.312031 | K19: 543987 | L19: 26933 | M19: 26557 | N19: =M19/L19*100 -> 98.603943 | O19: 68.664358 | P19: 565291 | Q19: 29977 | R19: 29326 | S19: =R19/Q19*100 -> 97.828335 | T19: 80.645161 | U19: 733150 | V19: 31971 | W19: 30696 | X19: =W19/V19*100 -> 96.012011 | Y19: 79.717776 | Z19: 752199.39 | AA19: 37004 | AB19: 35527 | AC19: 96.00854 | AD19: 79.513944 | AE19: 875716.48 | AF19: 37134 | AG19: 32798 | AH19: 88.323369 | AI19: 54.837353 | AJ19: 557552.21
A20: Source: Ministry of Tourism | AJ20: cmwzirUT cfoa IrcTcsinim :ctWrwf ivcaed utWmUluAwm | AP20: Registered Bed Capacity | AQ20: Beds in operation
A21: Note: Maldives border was closed for international visitirs on 27th March 2020 due to global COVID-19 outbreak and was re-opened on 15th July 2020 | AO21: Jan | AP21: =AF8 -> 37394 | AQ21: =AG8 -> 36094
A22: Due to COVIC-19 pandamic, some tourists were unable to travel back to their home country. | AO22: Feb | AP22: =AF9 -> 37522 | AQ22: =AG9 -> 36222
AO23: Mar | AP23: =AF10 -> 37522 | AQ23: =AG10 -> 36222
AO24: Apr | AP24: =AF11 -> 37522 | AQ24: =AG11 -> 7064
AO25: May | AP25: =AF12 -> 37522 | AQ25: =AG12 -> 2904
AO26: Jun | AP26: =AF13 -> 37522 | AQ26: =AG13 -> 3004
AO27: Jul | AP27: =AF14 -> 37522 | AQ27: =AG14 -> 9180
AO28: Aug | AP28: =AF15 -> 37614 | AQ28: =AG15 -> 16222
AO29: Sep | AP29: =AF16 -> 37622 | AQ29: =AG16 -> 20922
AO30: Oct | AP30: =AF17 -> 37900 | AQ30: =AG17 -> 26580
AO31: Nov | AP31: =AF18 -> 38000 | AQ31: =AG18 -> 30136
AO32: Dec | AP32: =AF19 -> 37134 | AQ32: =AG19 -> 32798

Sheet 10.5
A1: 2020 - 2019 ,urwvcnim unuverukcnunEb wgWjegudnea iaWa wgWj egudnea egukwtWToh uhwmcswmikea : 10.5 ulwvWt
A2: Table 10.5: BED CAPACITY AND UTILIZATION OF HOTELS BY MONTH, 2019 - 2020
A3: Month | B3: 2014 | G3: 2015 | L3: 2016 | Q3: 2017 | V3: 2018 | AA3: 2019 | AF3: 2020
B4: އެނދުގެ ޖާގަ | C4: ބޭނުންކުރެވުނު އެނދުގެ އަދަދު | D4: އެނދުގެ ޖާގައިން ބޭނުންކުރެވުނު މިންވަރު % | E4: އެނދުގެ ޖާގަ ބޭނުންކުރި މިންވަރު % | F4: ފަތުރުވެރިން ހޭދަކޮށްފައިވާ ރޭގެ އަދަދު | G4: އެނދުގެ ޖާގަ | H4: ބޭނުންކުރެވުނު އެނދުގެ އަދަދު | I4: އެނދުގެ ޖާގައިން ބޭނުންކުރެވުނު މިންވަރު % | J4: އެނދުގެ ޖާގަ ބޭނުންކުރި މިންވަރު % | K4: ފަތުރުވެރިން ހޭދަކޮށްފައިވާ ރޭގެ އަދަދު | L4: އެނދުގެ ޖާގަ | M4: ބޭނުންކުރެވުނު އެނދުގެ އަދަދު | N4: އެނދުގެ ޖާގައިން ބޭނުންކުރެވުނު މިންވަރު % | O4: އެނދުގެ ޖާގަ ބޭނުންކުރި މިންވަރު % | P4: ފަތުރުވެރިން ހޭދަކޮށްފައިވާ ރޭގެ އަދަދު | Q4: އެނދުގެ ޖާގަ | R4: ބޭނުންކުރެވުނު އެނދުގެ އަދަދު | S4: އެނދުގެ ޖާގައިން ބޭނުންކުރެވުނު މިންވަރު % | T4: އެނދުގެ ޖާގަ ބޭނުންކުރި މިންވަރު % | U4: ފަތުރުވެރިން ހޭދަކޮށްފައިވާ ރޭގެ އަދަދު | V4: އެނދުގެ ޖާގަ | W4: ބޭނުންކުރެވުނު އެނދުގެ އަދަދު | X4: އެނދުގެ ޖާގައިން ބޭނުންކުރެވުނު މިންވަރު % | Y4: އެނދުގެ ޖާގަ ބޭނުންކުރި މިންވަރު % | Z4: ފަތުރުވެރިން ހޭދަކޮށްފައިވާ ރޭގެ އަދަދު | AA4: އެނދުގެ ޖާގަ | AB4: ބޭނުންކުރެވުނު އެނދުގެ އަދަދު | AC4: އެނދުގެ ޖާގައިން ބޭނުންކުރެވުނު މިންވަރު % | AD4: އެނދުގެ ޖާގަ ބޭނުންކުރި މިންވަރު % | AE4: ފަތުރުވެރިން ހޭދަކޮށްފައިވާ ރޭގެ އަދަދު | AF4: އެނދުގެ ޖާގަ | AG4: ބޭނުންކުރެވުނު އެނދުގެ އަދަދު | AH4: އެނދުގެ ޖާގައިން ބޭނުންކުރެވުނު މިންވަރު % | AI4: އެނދުގެ ޖާގަ ބޭނުންކުރި މިންވަރު % | AJ4: ފަތުރުވެރިން ހޭދަކޮށްފައިވާ ރޭގެ އަދަދު
B5: Registered Bed Capacity | C5: Beds in operation | D5: % share of registered beds in operation | E5: Bed Capacity Utilization Rate % | F5: Tourist Bednights | G5: Registered Bed Capacity | H5: Beds in operation | I5: % share of registered beds in operation | J5: Bed Capacity Utilization Rate % | K5: Tourist Bednights | L5: Registered Bed Capacity | M5: Beds in operation | N5: % share of registered beds in operation | O5: Bed Capacity Utilization Rate % | P5: Tourist Bednights | Q5: Registered Bed Capacity | R5: Beds in operation | S5: % share of registered beds in operation | T5: Bed Capacity Utilization Rate % | U5: Tourist Bednights | V5: Registered Bed Capacity | W5: Beds in operation | X5: % share of registered beds in operation | Y5: Bed Capacity Utilization Rate % | Z5: Tourist Bednights | AA5: Registered Bed Capacity | AB5: Beds in operation | AC5: % share of registered beds in operation | AD5: Bed Capacity Utilization Rate % | AE5: Tourist Bednights | AF5: Registered Bed Capacity | AG5: Beds in operation | AH5: % share of registered beds in operation | AI5: Bed Capacity Utilization Rate % | AJ5: Tourist Bednights
A6: Annual Average | B6: =AVERAGE(B7:B18) -> 1592.9167 | C6: =AVERAGE(C7:C18) -> 1435.25 | D6: =AVERAGE(D7:D18) -> 90.115032 | E6: =AVERAGE(E7:E18) -> 42.621856 | F6: =SUM(F7:F18) -> 223717 | G6: =AVERAGE(G7:G18) -> 1682 | H6: =AVERAGE(H7:H18) -> 1456.1667 | I6: =AVERAGE(I7:I18) -> 86.595552 | J6: =AVERAGE(J7:J18) -> 38.453286 | K6: =SUM(K7:K18) -> 204439 | L6: =AVERAGE(L7:L18) -> 1713 | M6: =AVERAGE(M7:M18) -> 1465.5 | N6: =AVERAGE(N7:N18) -> 85.551664 | O6: =AVERAGE(O7:O18) -> 40.343423 | P6: =SUM(P7:P18) -> 216842 | Q6: =AVERAGE(Q7:Q18) -> 1582.1667 | R6: =AVERAGE(R7:R18) -> 1496.8333 | S6: =AVERAGE(S7:S18) -> 94.649515 | T6: =AVERAGE(T7:T18) -> 44.192331 | U6: =SUM(U7:U18) -> 241843.62 | V6: =AVERAGE(V7:V18) -> 1758.8333 | W6: =AVERAGE(W7:W18) -> 1758.8333 | X6: =AVERAGE(X7:X18) -> 100 | Y6: =AVERAGE(Y7:Y18) -> 40.364548 | Z6: =SUM(Z7:Z18) -> 255389.18 | AA6: =AVERAGE(AA7:AA18) -> 1755.6667 | AB6: =AVERAGE(AB7:AB18) -> 1723 | AC6: =AVERAGE(AC7:AC18) -> 98.00277 | AD6: =AVERAGE(AD7:AD18) -> 45.412557 | AE6: =SUM(AE7:AE18) -> 285763.87 | AF6: =AVERAGE(AF7:AF18) -> 1698 | AG6: =AVERAGE(AG7:AG18) -> 1032.5 | AH6: =AVERAGE(AH7:AH18) -> 60.806832 | AI6: =AVERAGE(AI7:AI18) -> 17.074462 | AJ6: =SUM(AJ7:AJ18) -> 100047.94
A7: January | B7: 1626 | C7: 1596 | D7: =C7/B7*100 -> 98.154982 | E7: 48.085941 | F7: 23791 | G7: 1744 | H7: 1508 | I7: =H7/G7*100 -> 86.46789 | J7: 43.685291 | K7: 20422 | L7: 1713 | M7: 1444 | N7: =M7/L7*100 -> 84.296556 | O7: 41.756769 | P7: 18692 | Q7: 1610 | R7: 1515 | S7: =R7/Q7*100 -> 94.099379 | T7: 56.421269 | U7: 26498.249 | V7: 1456 | W7: 1456 | X7: =W7/V7*100 -> 100 | Y7: 54.253811 | Z7: 24488 | AA7: 1862 | AB7: 1862 | AC7: 100 | AD7: 49.439315 | AE7: 28537.362 | AF7: 1698 | AG7: 1698 | AH7: 100 | AI7: 59.607833 | AJ7: 31376.371
A8: February | B8: 1626 | C8: 1596 | D8: =C8/B8*100 -> 98.154982 | E8: 50.147691 | F8: 22410 | G8: 1744 | H8: 1508 | I8: =H8/G8*100 -> 86.46789 | J8: 54.109038 | K8: 22847 | L8: 1713 | M8: 1456 | N8: =M8/L8*100 -> 84.997081 | O8: 46.999337 | P8: 19845 | Q8: 1610 | R8: 1515 | S8: =R8/Q8*100 -> 94.099379 | T8: 54.846576 | U8: 23265.917 | V8: 1456 | W8: 1456 | X8: =W8/V8*100 -> 100 | Y8: 54.363717 | Z8: 22163 | AA8: 1862 | AB8: 1862 | AC8: 100 | AD8: 64.336016 | AE8: 33542.225 | AF8: 1698 | AG8: 1698 | AH8: 100 | AI8: 56.992504 | AJ8: 28064.249
A9: March | B9: 1626 | C9: 1596 | D9: =C9/B9*100 -> 98.154982 | E9: 43.813162 | F9: 21677 | G9: 1744 | H9: 1508 | I9: =H9/G9*100 -> 86.46789 | J9: 43.871396 | K9: 20509 | L9: 1713 | M9: 1428 | N9: =M9/L9*100 -> 83.362522 | O9: 44.646246 | P9: 19764 | Q9: 1610 | R9: 1515 | S9: =R9/Q9*100 -> 94.099379 | T9: 49.994578 | U9: 23479.954 | V9: 1456 | W9: 1456 | X9: =W9/V9*100 -> 100 | Y9: 41.52118 | Z9: 18741 | AA9: 1870 | AB9: 1870 | AC9: 100 | AD9: 51.884118 | AE9: 30077.223 | AF9: 1698 | AG9: 1698 | AH9: 100 | AI9: 26.706872 | AJ9: 14057.963
A10: April | B10: 1626 | C10: 1380 | D10: =C10/B10*100 -> 84.870849 | E10: 46.76087 | F10: 19359 | G10: 1708 | H10: 1419 | I10: =H10/G10*100 -> 83.079625 | J10: 37.260982 | K10: 15862 | L10: 1713 | M10: 1428 | N10: =M10/L10*100 -> 83.362522 | O10: 39.446779 | P10: 16899 | Q10: 1610 | R10: 1515 | S10: =R10/Q10*100 -> 94.099379 | T10: 49.107327 | U10: 22319.28 | V10: 1860 | W10: 1860 | X10: =W10/V10*100 -> 100 | Y10: 38.91453 | Z10: 21714.308 | AA10: 1870 | AB10: 1870 | AC10: 100 | AD10: 51.594017 | AE10: 28944.244 | AF10: 1698 | AG10: 336 | AH10: 19.787986 | AI10: 0.54563492 | AJ10: 55
A11: May | B11: 1542 | C11: 1380 | D11: =C11/B11*100 -> 89.494163 | E11: 38.00374 | F11: 16258 | G11: 1708 | H11: 1423 | I11: =H11/G11*100 -> 83.313817 | J11: 31.888559 | K11: 14067 | L11: 1713 | M11: 1428 | N11: =M11/L11*100 -> 83.362522 | O11: 36.439414 | P11: 16131 | Q11: 1610 | R11: 1487 | S11: =R11/Q11*100 -> 92.360248 | T11: 38.580551 | U11: 17784.477 | V11: 1860 | W11: 1860 | X11: =W11/V11*100 -> 100 | Y11: 31.031844 | Z11: 17892.962 | AA11: 1870 | AB11: 1870 | AC11: 100 | AD11: 35.241935 | AE11: 20429.75 | AF11: 1698 | AG11: 0 | AH11: 0 | AI11: 0 | AJ11: 0
A12: June | B12: 1542 | C12: 1380 | D12: =C12/B12*100 -> 89.494163 | E12: 36.792271 | F12: 15232 | G12: 1648 | H12: 1444 | I12: =H12/G12*100 -> 87.621359 | J12: 28.732687 | K12: 12447 | L12: 1713 | M12: 1348 | N12: =M12/L12*100 -> 78.692353 | O12: 29.166667 | P12: 11795 | Q12: 1556 | R12: 1489 | S12: =R12/Q12*100 -> 95.694087 | T12: 19.860322 | U12: 8871.6058 | V12: 1860 | W12: 1860 | X12: =W12/V12*100 -> 100 | Y12: 25.785256 | Z12: 14388.173 | AA12: 1870 | AB12: 1870 | AC12: 100 | AD12: 33.220085 | AE12: 18636.468 | AF12: 1698 | AG12: 0 | AH12: 0 | AI12: 0 | AJ12: 0
A13: July | B13: 1542 | C13: 1380 | D13: =C13/B13*100 -> 89.494163 | E13: 34.382889 | F13: 14709 | G13: 1648 | H13: 1444 | I13: =H13/G13*100 -> 87.621359 | J13: 30.846216 | K13: 13808 | L13: 1713 | M13: 1509 | N13: =M13/L13*100 -> 88.091068 | O13: 37.749845 | P13: 17659 | Q13: 1588 | R13: 1544 | S13: =R13/Q13*100 -> 97.229219 | T13: 49.733545 | U13: 23804.464 | V13: 1860 | W13: 1860 | X13: =W13/V13*100 -> 100 | Y13: 32.903226 | Z13: 18972 | AA13: 1870 | AB13: 1772 | AC13: 94.759358 | AD13: 42.830645 | AE13: 23527.73 | AF13: 1698 | AG13: 252 | AH13: 14.840989 | AI13: 0 | AJ13: 0
A14: August | B14: 1542 | C14: 1380 | D14: =C14/B14*100 -> 89.494163 | E14: 45.261805 | F14: 19363 | G14: 1648 | H14: 1444 | I14: =H14/G14*100 -> 87.621359 | J14: 39.350818 | K14: 17615 | L14: 1713 | M14: 1509 | N14: =M14/L14*100 -> 88.091068 | O14: 41.890592 | P14: 19596 | Q14: 1588 | R14: 1490 | S14: =R14/Q14*100 -> 93.828715 | T14: 47.019584 | U14: 21718.346 | V14: 1860 | W14: 1860 | X14: =W14/V14*100 -> 100 | Y14: 34.723993 | Z14: 20021.854 | AA14: 1570 | AB14: 1472 | AC14: 93.757962 | AD14: 45.147849 | AE14: 20601.867 | AF14: 1698 | AG14: 956 | AH14: 56.301531 | AI14: 5.6451613 | AJ14: 1673
A15: September | B15: 1542 | C15: 1380 | D15: =C15/B15*100 -> 89.494163 | E15: 43.434783 | F15: 17982 | G15: 1648 | H15: 1444 | I15: =H15/G15*100 -> 87.621359 | J15: 32.689289 | K15: 14161 | L15: 1713 | M15: 1509 | N15: =M15/L15*100 -> 88.091068 | O15: 38.146676 | P15: 17269 | Q15: 1594 | R15: 1490 | S15: =R15/Q15*100 -> 93.475533 | T15: 36.073195 | U15: 16124.718 | V15: 1860 | W15: 1860 | X15: =W15/V15*100 -> 100 | Y15: 37.880717 | Z15: 21137.44 | AA15: 1570 | AB15: 1472 | AC15: 93.757962 | AD15: 42.861111 | AE15: 18927.467 | AF15: 1698 | AG15: 1318 | AH15: 77.62073 | AI15: 5.6497175 | AJ15: 2233.8983
A16: October | B16: 1542 | C16: 1380 | D16: =C16/B16*100 -> 89.494163 | E16: 41.206171 | F16: 17628 | G16: 1648 | H16: 1444 | I16: =H16/G16*100 -> 87.621359 | J16: 35.910553 | K16: 16075 | L16: 1713 | M16: 1509 | N16: =M16/L16*100 -> 88.091068 | O16: 40.069262 | P16: 18744 | Q16: 1594 | R16: 1490 | S16: =R16/Q16*100 -> 93.475533 | T16: 42.442941 | U16: 19604.394 | V16: 1858 | W16: 1858 | X16: =W16/V16*100 -> 100 | Y16: 39.569072 | Z16: 22790.994 | AA16: 1570 | AB16: 1472 | AC16: 93.757962 | AD16: 43.94086 | AE16: 20051.093 | AF16: 1698 | AG16: 1478 | AH16: 87.043581 | AI16: 7.1919619 | AJ16: 3295.2131
A17: November | B17: 1655 | C17: 1282 | D17: =C17/B17*100 -> 77.462236 | E17: 43.104524 | F17: 16578 | G17: 1648 | H17: 1444 | I17: =H17/G17*100 -> 87.621359 | J17: 39.506002 | K17: 17114 | L17: 1713 | M17: 1509 | N17: =M17/L17*100 -> 88.091068 | O17: 41.643472 | P17: 18852 | Q17: 1560 | R17: 1456 | S17: =R17/Q17*100 -> 93.333333 | T17: 37.616162 | U17: 16430.739 | V17: 1858 | W17: 1858 | X17: =W17/V17*100 -> 100 | Y17: 42.815934 | Z17: 23865.602 | AA17: 1642 | AB17: 1642 | AC17: 100 | AD17: 30.493301 | AE17: 15021 | AF17: 1698 | AG17: 1478 | AH17: 87.043581 | AI17: 13.875369 | AJ17: 6152.3385
A18: December | B18: 1704 | C18: 1493 | D18: =C18/B18*100 -> 87.617371 | E18: 40.468423 | F18: 18730 | G18: 1648 | H18: 1444 | I18: =H18/G18*100 -> 87.621359 | J18: 43.588598 | K18: 19512 | L18: 1713 | M18: 1509 | N18: =M18/L18*100 -> 88.091068 | O18: 46.166015 | P18: 21596 | Q18: 1456 | R18: 1456 | S18: =R18/Q18*100 -> 100 | T18: 48.611926 | U18: 21941.479 | V18: 1862 | W18: 1862 | X18: =W18/V18*100 -> 100 | Y18: 50.611292 | Z18: 29213.85 | AA18: 1642 | AB18: 1642 | AC18: 100 | AD18: 53.961429 | AE18: 27467.447 | AF18: 1698 | AG18: 1478 | AH18: 87.043581 | AI18: 28.678484 | AJ18: 13139.908
A19: Source: Ministry of Tourism | AJ19: cmwzirUT cfoa IrcTcsinim :ctWrwf ivcaed utWmUluAwm
A20: Note: Maldives border was closed for international visitirs on 27th March 2020 due to global COVID-19 outbreak and was re-opened on 15th July 2020
A21: Due to COVIC-19 pandamic, some tourists were unable to travel back to their home country. | AP21: Registered Bed Capacity | AQ21: Beds in operation
AO22: Jan | AP22: =AF7 -> 1698 | AQ22: =AG7 -> 1698
AO23: Feb | AP23: =AF8 -> 1698 | AQ23: =AG8 -> 1698
AO24: Mar | AP24: =AF9 -> 1698 | AQ24: =AG9 -> 1698
AO25: Apr | AP25: =AF10 -> 1698 | AQ25: =AG10 -> 336
AO26: May | AP26: =AF11 -> 1698 | AQ26: =AG11 -> 0
AO27: Jun | AP27: =AF12 -> 1698 | AQ27: =AG12 -> 0
AO28: Jul | AP28: =AF13 -> 1698 | AQ28: =AG13 -> 252
AO29: Aug | AP29: =AF14 -> 1698 | AQ29: =AG14 -> 956
AO30: Sep | AP30: =AF15 -> 1698 | AQ30: =AG15 -> 1318
AO31: Oct | AP31: =AF16 -> 1698 | AQ31: =AG16 -> 1478
AO32: Nov | AP32: =AF17 -> 1698 | AQ32: =AG17 -> 1478
AO33: Dec | AP33: =AF18 -> 1698 | AQ33: =AG18 -> 1478

Sheet 10.6
A1: 2020 - 2019 ,urwvcnim unuverukcnunEb wgWjegudnea iaWa wgWj egudnea egukwtcsuawhcTcseg uhwmcswmikea : 10.6 ulwvWt
A2: Table 10.6: BED CAPACITY AND UTILIZATION OF GUEST HOUSES BY MONTH, 2019 - 2020
A4: Month | B4: 2014 | G4: 2015 | L4: 2016 | Q4: 2017 | V4: 2018 | AA4: 2019 | AF4: 2020
B5: އެނދުގެ ޖާގަ | C5: ބޭނުންކުރެވުނު އެނދުގެ އަދަދު | D5: އެނދުގެ ޖާގައިން ބޭނުންކުރެވުނު މިންވަރު % | E5: އެނދުގެ ޖާގަ ބޭނުންކުރި މިންވަރު % | F5: ފަތުރުވެރިން ހޭދަކޮށްފައިވާ ރޭގެ އަދަދު | G5: އެނދުގެ ޖާގަ | H5: ބޭނުންކުރެވުނު އެނދުގެ އަދަދު | I5: އެނދުގެ ޖާގައިން ބޭނުންކުރެވުނު މިންވަރު % | J5: އެނދުގެ ޖާގަ ބޭނުންކުރި މިންވަރު % | K5: ފަތުރުވެރިން ހޭދަކޮށްފައިވާ ރޭގެ އަދަދު | L5: އެނދުގެ ޖާގަ | M5: ބޭނުންކުރެވުނު އެނދުގެ އަދަދު | N5: އެނދުގެ ޖާގައިން ބޭނުންކުރެވުނު މިންވަރު % | O5: އެނދުގެ ޖާގަ ބޭނުންކުރި މިންވަރު % | P5: ފަތުރުވެރިން ހޭދަކޮށްފައިވާ ރޭގެ އަދަދު | Q5: އެނދުގެ ޖާގަ | R5: ބޭނުންކުރެވުނު އެނދުގެ އަދަދު | S5: އެނދުގެ ޖާގައިން ބޭނުންކުރެވުނު މިންވަރު % | T5: އެނދުގެ ޖާގަ ބޭނުންކުރި މިންވަރު % | U5: ފަތުރުވެރިން ހޭދަކޮށްފައިވާ ރޭގެ އަދަދު | V5: އެނދުގެ ޖާގަ | W5: ބޭނުންކުރެވުނު އެނދުގެ އަދަދު | X5: އެނދުގެ ޖާގައިން ބޭނުންކުރެވުނު މިންވަރު % | Y5: އެނދުގެ ޖާގަ ބޭނުންކުރި މިންވަރު % | Z5: ފަތުރުވެރިން ހޭދަކޮށްފައިވާ ރޭގެ އަދަދު | AA5: އެނދުގެ ޖާގަ | AB5: ބޭނުންކުރެވުނު އެނދުގެ އަދަދު | AC5: އެނދުގެ ޖާގައިން ބޭނުންކުރެވުނު މިންވަރު % | AD5: އެނދުގެ ޖާގަ ބޭނުންކުރި މިންވަރު % | AE5: ފަތުރުވެރިން ހޭދަކޮށްފައިވާ ރޭގެ އަދަދު | AF5: އެނދުގެ ޖާގަ | AG5: ބޭނުންކުރެވުނު އެނދުގެ އަދަދު | AH5: އެނދުގެ ޖާގައިން ބޭނުންކުރެވުނު މިންވަރު % | AI5: އެނދުގެ ޖާގަ ބޭނުންކުރި މިންވަރު % | AJ5: ފަތުރުވެރިން ހޭދަކޮށްފައިވާ ރޭގެ އަދަދު
B6: Registered Bed Capacity | C6: Beds in operation | D6: % share of registered beds in operation | E6: Bed Capacity Utilization Rate % | F6: Tourist Bednights | G6: Registered Bed Capacity | H6: Beds in operation | I6: % share of registered beds in operation | J6: Bed Capacity Utilization Rate % | K6: Tourist Bednights | L6: Registered Bed Capacity | M6: Beds in operation | N6: % share of registered beds in operation | O6: Bed Capacity Utilization Rate % | P6: Tourist Bednights | Q6: Registered Bed Capacity | R6: Beds in operation | S6: % share of registered beds in operation | T6: Bed Capacity Utilization Rate % | U6: Tourist Bednights | V6: Registered Bed Capacity | W6: Beds in operation | X6: % share of registered beds in operation | Y6: Bed Capacity Utilization Rate % | Z6: Tourist Bednights | AA6: Registered Bed Capacity | AB6: Beds in operation | AC6: % share of registered beds in operation | AD6: Bed Capacity Utilization Rate % | AE6: Tourist Bednights | AF6: Registered Bed Capacity | AG6: Beds in operation | AH6: % share of registered beds in operation | AI6: Bed Capacity Utilization Rate % | AJ6: Tourist Bednights
A7: Annual Average | B7: =AVERAGE(B8:B19) -> 2533.4167 | C7: =AVERAGE(C8:C19) -> 2477.25 | D7: =AVERAGE(D8:D19) -> 97.778892 | E7: =AVERAGE(E8:E19) -> 18.290859 | F7: =SUM(F8:F19) -> 160804.69 | G7: =AVERAGE(G8:G19) -> 3971 | H7: =AVERAGE(H8:H19) -> 3831.1667 | I7: =AVERAGE(I8:I19) -> 96.508471 | J7: =AVERAGE(J8:J19) -> 23.754187 | K7: =SUM(K8:K19) -> 331839.67 | L7: =AVERAGE(L8:L19) -> 5392.5 | M7: =AVERAGE(M8:M19) -> 5248.9167 | N7: =AVERAGE(N8:N19) -> 97.395375 | O7: =AVERAGE(O8:O19) -> 33.51556 | P7: =SUM(P8:P19) -> 644472.93 | Q7: =AVERAGE(Q8:Q19) -> 6778.0833 | R7: =AVERAGE(R8:R19) -> 6728.8333 | S7: =AVERAGE(S8:S19) -> 99.211683 | T7: =AVERAGE(T8:T19) -> 30.768032 | U7: =SUM(U8:U19) -> 751079.83 | V7: =AVERAGE(V8:V19) -> 8017.25 | W7: =AVERAGE(W8:W19) -> 8000 | X7: =AVERAGE(X8:X19) -> 99.794445 | Y7: =AVERAGE(Y8:Y19) -> 32.573453 | Z7: =SUM(Z8:Z19) -> 944521.4 | AA7: =AVERAGE(AA8:AA19) -> 9210.1667 | AB7: =AVERAGE(AB8:AB19) -> 9200.1667 | AC7: =AVERAGE(AC8:AC19) -> 99.891364 | AD7: =AVERAGE(AD8:AD19) -> 33.867677 | AE7: =SUM(AE8:AE19) -> 1128597.2 | AF7: =AVERAGE(AF8:AF19) -> 10154.333 | AG7: =AVERAGE(AG8:AG19) -> 3615.0833 | AH7: =AVERAGE(AH8:AH19) -> 35.745578 | AI7: =AVERAGE(AI8:AI19) -> 18.371216 | AJ7: =SUM(AJ8:AJ19) -> 408938.6
A8: January | B8: 1996 | C8: 1912 | D8: =C8/B8*100 -> 95.791583 | E8: 25.663683 | F8: 15211.378 | G8: 3379 | H8: 3309 | I8: =H8/G8*100 -> 97.928381 | J8: 28.220153 | K8: 28947.95 | L8: 4799 | M8: 4765 | N8: =M8/L8*100 -> 99.291519 | O8: 32.640828 | P8: 48215.399 | Q8: 6134 | R8: 5717 | S8: =R8/Q8*100 -> 93.201826 | T8: 35.109388 | U8: 62223.316 | V8: 7464 | W8: 7464 | X8: =W8/V8*100 -> 100 | Y8: 44.88724 | Z8: 103861.89 | AA8: 8611 | AB8: 8601 | AC8: 99.883869 | AD8: 47.683582 | AE8: 127139.21 | AF8: 9927 | AG8: 9917 | AH8: 99.899265 | AI8: 48.320667 | AJ8: 148550.78
A9: February | B9: 2066 | C9: 2006 | D9: =C9/B9*100 -> 97.095837 | E9: 27.443395 | F9: 15414.406 | G9: 3385 | H9: 3265 | I9: =H9/G9*100 -> 96.454948 | J9: 30.232929 | K9: 27638.944 | L9: 4907 | M9: 4855 | N9: =M9/L9*100 -> 98.940289 | O9: 43.111789 | P9: 60699.243 | Q9: 6336 | R9: 6245 | S9: =R9/Q9*100 -> 98.563763 | T9: 43.470755 | U9: 76012.962 | V9: 7528 | W9: 7528 | X9: =W9/V9*100 -> 100 | Y9: 48.9503 | Z9: 103179.4 | AA9: 8895 | AB9: 8885 | AC9: 99.887577 | AD9: 52.778828 | AE9: 131303.17 | AF9: 10037 | AG9: 10027 | AH9: 99.900369 | AI9: 43.164473 | AJ9: 125514.95
A10: March | B10: 2224 | C10: 2206 | D10: =C10/B10*100 -> 99.190647 | E10: 24.985054 | F10: 17086.279 | G10: 3555 | H10: 3447 | I10: =H10/G10*100 -> 96.962025 | J10: 25.635743 | K10: 27393.586 | L10: 5085 | M10: 4963 | N10: =M10/L10*100 -> 97.600787 | O10: 38.107961 | P10: 58630.242 | Q10: 6398 | R10: 6381 | S10: =R10/Q10*100 -> 99.734292 | T10: 37.885077 | U10: 74940.85 | V10: 7750 | W10: 7750 | X10: =W10/V10*100 -> 100 | Y10: 38.764922 | Z10: 93132.725 | AA10: 8981 | AB10: 8971 | AC10: 99.888654 | AD10: 44.268487 | AE10: 123111.11 | AF10: 10093 | AG10: 10075 | AH10: 99.821659 | AI10: 19.435526 | AJ10: 60702.006
A11: April | B11: 2321 | C11: 2297 | D11: =C11/B11*100 -> 98.965963 | E11: 24.343891 | F11: 16775.376 | G11: 3695 | H11: 3563 | I11: =H11/G11*100 -> 96.427605 | J11: 25.353972 | K11: 27100.86 | L11: 5143 | M11: 5051 | N11: =M11/L11*100 -> 98.211161 | O11: 35.206282 | P11: 53348.079 | Q11: 6431 | R11: 6425 | S11: =R11/Q11*100 -> 99.906702 | T11: 32.134781 | U11: 61939.79 | V11: 7922 | W11: 7922 | X11: =W11/V11*100 -> 100 | Y11: 30.592478 | Z11: 72706.083 | AA11: 9047 | AB11: 9037 | AC11: 99.889466 | AD11: 39.530061 | AE11: 107169.95 | AF11: 10093 | AG11: 266 | AH11: 2.6354899 | AI11: 7.9072682 | AJ11: 631
A12: May | B12: 2385 | C12: 2361 | D12: =C12/B12*100 -> 98.993711 | E12: 14.651264 | F12: 10723.407 | G12: 3885 | H12: 3757 | I12: =H12/G12*100 -> 96.705277 | J12: 18.532126 | K12: 21583.811 | L12: 5207 | M12: 5121 | N12: =M12/L12*100 -> 98.348377 | O12: 24.966582 | P12: 39634.698 | Q12: 6598 | R12: 6589 | S12: =R12/Q12*100 -> 99.863595 | T12: 22.418999 | U12: 45792.823 | V12: 7948 | W12: 7948 | X12: =W12/V12*100 -> 100 | Y12: 22.085715 | Z12: 54416.553 | AA12: 9073 | AB12: 9063 | AC12: 99.889783 | AD12: 24.333647 | AE12: 68366.111 | AF12: 10093 | AG12: 74 | AH12: 0.73318141 | AI12: 4.7079337 | AJ12: 108
A13: June | B13: 2439 | C13: 2349 | D13: =C13/B13*100 -> 96.309963 | E13: 13.446727 | F13: 9475.9082 | G13: 3927 | H13: 3805 | I13: =H13/G13*100 -> 96.893303 | J13: 14.56474 | K13: 16625.651 | L13: 5365 | M13: 5231 | N13: =M13/L13*100 -> 97.50233 | O13: 19.553991 | P13: 30686.077 | Q13: 6717 | R13: 6711 | S13: =R13/Q13*100 -> 99.910674 | T13: 19.082403 | U13: 38418.603 | V13: 8006 | W13: 7998 | X13: =W13/V13*100 -> 99.900075 | Y13: 22.764137 | Z13: 54620.27 | AA13: 9125 | AB13: 9115 | AC13: 99.890411 | AD13: 22.651515 | AE13: 61940.568 | AF13: 10085 | AG13: 74 | AH13: 0.73376301 | AI13: 3.1081081 | AJ13: 69
A14: July | B14: 2609 | C14: 2567 | D14: =C14/B14*100 -> 98.390188 | E14: 13.407794 | F14: 10669.52 | G14: 3973 | H14: 3801 | I14: =H14/G14*100 -> 95.670778 | J14: 17.604229 | K14: 20743.239 | L14: 5438 | M14: 5267 | N14: =M14/L14*100 -> 96.855462 | O14: 28.652158 | P14: 46782.384 | Q14: 6914 | R14: 6893 | S14: =R14/Q14*100 -> 99.696268 | T14: 30.399153 | U14: 64957.822 | V14: 8098 | W14: 8090 | X14: =W14/V14*100 -> 99.90121 | Y14: 28.928325 | Z14: 72549.347 | AA14: 9221 | AB14: 9211 | AC14: 99.891552 | AD14: 21.885118 | AE14: 62490.985 | AF14: 10111 | AG14: 192 | AH14: 1.898922 | AI14: 6.1323925 | AJ14: 365
A15: August | B15: 2667 | C15: 2625 | D15: =C15/B15*100 -> 98.425197 | E15: 16.915697 | F15: 13765.149 | G15: 4135 | H15: 3963 | I15: =H15/G15*100 -> 95.840387 | J15: 25.160866 | K15: 30910.878 | L15: 5574 | M15: 5255 | N15: =M15/L15*100 -> 94.277 | O15: 32.957511 | P15: 53689.434 | Q15: 6987 | R15: 6981 | S15: =R15/Q15*100 -> 99.914126 | T15: 31.339917 | U15: 67823.029 | V15: 8134 | W15: 8112 | X15: =W15/V15*100 -> 99.72953 | Y15: 32.908999 | Z15: 82756.917 | AA15: 9313 | AB15: 9303 | AC15: 99.892623 | AD15: 32.68854 | AE15: 94271.461 | AF15: 10133 | AG15: 676 | AH15: 6.6712721 | AI15: 22.620968 | AJ15: 4740.45
A16: September | B16: 2729 | C16: 2671 | D16: =C16/B16*100 -> 97.874679 | E16: 11.256246 | F16: 9019.6296 | G16: 4255 | H16: 4095 | I16: =H16/G16*100 -> 96.239718 | J16: 18.418042 | K16: 22626.564 | L16: 5622 | M16: 5463 | N16: =M16/L16*100 -> 97.171825 | O16: 32.078978 | P16: 52574.237 | Q16: 7009 | R16: 7003 | S16: =R16/Q16*100 -> 99.914396 | T16: 22.481022 | U16: 47230.38 | V16: 8208 | W16: 8200 | X16: =W16/V16*100 -> 99.902534 | Y16: 25.14696 | Z16: 61861.521 | AA16: 9415 | AB16: 9405 | AC16: 99.893787 | AD16: 23.778213 | AE16: 67090.228 | AF16: 10115 | AG16: 1002 | AH16: 9.9060801 | AI16: 13.274232 | AJ16: 3990.234
A17: October | B17: 2782 | C17: 2722 | D17: =C17/B17*100 -> 97.843278 | E17: 13.170223 | F17: 11113.297 | G17: 4349 | H17: 4175 | I17: =H17/G17*100 -> 95.99908 | J17: 22.28364 | K17: 28840.601 | L17: 5652 | M17: 5503 | N17: =M17/L17*100 -> 97.363765 | O17: 36.007219 | P17: 61425.794 | Q17: 7149 | R17: 7143 | S17: =R17/Q17*100 -> 99.916072 | T17: 27.200701 | U17: 60231.329 | V17: 8294 | W17: 8286 | X17: =W17/V17*100 -> 99.903545 | Y17: 25.171559 | Z17: 64657.176 | AA17: 9525 | AB17: 9515 | AC17: 99.895013 | AD17: 25.389397 | AE17: 74889.836 | AF17: 10411 | AG17: 2256 | AH17: 21.669388 | AI17: 13.477684 | AJ17: 9425.7534
A18: November | B18: 2984 | C18: 2914 | D18: =C18/B18*100 -> 97.654155 | E18: 15.024267 | F18: 13134.214 | G18: 4493 | H18: 4339 | I18: =H18/G18*100 -> 96.572446 | J18: 26.652216 | K18: 34693.189 | L18: 5884 | M18: 5633 | N18: =M18/L18*100 -> 95.734194 | O18: 37.906863 | P18: 64058.807 | Q18: 7360 | R18: 7354 | S18: =R18/Q18*100 -> 99.918478 | T18: 30.443777 | U18: 67165.061 | V18: 8292 | W18: 8248 | X18: =W18/V18*100 -> 99.469368 | Y18: 30.452926 | Z18: 75352.721 | AA18: 9563 | AB18: 9553 | AC18: 99.89543 | AD18: 31.740818 | AE18: 90966.011 | AF18: 10411 | AG18: 3434 | AH18: 32.984343 | AI18: 14.278253 | AJ18: 14709.456
A19: December | B19: 3199 | C19: 3097 | D19: =C19/B19*100 -> 96.811504 | E19: 19.18207 | F19: 18416.13 | G19: 4621 | H19: 4455 | I19: =H19/G19*100 -> 96.407704 | J19: 32.391583 | K19: 44734.396 | L19: 6034 | M19: 5880 | N19: =M19/L19*100 -> 97.447796 | O19: 40.99656 | P19: 74728.53 | Q19: 7304 | R19: 7304 | S19: =R19/Q19*100 -> 100 | T19: 37.250408 | U19: 84343.863 | V19: 8563 | W19: 8454 | X19: =W19/V19*100 -> 98.727082 | Y19: 40.227872 | Z19: 105426.79 | AA19: 9753 | AB19: 9743 | AC19: 99.898198 | AD19: 39.683914 | AE19: 119858.52 | AF19: 10343 | AG19: 5388 | AH19: 52.093203 | AI19: 24.027092 | AJ19: 40131.972
A20: Source: Ministry of Tourism | AJ20: cmwzirUT cfoa IrcTcsinim :ctWrwf ivcaed utWmUluAwm | AO20: Registered Bed Capacity | AP20: Beds in operation
A21: Note: Maldives border was closed for international visitirs on 27th March 2020 due to global COVID-19 outbreak and was re-opened on 15th July 2020 | AN21: Jan | AO21: =AF8 -> 9927 | AP21: =AG8 -> 9917
A22: Due to COVIC-19 pandamic, some tourists were unable to travel back to their home country. | AN22: Feb | AO22: =AF9 -> 10037 | AP22: =AG9 -> 10027
AN23: Mar | AO23: =AF10 -> 10093 | AP23: =AG10 -> 10075
AN24: Apr | AO24: =AF11 -> 10093 | AP24: =AG11 -> 266
AN25: May | AO25: =AF12 -> 10093 | AP25: =AG12 -> 74
AN26: Jun | AO26: =AF13 -> 10085 | AP26: =AG13 -> 74
AN27: Jul | AO27: =AF14 -> 10111 | AP27: =AG14 -> 192
AN28: Aug | AO28: =AF15 -> 10133 | AP28: =AG15 -> 676
AN29: Sep | AO29: =AF16 -> 10115 | AP29: =AG16 -> 1002
AN30: Oct | AO30: =AF17 -> 10411 | AP30: =AG17 -> 2256
AN31: Nov | AO31: =AF18 -> 10411 | AP31: =AG18 -> 3434
AN32: Dec | AO32: =AF19 -> 10343 | AP32: =AG19 -> 5388

Sheet 10.7
A1: 2020 - 2019 ,urwvcnim unuverukcnunEb wgWj egudnea iaWa wgWj eg udnea egukwtudnwLua IrWfws uhwmcswmikea : 10.7 ulwvWt
A2: Table 10.7: BED CAPACITY AND UTILIZATION OF SAFARI VESSELS BY MONTH, 2019 - 2020
A3: Month | B3: 2014 | G3: 2015 | L3: 2016 | Q3: 2017 | V3: 2018 | AA3: 2019 | AF3: 2020
B4: އެނދުގެ ޖާގަ | C4: ބޭނުންކުރެވުނު އެނދުގެ އަދަދު | D4: އެނދުގެ ޖާގައިން ބޭނުންކުރެވުނު މިންވަރު % | E4: އެނދުގެ ޖާގަ ބޭނުންކުރި މިންވަރު % | F4: ފަތުރުވެރިން ހޭދަކޮށްފައިވާ ރޭގެ އަދަދު | G4: އެނދުގެ ޖާގަ | H4: ބޭނުންކުރެވުނު އެނދުގެ އަދަދު | I4: އެނދުގެ ޖާގައިން ބޭނުންކުރެވުނު މިންވަރު % | J4: އެނދުގެ ޖާގަ ބޭނުންކުރި މިންވަރު % | K4: ފަތުރުވެރިން ހޭދަކޮށްފައިވާ ރޭގެ އަދަދު | L4: އެނދުގެ ޖާގަ | M4: ބޭނުންކުރެވުނު އެނދުގެ އަދަދު | N4: އެނދުގެ ޖާގައިން ބޭނުންކުރެވުނު މިންވަރު % | O4: އެނދުގެ ޖާގަ ބޭނުންކުރި މިންވަރު % | P4: ފަތުރުވެރިން ހޭދަކޮށްފައިވާ ރޭގެ އަދަދު | Q4: އެނދުގެ ޖާގަ | R4: ބޭނުންކުރެވުނު އެނދުގެ އަދަދު | S4: އެނދުގެ ޖާގައިން ބޭނުންކުރެވުނު މިންވަރު % | T4: އެނދުގެ ޖާގަ ބޭނުންކުރި މިންވަރު % | U4: ފަތުރުވެރިން ހޭދަކޮށްފައިވާ ރޭގެ އަދަދު | V4: އެނދުގެ ޖާގަ | W4: ބޭނުންކުރެވުނު އެނދުގެ އަދަދު | X4: އެނދުގެ ޖާގައިން ބޭނުންކުރެވުނު މިންވަރު % | Y4: އެނދުގެ ޖާގަ ބޭނުންކުރި މިންވަރު % | Z4: ފަތުރުވެރިން ހޭދަކޮށްފައިވާ ރޭގެ އަދަދު | AA4: އެނދުގެ ޖާގަ | AB4: ބޭނުންކުރެވުނު އެނދުގެ އަދަދު | AC4: އެނދުގެ ޖާގައިން ބޭނުންކުރެވުނު މިންވަރު % | AD4: އެނދުގެ ޖާގަ ބޭނުންކުރި މިންވަރު % | AE4: ފަތުރުވެރިން ހޭދަކޮށްފައިވާ ރޭގެ އަދަދު | AF4: އެނދުގެ ޖާގަ | AG4: ބޭނުންކުރެވުނު އެނދުގެ އަދަދު | AH4: އެނދުގެ ޖާގައިން ބޭނުންކުރެވުނު މިންވަރު % | AI4: އެނދުގެ ޖާގަ ބޭނުންކުރި މިންވަރު % | AJ4: ފަތުރުވެރިން ހޭދަކޮށްފައިވާ ރޭގެ އަދަދު
B5: Registered Bed Capacity | C5: Beds in operation | D5: % share of registered beds in operation | E5: Bed Capacity Utilization Rate % | F5: Tourist Bednights | G5: Registered Bed Capacity | H5: Beds in operation | I5: % share of registered beds in operation | J5: Bed Capacity Utilization Rate % | K5: Tourist Bednights | L5: Registered Bed Capacity | M5: Beds in operation | N5: % share of registered beds in operation | O5: Bed Capacity Utilization Rate % | P5: Tourist Bednights | Q5: Registered Bed Capacity | R5: Beds in operation | S5: % share of registered beds in operation | T5: Bed Capacity Utilization Rate % | U5: Tourist Bednights | V5: Registered Bed Capacity | W5: Beds in operation | X5: % share of registered beds in operation | Y5: Bed Capacity Utilization Rate % | Z5: Tourist Bednights | AA5: Registered Bed Capacity | AB5: Beds in operation | AC5: % share of registered beds in operation | AD5: Bed Capacity Utilization Rate % | AE5: Tourist Bednights | AF5: Registered Bed Capacity | AG5: Beds in operation | AH5: % share of registered beds in operation | AI5: Bed Capacity Utilization Rate % | AJ5: Tourist Bednights
A6: Annual Average | B6: =AVERAGE(B7:B18) -> 2711.3333 | C6: =AVERAGE(C7:C18) -> 2616.5833 | D6: =AVERAGE(D7:D18) -> 96.505373 | E6: =AVERAGE(E7:E18) -> 26.948089 | F6: =SUM(F7:F18) -> 256239.57 | G6: =AVERAGE(G7:G18) -> 2905.0833 | H6: =AVERAGE(H7:H18) -> 2788.1667 | I6: =AVERAGE(I7:I18) -> 95.975156 | J6: =AVERAGE(J7:J18) -> 29.175364 | K6: =SUM(K7:K18) -> 296621.04 | L6: =AVERAGE(L7:L18) -> 2561.75 | M6: =AVERAGE(M7:M18) -> 2520.1667 | N6: =AVERAGE(N7:N18) -> 98.348215 | O6: =AVERAGE(O7:O18) -> 28.964643 | P6: =SUM(P7:P18) -> 263842.72 | Q6: =AVERAGE(Q7:Q18) -> 2728.25 | R6: =AVERAGE(R7:R18) -> 2680.75 | S6: =AVERAGE(S7:S18) -> 98.258836 | T6: =AVERAGE(T7:T18) -> 26.385018 | U6: =SUM(U7:U18) -> 256783.1 | V6: =AVERAGE(V7:V18) -> 2729.1667 | W6: =AVERAGE(W7:W18) -> 2728 | X6: =AVERAGE(X7:X18) -> 99.95756 | Y6: =AVERAGE(Y7:Y18) -> 28.109894 | Z6: =SUM(Z7:Z18) -> 277720.49 | AA6: =AVERAGE(AA7:AA18) -> 2922.5 | AB6: =AVERAGE(AB7:AB18) -> 2905.5833 | AC6: =AVERAGE(AC7:AC18) -> 99.42193 | AD6: =AVERAGE(AD7:AD18) -> 26.15365 | AE6: =SUM(AE7:AE18) -> 276239.5 | AF6: =AVERAGE(AF7:AF18) -> 2922.4167 | AG6: =AVERAGE(AG7:AG18) -> 1651.4167 | AH6: =AVERAGE(AH7:AH18) -> 35.745578 | AI6: =AVERAGE(AI7:AI18) -> 18.371216 | AJ6: =SUM(AJ7:AJ18) -> 118380.72
A7: January | B7: 2706 | C7: 2579 | D7: =C7/B7*100 -> 95.306726 | E7: 24.875685 | F7: 19887.862 | G7: 2861 | H7: 2765 | I7: =H7/G7*100 -> 96.64453 | J7: 36.877545 | K7: 31609.587 | L7: 2453 | M7: 2353 | N7: =M7/L7*100 -> 95.923359 | O7: 43.116712 | P7: 31450.623 | Q7: 2748 | R7: 2691 | S7: =R7/Q7*100 -> 97.925764 | T7: 34.394757 | U7: 28692.451 | V7: 2619 | W7: 2619 | X7: =W7/V7*100 -> 100 | Y7: 34.710268 | Z7: 28180.919 | AA7: 2879 | AB7: 2865 | AC7: 99.51372 | AD7: 32.349116 | AE7: 28730.867 | AF7: 2997 | AG7: 2970 | AH7: 99.899265 | AI7: 48.320667 | AJ7: 31667.826
A8: February | B8: 2706 | C8: 2594 | D8: =C8/B8*100 -> 95.86105 | E8: 45.687061 | F8: 33183.426 | G8: 2886 | H8: 2788 | I8: =H8/G8*100 -> 96.604297 | J8: 46.667144 | K8: 36430.239 | L8: 2453 | M8: 2354 | N8: =M8/L8*100 -> 95.964126 | O8: 48.473004 | P8: 33090.581 | Q8: 2703 | R8: 2647 | S8: =R8/Q8*100 -> 97.928228 | T8: 38.254928 | U8: 28353.023 | V8: 2663 | W8: 2663 | X8: =W8/V8*100 -> 100 | Y8: 43.641398 | Z8: 32540.772 | AA8: 2879 | AB8: 2865 | AC8: 99.51372 | AD8: 40.094852 | AE8: 32164.09 | AF8: 3006 | AG8: 2979 | AH8: 99.900369 | AI8: 43.164473 | AJ8: 33893.246
A9: March | B9: 2706 | C9: 2620 | D9: =C9/B9*100 -> 96.821877 | E9: 49.695941 | F9: 40363.043 | G9: 2923 | H9: 2825 | I9: =H9/G9*100 -> 96.64728 | J9: 47.292053 | K9: 41416.015 | L9: 2487 | M9: 2397 | N9: =M9/L9*100 -> 96.381182 | O9: 46.904408 | P9: 34853.259 | Q9: 2738 | R9: 2675 | S9: =R9/Q9*100 -> 97.69905 | T9: 40.594606 | U9: 33663.077 | V9: 2663 | W9: 2663 | X9: =W9/V9*100 -> 100 | Y9: 43.597124 | Z9: 35990.734 | AA9: 2901 | AB9: 2887 | AC9: 99.517408 | AD9: 40.852167 | AE9: 36561.464 | AF9: 3006 | AG9: 3006 | AH9: 99.821659 | AI9: 19.435526 | AJ9: 18124.181
A10: April | B10: 2706 | C10: 2620 | D10: =C10/B10*100 -> 96.821877 | E10: 38.130552 | F10: 29970.614 | G10: 2917 | H10: 2815 | I10: =H10/G10*100 -> 96.503257 | J10: 42.333619 | K10: 35750.741 | L10: 2539 | M10: 2527 | N10: =M10/L10*100 -> 99.527373 | O10: 36.980374 | P10: 28034.822 | Q10: 2738 | R10: 2675 | S10: =R10/Q10*100 -> 97.69905 | T10: 36.021991 | U10: 28907.648 | V10: 2719 | W10: 2719 | X10: =W10/V10*100 -> 100 | Y10: 38.759369 | Z10: 31616.017 | AA10: 2925 | AB10: 2911 | AC10: 99.521368 | AD10: 36.634569 | AE10: 31992.969 | AF10: 3006 | AG10: 24 | AH10: 2.6354899 | AI10: 7.9072682 | AJ10: 30
A11: May | B11: 2706 | C11: 2620 | D11: =C11/B11*100 -> 96.821877 | E11: 17.444128 | F11: 14168.121 | G11: 2898 | H11: 2800 | I11: =H11/G11*100 -> 96.618357 | J11: 21.355264 | K11: 18536.369 | L11: 2567 | M11: 2553 | N11: =M11/L11*100 -> 99.454616 | O11: 19.1067 | P11: 15121.615 | Q11: 2748 | R11: 2716 | S11: =R11/Q11*100 -> 98.835517 | T11: 18.52223 | U11: 15594.977 | V11: 2741 | W11: 2741 | X11: =W11/V11*100 -> 100 | Y11: 19.317641 | Z11: 16414.393 | AA11: 2925 | AB11: 2911 | AC11: 99.521368 | AD11: 20.019074 | AE11: 18065.412 | AF11: 3006 | AG11: 0 | AH11: 0.73318141 | AI11: 4.7079337 | AJ11: 0
A12: June | B12: 2706 | C12: 2620 | D12: =C12/B12*100 -> 96.821877 | E12: 6.1425577 | F12: 4828.0503 | G12: 2886 | H12: 2750 | I12: =H12/G12*100 -> 95.287595 | J12: 7.0737425 | K12: 5835.8376 | L12: 2583 | M12: 2521 | N12: =M12/L12*100 -> 97.59969 | O12: 8.9965013 | P12: 6804.0539 | Q12: 2748 | R12: 2726 | S12: =R12/Q12*100 -> 99.199418 | T12: 9.8514851 | U12: 8056.5446 | V12: 2749 | W12: 2735 | X12: =W12/V12*100 -> 99.490724 | Y12: 11.380729 | Z12: 9337.8878 | AA12: 2925 | AB12: 2911 | AC12: 99.521368 | AD12: 8.6579433 | AE12: 7560.9819 | AF12: 2982 | AG12: 0 | AH12: 0.73376301 | AI12: 3.1081081 | AJ12: 0
A13: July | B13: 2706 | C13: 2620 | D13: =C13/B13*100 -> 96.821877 | E13: 11.226459 | F13: 9118.1297 | G13: 2886 | H13: 2731 | I13: =H13/G13*100 -> 94.629245 | J13: 13.317581 | K13: 11274.797 | L13: 2583 | M13: 2561 | N13: =M13/L13*100 -> 99.148277 | O13: 11.75424 | P13: 9331.8088 | Q13: 2748 | R13: 2700 | S13: =R13/Q13*100 -> 98.253275 | T13: 12.746793 | U13: 10669.066 | V13: 2764 | W13: 2764 | X13: =W13/V13*100 -> 100 | Y13: 13.563614 | Z13: 11621.847 | AA13: 2903 | AB13: 2889 | AC13: 99.51774 | AD13: 11.267037 | AE13: 10090.646 | AF13: 2905 | AG13: 197 | AH13: 1.898922 | AI13: 6.1323925 | AJ13: 215
A14: August | B14: 2706 | C14: 2620 | D14: =C14/B14*100 -> 96.821877 | E14: 18.533266 | F14: 15052.719 | G14: 2886 | H14: 2757 | I14: =H14/G14*100 -> 95.530146 | J14: 21.355602 | K14: 18251.992 | L14: 2583 | M14: 2573 | N14: =M14/L14*100 -> 99.612853 | O14: 22.551569 | P14: 17987.808 | Q14: 2733 | R14: 2625 | S14: =R14/Q14*100 -> 96.048299 | T14: 21.34696 | U14: 17371.089 | V14: 2764 | W14: 2764 | X14: =W14/V14*100 -> 100 | Y14: 22.089795 | Z14: 18927.42 | AA14: 2926 | AB14: 2905 | AC14: 99.282297 | AD14: 20.965341 | AE14: 18880.337 | AF14: 2916 | AG14: 1409 | AH14: 6.6712721 | AI14: 22.620968 | AJ14: 2303.9451
A15: September | B15: 2711 | C15: 2625 | D15: =C15/B15*100 -> 96.827739 | E15: 15.510732 | F15: 12214.701 | G15: 2905 | H15: 2776 | I15: =H15/G15*100 -> 95.55938 | J15: 21.608997 | K15: 17995.972 | L15: 2583 | M15: 2559 | N15: =M15/L15*100 -> 99.070848 | O15: 20.961875 | P15: 16092.431 | Q15: 2759 | R15: 2724 | S15: =R15/Q15*100 -> 98.731424 | T15: 18.83457 | U15: 15391.611 | V15: 2769 | W15: 2769 | X15: =W15/V15*100 -> 100 | Y15: 23.86614 | Z15: 19825.603 | AA15: 2930 | AB15: 2909 | AC15: 99.283276 | AD15: 23.062305 | AE15: 20126.474 | AF15: 2876 | AG15: 2086 | AH15: 9.9060801 | AI15: 13.274232 | AJ15: 4475.1151
A16: October | B16: 2671 | C16: 2572 | D16: =C16/B16*100 -> 96.293523 | E16: 30.159061 | F16: 24046.422 | G16: 2935 | H16: 2825 | I16: =H16/G16*100 -> 96.252129 | J16: 28.186504 | K16: 24684.331 | L16: 2608 | M16: 2586 | N16: =M16/L16*100 -> 99.156442 | O16: 26.895113 | P16: 21560.737 | Q16: 2779 | R16: 2757 | S16: =R16/Q16*100 -> 99.208348 | T16: 26.444009 | U16: 22600.901 | V16: 2769 | W16: 2769 | X16: =W16/V16*100 -> 100 | Y16: 29.74977 | Z16: 25536.905 | AA16: 2957 | AB16: 2936 | AC16: 99.289821 | AD16: 25.478427 | AE16: 23189.445 | AF16: 2858 | AG16: 2286 | AH16: 21.669388 | AI16: 13.477684 | AJ16: 7406.5844
A17: November | B17: 2767 | C17: 2668 | D17: =C17/B17*100 -> 96.422118 | E17: 33.050314 | F17: 26453.472 | G17: 2939 | H17: 2813 | I17: =H17/G17*100 -> 95.712827 | J17: 35.778026 | K17: 30193.076 | L17: 2608 | M17: 2586 | N17: =M17/L17*100 -> 99.156442 | O17: 32.451759 | P17: 25176.075 | Q17: 2779 | R17: 2747 | S17: =R17/Q17*100 -> 98.848507 | T17: 28.916553 | U17: 23830.132 | V17: 2772 | W17: 2772 | X17: =W17/V17*100 -> 100 | Y17: 29.963028 | Z17: 24917.254 | AA17: 2957 | AB17: 2936 | AC17: 99.289821 | AD17: 25.448536 | AE17: 22415.071 | AF17: 2859 | AG17: 2330 | AH17: 32.984343 | AI17: 14.278253 | AJ17: 7804.5159
A18: December | B18: 2739 | C18: 2641 | D18: =C18/B18*100 -> 96.422052 | E18: 32.921314 | F18: 26953.009 | G18: 2939 | H18: 2813 | I18: =H18/G18*100 -> 95.712827 | J18: 28.258294 | K18: 24642.08 | L18: 2694 | M18: 2672 | N18: =M18/L18*100 -> 99.18337 | O18: 29.383455 | P18: 24338.903 | Q18: 2518 | R18: 2486 | S18: =R18/Q18*100 -> 98.72915 | T18: 30.691337 | U18: 23652.586 | V18: 2758 | W18: 2758 | X18: =W18/V18*100 -> 100 | Y18: 26.679852 | Z18: 22810.74 | AA18: 2963 | AB18: 2942 | AC18: 99.291259 | AD18: 29.014436 | AE18: 26461.746 | AF18: 2652 | AG18: 2530 | AH18: 52.093203 | AI18: 24.027092 | AJ18: 12460.309
A19: Source: Ministry of Tourism | AJ19: cmwzirUT cfoa IrcTcsinim :ctWrwf ivcaed utWmUluAwm
A20: Note: Maldives border was closed for international visitirs on 27th March 2020 due to global COVID-19 outbreak and was re-opened on 15th July 2020 | AP20: Registered Bed Capacity | AQ20: Beds in operation
A21: Due to COVIC-19 pandamic, some tourists were unable to travel back to their home country. | AO21: Jan | AP21: =AF7 -> 2997 | AQ21: =AG7 -> 2970
AO22: Feb | AP22: =AF8 -> 3006 | AQ22: =AG8 -> 2979
AO23: Mar | AP23: =AF9 -> 3006 | AQ23: =AG9 -> 3006
AO24: Apr | AP24: =AF10 -> 3006 | AQ24: =AG10 -> 24
AO25: May | AP25: =AF11 -> 3006 | AQ25: =AG11 -> 0
AO26: Jun | AP26: =AF12 -> 2982 | AQ26: =AG12 -> 0
AO27: Jul | AP27: =AF13 -> 2905 | AQ27: =AG13 -> 197
AO28: Aug | AP28: =AF14 -> 2916 | AQ28: =AG14 -> 1409
AO29: Sep | AP29: =AF15 -> 2876 | AQ29: =AG15 -> 2086
AO30: Oct | AP30: =AF16 -> 2858 | AQ30: =AG16 -> 2286
AO31: Nov | AP31: =AF17 -> 2859 | AQ31: =AG17 -> 2330
AO32: Dec | AP32: =AF18 -> 2652 | AQ32: =AG18 -> 2530

Sheet 10.8
A1: ތާވަލު 10.8: ޖިންސުގެ ގޮތުން އެކިމަސްމަހު ރާއްޖެއައި ފަތުރުވެރިންގެ އަދަދު، 2015 - 2020
A2: TABLE 10.8: MONTHLY ARRIVAL OF TOURISTS BY SEX, 2015 - 2020
B4: ޖުމްލަ Total | C4: ޖެނުއަރީ Jan | D4: ފެބްރުއަރީ Feb | E4: މާރޗް Mar | F4: އޭޕްރިލް Apr | G4: މެއި May | H4: ޖޫން Jun | I4: ޖުލައި Jul | J4: އޮގަސްޓު Aug | K4: ސެޕްޓެމްބަރ Sep | L4: އޮކްޓޯބަރ Oct | M4: ނޮވެމްބަރ Nov | N4: ޑިސެމްބަރ Dec
A5: 2015 | O5: 2015
A6: Total | B6: =SUM(B7:B8) -> 1234248 | C6: =SUM(C7:C8) -> 97073 | D6: =SUM(D7:D8) -> 120468 | E6: =SUM(E7:E8) -> 112427 | F6: =SUM(F7:F8) -> 102242 | G6: =SUM(G7:G8) -> 95389 | H6: =SUM(H7:H8) -> 81506 | I6: =SUM(I7:I8) -> 104517 | ... N6: =SUM(N7:N8) -> 119255 | O6: ޖުމްލަ
A7: Male | B7: =SUM(C7:N7) -> 598458 | C7: 47173 | D7: 57866 | E7: 54087 | F7: 49321 | G7: 46353 | H7: 39330 | I7: 49602 | J7: 53154 | K7: 46533 | L7: 52055 | M7: 44453 | N7: 58531 | O7: ފިރިހެން
A8: Female | B8: =SUM(C8:N8) -> 635790 | C8: 49900 | D8: 62602 | E8: 58340 | F8: 52921 | G8: 49036 | H8: 42176 | I8: 54915 | J8: 56990 | K8: 48978 | L8: 53443 | M8: 45765 | N8: 60724 | O8: އަންހެން
A9: 2016 | O9: 2016
A10: Total | B10: =SUM(B11:B12) -> 1286135 | C10: =SUM(C11:C12) -> 108396 | D10: =SUM(D11:D12) -> 120639 | E10: =SUM(E11:E12) -> 115131 | F10: =SUM(F11:F12) -> 103493 | G10: =SUM(G11:G12) -> 93228 | H10: =SUM(H11:H12) -> 79034 | I10: =SUM(I11:I12) -> 110432 | ... N10: =SUM(N11:N12) -> 119530 | O10: ޖުމްލަ
A11: Male | B11: =SUM(C11:N11) -> 623657 | C11: 52580 | D11: 58245 | E11: 55809 | F11: 49741 | G11: 45523 | H11: 37767 | I11: 52833 | J11: 53869 | K11: 49635 | L11: 58020 | M11: 51192 | N11: 58443 | O11: ފިރިހެން
A12: Female | B12: =SUM(C12:N12) -> 662478 | C12: 55816 | D12: 62394 | E12: 59322 | F12: 53752 | G12: 47705 | H12: 41267 | I12: 57599 | J12: 58413 | K12: 52274 | L12: 59469 | M12: 53380 | N12: 61087 | O12: އަންހެން
A13: 2017 | O13: 2017
A14: Total | B14: =SUM(C14:N14) -> 1389542 | C14: =SUM(C15:C16) -> 125336 | D14: =SUM(D15:D16) -> 121052 | E14: =SUM(E15:E16) -> 112665 | F14: =SUM(F15:F16) -> 119774 | G14: =SUM(G15:G16) -> 93491 | H14: =SUM(H15:H16) -> 85222 | I14: =SUM(I15:I16) -> 113175 | J14: =SUM(J15:J16) -> 121310 | ... N14: =SUM(N15:N16) -> 143041 | O14: ޖުމްލަ
A15: Male | B15: =SUM(C15:N15) -> 667286 | C15: 60242 | D15: 58195 | E15: 54157 | F15: 57109 | G15: 45177 | H15: 40579 | I15: 54239 | J15: 57649 | K15: 51284 | L15: 61740 | M15: 57934 | N15: 68981 | O15: ފިރިހެން
A16: Female | B16: =SUM(C16:N16) -> 722256 | C16: 65094 | D16: 62857 | E16: 58508 | F16: 62665 | G16: 48314 | H16: 44643 | I16: 58936 | J16: 63661 | K16: 54700 | L16: 66246 | M16: 62572 | N16: 74060 | O16: އަންހެން
A17: 2018 | O17: 2018
A18: Total | B18: =SUM(C18:N18) -> 1484274 | C18: =SUM(C19:C20) -> 142351 | D18: =SUM(D19:D20) -> 144286 | E18: =SUM(E19:E20) -> 133466 | F18: =SUM(F19:F20) -> 119713 | G18: =SUM(G19:G20) -> 92913 | H18: =SUM(H19:H20) -> 93786 | I18: =SUM(I19:I20) -> 122332 | J18: =SUM(J19:J20) -> 123992 | ... N18: =SUM(N19:N20) -> 150818 | O18: ޖުމްލަ
A19: Male | B19: =SUM(C19:N19) -> 710256 | C19: 67601 | D19: 68779 | E19: 64018 | F19: 57300 | G19: 44543 | H19: 44461 | I19: 58223 | J19: 58839 | K19: 51698 | L19: 61444 | M19: 60624 | N19: 72726 | O19: ފިރިހެން
A20: Female | B20: =SUM(C20:N20) -> 774018 | C20: 74750 | D20: 75507 | E20: 69448 | F20: 62413 | G20: 48370 | H20: 49325 | I20: 64109 | J20: 65153 | K20: 55922 | L20: 65949 | M20: 64980 | N20: 78092 | O20: އަންހެން
A21: 2019 | O21: 2019
A22: Total | B22: =SUM(C22:N22) -> 1702887 | C22: =SUM(C23:C24) -> 151552 | D22: =SUM(D23:D24) -> 168583 | E22: =SUM(E23:E24) -> 162843 | F22: =SUM(F23:F24) -> 163114 | G22: =SUM(G23:G24) -> 103022 | H22: =SUM(H23:H24) -> 113475 | I22: =SUM(I23:I24) -> 132144 | J22: =SUM(J23:J24) -> 139338 | ... N22: =SUM(N23:N24) -> 171348 | O22: ޖުމްލަ
A23: Male | B23: =SUM(C23:N23) -> 816083 | C23: 72654 | D23: 80612 | E23: 77386 | F23: 77481 | G23: 49160 | H23: 54044 | I23: 63259 | J23: 66671 | K23: 57144 | L23: 68634 | M23: 66248 | N23: 82790 | O23: ފިރިހެން
A24: Female | B24: =SUM(C24:N24) -> 886804 | C24: 78898 | D24: 87971 | E24: 85457 | F24: 85633 | G24: 53862 | H24: 59431 | I24: 68885 | J24: 72667 | K24: 60475 | L24: 73294 | M24: 71673 | N24: 88558 | O24: އަންހެން
A25: 2020 | O25: 2020
A26: Total | B26: =SUM(C26:N26) -> 555494 | C26: =SUM(C27:C28) -> 173347 | D26: =SUM(D27:D28) -> 149785 | E26: =SUM(E27:E28) -> 59630 | F26: =SUM(F27:F28) -> 13 | G26: =SUM(G27:G28) -> 41 | H26: =SUM(H27:H28) -> 1 | I26: =SUM(I27:I28) -> 1752 | J26: =SUM(J27:J28) -> 7636 | ... N26: =SUM(N27:N28) -> 96412 | O26: ޖުމްލަ
A27: Male | B27: =SUM(C27:N27) -> 266811 | C27: 82485 | D27: 71772 | E27: 28412 | F27: 12 | G27: 27 | H27: 1 | I27: 862 | J27: 3794 | K27: 4869 | L27: 10646 | M27: 17220 | N27: 46711 | O27: ފިރިހެން
A28: Female | B28: =SUM(C28:N28) -> 288683 | C28: 90862 | D28: 78013 | E28: 31218 | F28: 1 | G28: 14 | H28: 0 | I28: 890 | J28: 3842 | K28: 4736 | L28: 10869 | M28: 18537 | N28: 49701 | O28: އަންހެން
A29: Source: Ministry of Tourism | O29: cmwzirUT cfoa IrcTcsinim :ctWrwf ivcaed utWmUluAwm | Z29: Jan | AA29: Feb | AB29: Mar | AC29: Apr | AD29: May | AE29: Jun | AF29: Jul | AG29: Aug | AH29: Sep | AI29: Oct | AJ29: Nov | AK29: Dec
A30: Note: Maldives border was closed for international visitirs on 27th March 2020 due to global COVID-19 outbreak and was re-opened on 15th July 2020
A31: Due to COVIC-19 pandamic, some tourists were unable to travel back to their home country.
AF42: Male | AG42: Female
AE43: 2015 | AF43: 598458 | AG43: 635790
AE44: 2016 | AF44: 623657 | AG44: 662478
AE45: 2017 | AF45: 667286 | AG45: 722256
AE46: 2018 | AF46: =B19 -> 710256 | AG46: =B20 -> 774018
AE47: 2019 | AF47: =B23 -> 816083 | AG47: =B24 -> 886804
AE48: 2020 | AF48: =B27 -> 266811 | AG48: =B28 -> 288683

Sheet 10.9
A1: 2020 - 2017 , udwdwA egEr irukwdEh cnirevurutwf iaWrwviawa cnirevurutwf iawguhwmcswmikea : 10.9 ulwvWt
A2: Table 10.9: TOURIST ARRIVALS,AND TOURIST BED-NIGHTS BY MONTH, 2017 - 2020
A3: Month | E3: Tourist Bed-nights* | M3: Tourist Arrivals | Q3: % change same month of previous year | T3: % change from previous month | W3: cswm
Q4: ވޭތުވެދިޔަ އަހަރުގެ މިމަހާއި އަޅާބަލާއިރު އިތުރުވި މިންވަރު | T4: ވޭތުވެދިޔަ މަހާއި އަޅާބަލާއިރު އިތުރުވި މިންވަރު
E5: ފަތުރުވެރިން ހޭދަކުރި ރޭގެ އަދަދު | M5: ފަތުރުވެރިންގެ އަދަދު | Q5: Tourist Bed-nights* | S5: Tourist Arrivals | T5: Tourist Bed-nights* | V5: Tourist Arrivals
Q6: ފަތުރުވެރިން ހޭދަކުރި ރޭގެ އަދަދު | S6: ފަތުރުވެރިންގެ އަދަދު | T6: ފަތުރުވެރިން ހޭދަކުރި ރޭގެ އަދަދު | V6: ފަތުރުވެރިންގެ އަދަދު
B7: 2014 | C7: 2015 | D7: 2016 | E7: 2017 | F7: 2018 | G7: 2019 | H7: 2020 | J7: 2014 | K7: 2015 | L7: 2016 | M7: 2017 | N7: 2018 | O7: 2019 | P7: 2020 | Q7: 2019-2020 | T7: 2020
A8: Total | B8: =SUM(B9:B20) -> 7505622.3 | C8: =SUM(C9:C20) -> 7322683.1 | D8: =SUM(D9:D20) -> 7770922.6 | E8: =SUM(E9:E20) -> 8593283.6 | F8: =SUM(F9:F20) -> 9478093.9 | G8: =SUM(G9:G20) -> 10688387 | H8: =SUM(H9:H20) -> 3984712.4 | J8: =SUM(J9:J20) -> 1204857 | K8: =SUM(K9:K20) -> 1234248 | L8: =SUM(L9:L20) -> 1286135 | M8: =SUM(M9:M20) -> 1389542 | N8: =SUM(N9:N20) -> 1484274 | O8: =SUM(O9:O20) -> 1702887 | P8: =SUM(P9:P20) -> 555494 | Q8: =((H8/G8)-1)*100 -> -62.719235 | S8: =((P8/O8)-1)*100 -> -67.37928 | T8: _ | V8: _ | W8: wlcmuj
A9: January | B9: 702057.24 | C9: 663541.54 | D9: 658991.02 | E9: 800126.36 | F9: 941496.94 | G9: 998457.16 | H9: 1142718.4 | J9: 105296 | K9: 97073 | L9: 108396 | M9: 125336 | N9: 142351 | O9: 151552 | P9: 173347 | Q9: =((H9/G9)-1)*100 -> 14.448415 | S9: =((P9/O9)-1)*100 -> 14.381202 | T9: =((H9/G20)-1)*100 -> 8.8817368 | V9: =((P9/O20)-1)*100 -> 1.1666317 | W9: Irwaunej
A10: February | B10: 701834.83 | C10: 713662.18 | D10: 749459.82 | E10: 772412.99 | F10: 925585.2 | G10: 1019637.3 | H10: 1020309.7 | J10: 110705 | K10: 120468 | L10: 120639 | M10: 121052 | N10: 144286 | O10: 168583 | P10: 149785 | Q10: =((H10/G10)-1)*100 -> 0.065944849 | S10: =((P10/O10)-1)*100 -> -11.150591 | T10: =((H10/H9)-1)*100 -> -10.712064 | V10: =((P10/P9)-1)*100 -> -13.59239 | W10: Irwaurcbef
A11: March | B11: 706437.32 | C11: 692862.6 | D11: 746568.5 | E11: 750431.76 | F11: 873729.27 | G11: 1006770.3 | H11: 562302.21 | J11: 105560 | K11: 112427 | L11: 115131 | M11: 112665 | N11: 133466 | O11: 162843 | P11: 59630 | Q11: =((H11/G11)-1)*100 -> -44.147915 | S11: =((P11/O11)-1)*100 -> -63.381908 | T11: =((H11/H10)-1)*100 -> -44.889064 | V11: =((P11/P10)-1)*100 -> -60.189605 | W11: cCWm
A12: April | B12: 673309.99 | C12: 640521.6 | D12: 655921.9 | E12: 742497.62 | F12: 796839.94 | G12: 981769.33 | H12: 8844.0203 | J12: 105309 | K12: 102242 | L12: 103493 | M12: 119774 | N12: 119713 | O12: 163114 | P12: 13 | Q12: =((H12/G12)-1)*100 -> -99.099175 | S12: =((P12/O12)-1)*100 -> -99.99203 | T12: =((H12/H11)-1)*100 -> -98.427177 | V12: =((P12/P11)-1)*100 -> -99.978199 | W12: clIrcpEa
A13: May | B13: 577519.53 | C13: 575317.18 | D13: 573465.31 | E13: 601496.37 | F13: 641543.89 | G13: 717991.88 | H13: 4776.6212 | J13: 91296 | K13: 95389 | L13: 93228 | M13: 93491 | N13: 92913 | O13: 103022 | P13: 41 | Q13: =((H13/G13)-1)*100 -> -99.334725 | S13: =((P13/O13)-1)*100 -> -99.960203 | T13: =((H13/H12)-1)*100 -> -45.990387 | V13: =((P13/P12)-1)*100 -> 215.38462 | W13: iaem
A14: June | B14: 472676.96 | C14: 447882.49 | D14: 443937.13 | E14: 480889.64 | F14: 544549.71 | G14: 714606.98 | H14: 2325.8012 | J14: 83347 | K14: 81506 | L14: 79034 | M14: 85222 | N14: 93786 | O14: 113475 | P14: 1 | Q14: =((H14/G14)-1)*100 -> -99.674534 | S14: =((P14/O14)-1)*100 -> -99.999119 | T14: =((H14/H13)-1)*100 -> -51.308654 | V14: =((P14/P13)-1)*100 -> -97.560976 | W14: cnUj
A15: July | B15: 576664.65 | C15: 570407.4 | D15: 629327.19 | E15: 688020.73 | F15: 743513.82 | G15: 776707.97 | H15: 24673.425 | J15: 100191 | K15: 104517 | L15: 110432 | M15: 113175 | N15: 122332 | O15: 132144 | P15: 1752 | Q15: =((H15/G15)-1)*100 -> -96.823333 | S15: =((P15/O15)-1)*100 -> -98.674174 | T15: =((H15/H14)-1)*100 -> 960.85701 | V15: =((P15/P14)-1)*100 -> 175100 | W15: iawluj
A16: August | B16: 644401.87 | C16: 634864.87 | D16: 679120.24 | E16: 746618.12 | F16: 822923.11 | G16: 910642.62 | H16: 71370.695 | J16: 104186 | K16: 110144 | L16: 112282 | M16: 121310 | N16: 123992 | O16: 139338 | P16: 7636 | Q16: =((H16/G16)-1)*100 -> -92.162601 | S16: =((P16/O16)-1)*100 -> -94.519801 | T16: =((H16/H15)-1)*100 -> 189.2614 | V16: =((P16/P15)-1)*100 -> 335.84475 | W16: cTcswgOa
A17: September | B17: 550854.33 | C17: 545085.54 | D17: 589810.67 | E17: 604175.35 | F17: 648410.82 | G17: 708842.02 | H17: 75367.862 | J17: 95114 | K17: 95511 | L17: 101909 | M17: 105984 | N17: 107620 | O17: 117619 | P17: 9605 | Q17: =((H17/G17)-1)*100 -> -89.367467 | S17: =((P17/O17)-1)*100 -> -91.833802 | T17: =((H17/H16)-1)*100 -> 5.6005722 | V17: =((P17/P16)-1)*100 -> 25.785752 | W17: rwbcmeTcpes
A18: October | B18: 684193.72 | C18: 638669.93 | D18: 706407.53 | E18: 793474.42 | F18: 820686.79 | G18: 916411.33 | H18: 169709.08 | J18: 110331 | K18: 105498 | L18: 117489 | M18: 127986 | N18: 127393 | O18: 141928 | P18: 21515 | Q18: =((H18/G18)-1)*100 -> -81.481124 | S18: =((P18/O18)-1)*100 -> -84.840905 | T18: =((H18/H17)-1)*100 -> 125.17433 | V18: =((P18/P17)-1)*100 -> 123.99792 | W18: rwbOTckoa
A19: November | B19: 572968.69 | C19: 566992.27 | D19: 651958.88 | E19: 750052.33 | F19: 809163.63 | G19: 887046.05 | H19: 279030.28 | J19: 89778 | K19: 90218 | L19: 104572 | M19: 120506 | N19: 125604 | O19: 137921 | P19: 35757 | Q19: =((H19/G19)-1)*100 -> -68.543879 | S19: =((P19/O19)-1)*100 -> -74.074289 | T19: =((H19/H18)-1)*100 -> 64.416825 | V19: =((P19/P18)-1)*100 -> 66.195677 | W19: rwbcmevon
A20: December | B20: 642703.14 | C20: 632875.48 | D20: 685954.43 | E20: 863087.93 | F20: 909650.78 | G20: 1049504.2 | H20: 623284.4 | J20: 103744 | K20: 119255 | L20: 119530 | M20: 143041 | N20: 150818 | O20: 171348 | P20: 96412 | Q20: =((H20/G20)-1)*100 -> -40.611538 | S20: =((P20/O20)-1)*100 -> -43.733221 | T20: =((H20/H19)-1)*100 -> 123.37518 | V20: =((P20/P19)-1)*100 -> 169.63112 | W20: rwbcmesiD
A21: Note: * Tourist Bed night figures include resorts/hotels/safaris & guesthouses | W21: ނޯޓް: ފަތުރުވެރިން ހޭދަކުރި ރޭގެ އަދަދުގެ ތެރޭގައި ރިސޯޓް، ހޮޓާ، ސަފާރީ އަދި ގެސްޓްހައުސްތައްވެސް ހިމެނެއެވެ.
A22: Source: Ministry of Tourism | W22: cmwzirUT cfoa IrcTcsinim :ctWrwf ivcaed utWmUluAwm
A23: Note: Maldives border was closed for international visitirs on 27th March 2020 due to global COVID-19 outbreak and was re-opened on 15th July 2020
A24: Due to COVIC-19 pandamic, some tourists were unable to travel back to their home country.
AO50: Jan
AO51: Feb
AO52: Mar
AO53: Apr
AO54: May
AO55: Jun
AO56: Jul
AO57: Aug
AO58: Sep
AO59: Oct
AO60: Nov
AO61: Dec

Sheet 10.10
A1: 2023 - 2010 ,ctwbcsin egInwdcmWa iaWdwrwK egWriaWd egumwkirevurutwf cniaeret eguTejwb egurWkurws : 10.10 ulwvWt
A2: Table 10.10 : PROPORTION OF TOURISM REVENUE AND EXPENDITURE TO CENTRAL GOVERNMENT BUDGET, 2010 - 2020
A3: (In Million MVR)
A4: Particulars | N4: Actual | O4: Actual | P4: Actual | Q4: Actual | R4: Revised | S4: Estimate
B5: 2003 | C5: 2004 | D5: 2005 | E5: 2006 | F5: 2007 | G5: 2008 | H5: 2009 | I5: 2010 | J5: 2011 | K5: 2012 | L5: 2013 | M5: 2014 | N5: 2015 | O5: 2016 | P5: 2017 | Q5: 2018 | R5: 2019 | S5: 2020
A6: Central Government Budget | T6: InwdcmWa eguTejwb egurWkurws
A7: Total Revenue | B7: 2964.3 | C7: 3351.8 | D7: 3788.3 | E7: 5286.7 | F7: 6527.2 | G7: 6939.54 | H7: 5313.3195 | I7: 6392.3855 | J7: 9172.1262 | K7: 9771.4431 | L7: 11783.093 | M7: 14998.954 | N7: 16669.26 | O7: 18324.938 | P7: 19914.873 | Q7: 21403.16 | R7: 22008.822 | S7: 12550.225 | T7: InwdcmWa wlcmuj
A8: Tourism Revenue* | B8: 899.7 | C8: 921.5 | D8: 911.8 | E8: 1776.9 | F8: 2216 | G8: 1969.8 | H8: 1429.8078 | I8: 1703.6 | J8: 2568.2981 | K8: 3389.5098 | L8: 4122.6635 | M8: 5621.5076 | N8: 6532.7918 | O8: 6471.0405 | P8: 6595.9008 | Q8: 7329.3774 | R8: 7797.4296 | S8: 2892.2325 | T8: InwdcmWa cniaWriaWd egumwkirevurutwf
A9: % Share of Tourism Revenue | B9: 30.351179 | C9: 27.49269 | D9: 24.068844 | E9: 34 | F9: 34 | G9: 28 | H9: 26.909878 | I9: 26.650458 | J9: 28.00112 | K9: 34.687914 | L9: 34.987957 | M9: =(M8/M7)*100 -> 37.479331 | N9: =(N8/N7)*100 -> 39.190652 | O9: =(O8/O7)*100 -> 35.312756 | P9: =(P8/P7)*100 -> 33.120477 | Q9: =(Q8/Q7)*100 -> 34.244371 | R9: =(R8/R7)*100 -> 35.428655 | S9: =(S8/S7)*100 -> 23.045264 | T9: cniawtcaws InwdcmWa cniaWriaWd egumwkirevurutwf
A10: Central Government Expenditure | T10: urwvcnim WvudwrwK cnuTejwb egurWkurws
A11: Total Expenditure | B11: 3551.9 | C11: 3779.1 | D11: 5775.4 | E11: 7066.2 | F11: 8325.4 | G11: 10342.4 | H11: 11104.27 | I11: =SUM(I12:I13) -> 10996.362 | J11: =SUM(J12:J13) -> 12663.727 | K11: 13200.235 | L11: =SUM(L12:L13) -> 13666.256 | M11: =SUM(M12:M13) -> 16539.374 | N11: =SUM(N12:N13) -> 21440.752 | O11: =SUM(O12:O13) -> 25306.509 | P11: =SUM(P12:P13) -> 22497.557 | Q11: =SUM(Q12:Q13) -> 26522.293 | R11: =SUM(R12:R13) -> 30128.217 | S11: =SUM(S12:S13) -> 31787.135 | T11: udwrwK wlcmuj
A12: Current Expenditure | B12: 2345.7 | C12: 2788.1 | D12: 4643.3 | E12: 5607.8 | F12: 6560.1 | G12: 7463.2 | H12: 8764.9 | I12: 8428.0734 | J12: 9075.7435 | K12: 10316.485 | L12: 11573.215 | M12: 13959.969 | N12: 16733.6 | O12: 16141.005 | P12: 14955.177 | Q12: 18268.036 | R12: 21371.958 | S12: 20876.938 | T12: ރިކަރަންޓް ޚަރަދު
A13: Capital Expenditure | B13: 1206.2 | C13: 991 | D13: 1132.1 | E13: 1458.4 | F13: 1765.3 | G13: 2879.2 | H13: 2339.3 | I13: 2568.2887 | J13: 3587.9832 | K13: 2883.7493 | L13: 2093.0414 | M13: 2579.4051 | N13: 4707.1522 | O13: 9165.5047 | P13: 7542.3806 | Q13: 8254.2566 | R13: 8756.2591 | S13: 10910.197 | T13: ކެޕިޓަލް ޚަރަދު
A14: Tourism Expenditure | B14: 34.9 | C14: 56.3 | D14: 57.4 | E14: 100.8 | F14: 108.2 | G14: 93.3 | H14: 56.6 | I14: =SUM(I15:I16) -> 46.85 | J14: =SUM(J15:J16) -> 33.749469 | K14: =SUM(K15:K16) -> 52.6 | L14: =SUM(L15:L16) -> 33.124519 | M14: =SUM(M15:M16) -> 49.642775 | N14: =SUM(N15:N16) -> 103.70915 | O14: =SUM(O15:O16) -> 143.48096 | P14: =SUM(P15:P16) -> 62.798475 | ... S14: =SUM(S15:S16) -> 41.969962 | T14: urwvcnimWvudwrwK cSwmwkirevurutwf
A15: Current Expenditure | B15: 34.5 | C15: 55.6 | D15: 56.9 | E15: 100.1 | F15: 107.8 | G15: 80.1 | H15: 56.43 | I15: 43.83 | J15: 33.652 | K15: 52.4 | L15: 33.053981 | M15: 48.876988 | N15: 103.02846 | O15: 142.91155 | P15: 62.6652 | Q15: =[2]BA_Budget!$F$10/10^6 -> 62.31615 | R15: =[3]BA_Budget!$F$14/10^6 -> 43.368542 | S15: =[3]BA_Budget!$E$14/10^6 -> 38.354809 | T15: ރިކަރަންޓް ޚަރަދު
A16: Capital Expenditure | B16: 0.4 | C16: 0.7 | D16: 0.5 | E16: 0.7 | F16: 0.4 | G16: 13.2 | H16: 0.13069 | I16: 3.02 | J16: 0.097469 | K16: 0.2 | L16: 0.070538 | M16: 0.765787 | N16: 0.680686 | O16: 0.56940856 | P16: 0.133275 | Q16: =[2]BA_Budget!$F$11/10^6 -> 0.8268 | R16: =[3]BA_Budget!$F$27/10^6 -> 0.811887 | S16: =[3]BA_Budget!$E$27/10^6 -> 3.615153 | T16: ކެޕިޓަލް ޚަރަދު
A17: % Share of Tourism Expenditure | B17: 0.98257271 | C17: 1.4897727 | D17: 0.99387055 | E17: 1.4265093 | F17: =F14/F11*100 -> 1.2996373 | G17: =G14/G11*100 -> 0.9021117 | H17: =H14/H11*100 -> 0.50971381 | I17: =I14/I11*100 -> 0.42604999 | J17: =J14/J11*100 -> 0.26650503 | K17: =K14/K11*100 -> 0.39847777 | L17: =L14/L11*100 -> 0.24238182 | M17: =M14/M11*100 -> 0.30014906 | ... S17: =S14/S11*100 -> 0.13203443 | T17: cniawtcaws cnutogWviawfiheb urwvcnim WvudwrwK cSwmwkirevurutwf
A18: Current Expenditure | B18: 1.4707763 | C18: 1.9941896 | D18: 1.2254216 | E18: 1.7850137 | F18: 1.6432676 | G18: 1.0732662 | H18: 0.64381796 | I18: 0.52004768 | J18: 0.37079056 | K18: 0.50792493 | L18: 0.28560761 | M18: =M15/M12*100 -> 0.35012248 | N18: =N15/N12*100 -> 0.61569814 | O18: =O15/O12*100 -> 0.88539438 | P18: =P15/P12*100 -> 0.41902013 | Q18: =Q15/Q12*100 -> 0.34112123 | R18: =R15/R12*100 -> 0.20292265 | S18: =S15/S12*100 -> 0.18371856 | T18: ރިކަރަންޓް ޚަރަދު
A19: Capital Expenditure | B19: 0.033161996 | C19: 0.070635721 | D19: 0.04416571 | E19: 0.047997806 | F19: 0.022659038 | G19: 0.45846068 | H19: 0.005586714 | I19: 0.11758803 | J19: 0.00271654 | K19: 0.0069354156 | L19: 0.001893511 | M19: =M16/M13*100 -> 0.029688512 | N19: =N16/N13*100 -> 0.014460675 | O19: =O16/O13*100 -> 0.0062125172 | P19: =P16/P13*100 -> 0.001767015 | Q19: =Q16/Q13*100 -> 0.01001665 | R19: =R16/R13*100 -> 0.009272076 | S19: =S16/S13*100 -> 0.033135542 | T19: ކެޕިޓަލް ޚަރަދު
A20: Note:
A21: * Tourism Revenue: 2010 onwards the figures include Tourism tax, and Resort lease rent (Resort kuli)
A22: * 2011 onwards Tourism Goods and Services tax has been included in Total Revenue
A23: * 2012 onwards lease period Extension fee has been included in Total Revenue
A24: * Tourism Tax was abolished in Nov 2014
A25: * Green tax introduced in Nov 2015
A26: * TGST rate was increased from 8% to 12% starting Nov 2014
A27: * lease period extension fee (consession fee for upto 50 years) was started in mid 2014 after a court ruling. LPEF will be paid in 6 installments, most of which fall for 2015. The last payment will be in March 2016.
A29: * Resort lease rent for 2015 - 2017 includes the amount for new revenue measures in budget 2015
A30: * Resort lease rent for 2016 - 2018 includes the amount for new revenue measures in budget 2016
A31: Source: Ministry of Finance and Treasury

Sheet 10.11
A1: 2020 udwdwA egcnirevurutwf iawaejcaWr cnutogegukwtumuawq uhwmcswmikea : 10.11 ulwvWt
A2: Table 10.11 : MONTHLY DISTRIBUTION OF TOURIST ARRIVALS BY NATIONALITY, 2020
A3: Country of Nationality | B3: ޖުމްލަ Total | C3: ޖެނުއަރީ Jan | D3: ފެބްރުއަރީ Feb | E3: މާރޗް Mar | F3: އޭޕްރިލް Apr | G3: މެއި May | H3: ޖޫން Jun | I3: ޖުލައި Jul | J3: އޮގަސްޓު Aug | K3: ސެޕްޓެމްބަރ Sep | L3: އޮކްޓޯބަރ Oct | M3: ނޮވެމްބަރ Nov | N3: ޑިސެމްބަރ Dec | O3: ޤައުމިއްޔަތު/ މަސް
A4: Total | B4: =B5+B11+B15+B16+B17+B18+B19+B20 -> 555494 | C4: =C5+C11+C15+C16+C17+C18+C19+C20 -> 173347 | D4: =D5+D11+D15+D16+D17+D18+D19+D20 -> 149785 | E4: =E5+E11+E15+E16+E17+E18+E19+E20 -> 59630 | F4: =F5+F11+F15+F16+F17+F18+F19+F20 -> 13 | G4: =G5+G11+G15+G16+G17+G18+G19+G20 -> 41 | H4: =H5+H11+H15+H16+H17+H18+H19+H20 -> 1 | I4: =I5+I11+I15+I16+I17+I18+I19+I20 -> 1752 | ... N4: =N5+N11+N15+N16+N17+N18+N19+N20 -> 96412 | O4: ޖުމްލަ
A5: Europe | B5: =SUM(B6:B10) -> 348349 | C5: =SUM(C6:C10) -> 94725 | D5: =SUM(D6:D10) -> 102348 | E5: =SUM(E6:E10) -> 42015 | F5: =SUM(F6:F10) -> 0 | G5: =SUM(G6:G10) -> 37 | H5: =SUM(H6:H10) -> 1 | I5: =SUM(I6:I10) -> 1044 | ... N5: =SUM(N6:N10) -> 63487 | O5: ޔޫރަޕް
A6: Central/Eastern Europe | B6: =SUM(C6:N6) -> 120383 | C6: 28280 | D6: 23141 | E6: 12233 | F6: 0 | G6: 23 | H6: 0 | I6: 240 | J6: 1197 | K6: 2929 | L6: 8581 | M6: 12697 | N6: 31062 | O6: މެދު/އިރުމަތި ޔޫރަޕް
A7: Northern Europe | B7: =SUM(C7:N7) -> 67822 | C7: 15264 | D7: 21059 | E7: 8978 | F7: 0 | G7: 0 | H7: 1 | I7: 307 | J7: 795 | K7: 728 | L7: 2216 | M7: 2469 | N7: 16005 | O7: އުތުރު ޔޫރަޕް
A8: Southern Europe | B8: =SUM(C8:N8) -> 63150 | C8: 24902 | D8: 24809 | E8: 5700 | F8: 0 | G8: 1 | H8: 0 | I8: 153 | J8: 939 | K8: 786 | L8: 1219 | M8: 1209 | N8: 3432 | O8: ދެކުނު ޔޫރަޕް
A9: Western Europe | B9: =SUM(C9:N9) -> 91696 | C9: 24416 | D9: 32016 | E9: 14672 | F9: 0 | G9: 13 | H9: 0 | I9: 298 | J9: 771 | K9: 831 | L9: 2490 | M9: 3907 | N9: 12282 | O9: ހުޅަނގު ޔޫރަޕް
A10: East/Mediterranean Europe | B10: =SUM(C10:N10) -> 5298 | C10: 1863 | D10: 1323 | E10: 432 | F10: 0 | G10: 0 | H10: 0 | I10: 46 | J10: 126 | K10: 245 | L10: 317 | M10: 240 | N10: 706 | O10: އިރުމަތި/މެޑިޓަރޭނިއަން ޔޫރަޕް
A11: Asia | B11: =SUM(C11:N11) -> 134279 | C11: =SUM(C12:C14) -> 58762 | D11: =SUM(D12:D14) -> 31785 | E11: =SUM(E12:E14) -> 10953 | F11: =SUM(F12:F14) -> 12 | G11: =SUM(G12:G14) -> 4 | H11: =SUM(H12:H14) -> 0 | I11: =SUM(I12:I14) -> 122 | J11: =SUM(J12:J14) -> 545 | ... N11: =SUM(N12:N14) -> 20699 | O11: އޭޝިއާ
A12: North East Asia | B12: =SUM(C12:N12) -> 51319 | C12: 38543 | D12: 9652 | E12: 2383 | F12: 0 | G12: 0 | H12: 0 | I12: 27 | J12: 56 | K12: 63 | L12: 90 | M12: 133 | N12: 372 | O12: ހުޅަނގު އުތުރު އޭޝިއާ
A13: South East Asia | B13: =SUM(C13:N13) -> 12746 | C13: 4198 | D13: 4901 | E13: 2482 | F13: 0 | G13: 0 | H13: 0 | I13: 33 | J13: 117 | K13: 74 | L13: 150 | M13: 260 | N13: 531 | O13: ހުޅަނގު ދެކުނު އޭޝިއާ
A14: South Asia | B14: =SUM(C14:N14) -> 70214 | C14: 16021 | D14: 17232 | E14: 6088 | F14: 12 | G14: 4 | H14: 0 | I14: 62 | J14: 372 | K14: 575 | L14: 1887 | M14: 8165 | N14: 19796 | O14: ދެކުނު އޭޝިއާ
A15: Oceania | B15: =SUM(C15:N15) -> 7964 | C15: 2926 | D15: 2260 | E15: 1468 | F15: 0 | G15: 0 | H15: 0 | I15: 29 | J15: 62 | K15: 66 | L15: 189 | M15: 236 | N15: 728 | O15: އެފްރިކާ
A16: Africa | B16: =SUM(C16:N16) -> 6458 | C16: 1536 | D16: 1118 | E16: 658 | F16: 0 | G16: 0 | H16: 0 | I16: 55 | J16: 163 | K16: 159 | L16: 270 | M16: 503 | N16: 1996 | O16: އެމެރިކާ
A17: America | B17: =SUM(C17:N17) -> 32060 | C17: 8078 | D17: 7460 | E17: 3183 | F17: 0 | G17: 0 | H17: 0 | I17: 255 | J17: 970 | K17: 1519 | L17: 2276 | M17: 3390 | N17: 4929 | O17: އޯޝަނިޔާ
A18: Middle East | B18: =SUM(C18:N18) -> 26286 | C18: 7297 | D18: 4793 | E18: 1346 | F18: 1 | G18: 0 | H18: 0 | I18: 247 | J18: 2066 | K18: 1627 | L18: 1822 | M18: 2530 | N18: 4557 | O18: މެދު އިރުމަތި
A19: UN Passport Holders | B19: =SUM(C19:N19) -> 21 | C19: 11 | D19: 5 | E19: 3 | F19: 0 | G19: 0 | H19: 0 | I19: 0 | J19: 0 | K19: 0 | L19: 1 | M19: 1 | N19: 0 | O19: ޔޫ.އެން ޕާސްޕޯޓް ހޯލްޑަރ
A20: Others/Not Stated | B20: =SUM(C20:N20) -> 77 | C20: 12 | D20: 16 | E20: 4 | F20: 0 | G20: 0 | H20: 0 | I20: 0 | J20: 2 | K20: 3 | L20: 7 | M20: 17 | N20: 16 | O20: ބަޔާން ނުކުރާ
A21: Source: Ministry of Tourism | O21: cmwzirUT cfoa IrcTcsinim :ctWrwf ivcaed utWmUluAwm
A22: Maldives Immigration | M22: މޯލްޑީވްސް އިމިގްރޭޝަން
A23: Note: Maldives border was closed for international visitirs on 27th March 2020 due to global COVID-19 outbreak and was re-opened on 15th July 2020
A24: Due to COVIC-19 pandamic, some tourists were unable to travel back to their home country.
X27: Jan | Y27: Feb | Z27: Mar | AA27: Apr | AB27: May | AC27: Jun | AD27: Jul | AE27: Aug | AF27: Sep | AG27: Oct | AH27: Nov | AI27: Dec
W28: Central/Eastern Europe | X28: =C6 -> 28280 | Y28: =D6 -> 23141 | Z28: =E6 -> 12233 | AA28: =F6 -> 0 | AB28: =G6 -> 23 | AC28: =H6 -> 0 | AD28: =I6 -> 240 | AE28: =J6 -> 1197 | ... AI28: =N6 -> 31062
W29: Northern Europe | X29: =C7 -> 15264 | Y29: =D7 -> 21059 | Z29: =E7 -> 8978 | AA29: =F7 -> 0 | AB29: =G7 -> 0 | AC29: =H7 -> 1 | AD29: =I7 -> 307 | AE29: =J7 -> 795 | ... AI29: =N7 -> 16005
W30: Southern Europe | X30: =C8 -> 24902 | Y30: =D8 -> 24809 | Z30: =E8 -> 5700 | AA30: =F8 -> 0 | AB30: =G8 -> 1 | AC30: =H8 -> 0 | AD30: =I8 -> 153 | AE30: =J8 -> 939 | ... AI30: =N8 -> 3432
W31: Western Europe | X31: =C9 -> 24416 | Y31: =D9 -> 32016 | Z31: =E9 -> 14672 | AA31: =F9 -> 0 | AB31: =G9 -> 13 | AC31: =H9 -> 0 | AD31: =I9 -> 298 | AE31: =J9 -> 771 | ... AI31: =N9 -> 12282
W32: East/Mediterranean Europe | X32: =C10 -> 1863 | Y32: =D10 -> 1323 | Z32: =E10 -> 432 | AA32: =F10 -> 0 | AB32: =G10 -> 0 | AC32: =H10 -> 0 | AD32: =I10 -> 46 | AE32: =J10 -> 126 | ... AI32: =N10 -> 706
X36: Jan | Y36: Feb | Z36: Mar | AA36: Apr | AB36: May | AC36: Jun | AD36: Jul | AE36: Aug | AF36: Sep | AG36: Oct | AH36: Nov | AI36: Dec
W37: North East Asia | X37: =C12 -> 38543 | Y37: =D12 -> 9652 | Z37: =E12 -> 2383 | AA37: =F12 -> 0 | AB37: =G12 -> 0 | AC37: =H12 -> 0 | AD37: =I12 -> 27 | AE37: =J12 -> 56 | ... AI37: =N12 -> 372
W38: South East Asia | X38: =C13 -> 4198 | Y38: =D13 -> 4901 | Z38: =E13 -> 2482 | AA38: =F13 -> 0 | AB38: =G13 -> 0 | AC38: =H13 -> 0 | AD38: =I13 -> 33 | AE38: =J13 -> 117 | ... AI38: =N13 -> 531
W39: South Asia | X39: =C14 -> 16021 | Y39: =D14 -> 17232 | Z39: =E14 -> 6088 | AA39: =F14 -> 12 | AB39: =G14 -> 4 | AC39: =H14 -> 0 | AD39: =I14 -> 62 | AE39: =J14 -> 372 | ... AI39: =N14 -> 19796

Sheet 10.12
A1: ތާވަލު 10.12: ރިސޯޓުތަކުގެ އެނދުގެ ޖާގަ އަތޮޅުތަކަށް ބެހިފައިވާ ގޮތް، 2013 - 2020
A2: Table 10.12 : BED CAPACITY OF TOURIST RESORTS BY ATOLL, 2013 - 2020
A3: Resorts | B3: Bed Capacity | N3: % Share
B4: 2009 | C4: 2010 | D4: 2011 | E4: 2012 | F4: 2013 | G4: 2014 | H4: 2015 | I4: 2016 | J4: 2017 | K4: 2018 | L4: 2019 | M4: 2020 | N4: in 2020 | O4: އަތޮޅުތައް
A5: All Resorts ( include marinas) | B5: =SUM(B6:B24) -> 20942 | C5: =SUM(C6:C24) -> 21342 | D5: =SUM(D6:D24) -> 22120 | E5: =SUM(E6:E24) -> 22963 | F5: =SUM(F6:F24) -> 23487 | G5: =SUM(G6:G24) -> 24031 | H5: =SUM(H6:H24) -> 24877 | I5: =SUM(I6:I24) -> 27031 | ... M5: =SUM(M6:M24) -> 37134 | N5: =M5/$M$5*100 -> 100 | O5: ޖުމްލަ
A6: North Thiladhunmathi Atoll (HA) | B6: 432 | C6: 456 | D6: 456 | E6: 456 | F6: 456 | G6: 464 | H6: 464 | I6: 464 | J6: 594 | K6: 594 | L6: 594 | M6: 394 | N6: =M6/$M$5*100 -> 1.0610222 | O6: ތިލަދުންމަތި އުތުރުބުރި (ހއ)
A7: South Thiladhunmathi Atoll (H.Dh) | F7: - | G7: - | H7: - | I7: - | J7: - | K7: 118 | L7: 118 | M7: 118 | N7: =M7/$M$5*100 -> 0.31776808 | O7: ތިލަދުންމަތި ދެކުނުބުރި (ހދ)
A8: North Miladhunmadulu Atoll (Sh) | B8: 0 | C8: 0 | D8: 0 | E8: 159 | F8: 159 | G8: 159 | H8: 159 | I8: 159 | J8: 227 | K8: 227 | L8: 457 | M8: 457 | N8: =M8/$M$5*100 -> 1.2306781 | O8: މިލަދުންމަޑޫލު އުތުރުބުރި (ށ)
A9: South Miladhunmadulu Atoll (N) | B9: 490 | C9: 542 | D9: 542 | E9: 542 | F9: 796 | G9: 796 | H9: 796 | I9: 832 | J9: 1176 | K9: 1388 | L9: 1398 | M9: 1436 | N9: =M9/$M$5*100 -> 3.867076 | O9: މިލަދުންމަޑޫލު ދެކުނުބުރި (ނ)
A10: North Maalhosmadulu (R) | B10: 470 | C10: 470 | D10: 470 | E10: 470 | F10: 470 | G10: 656 | H10: 680 | I10: 810 | J10: 1616 | K10: 1960 | L10: 3324 | M10: 3288 | N10: =M10/$M$5*100 -> 8.8544191 | O10: މާޅޮސްމަޑުލު އުތުރުބުރި (ރ)
A11: South Maalhosmadulu (B) | B11: 1240 | C11: 1398 | D11: 1398 | E11: 1660 | F11: 1704 | G11: 1704 | H11: 1700 | I11: 2302 | J11: 2562 | K11: 2882 | L11: 2918 | M11: 3104 | N11: =M11/$M$5*100 -> 8.3589164 | O11: މާޅޮސްމަޑުލު ދެކުނުބުރި (ބ)
A12: Faadhippolhu (Lh) | B12: 1336 | C12: 1336 | D12: 1336 | E12: 1336 | F12: 1476 | G12: 1636 | H12: 1636 | I12: 2138 | J12: 2250 | K12: 2284 | L12: 2440 | M12: 2468 | N12: =M12/$M$5*100 -> 6.6462002 | O12: ފާދިއްޕޮޅު (ޅ)
A13: Male' Atoll (K) | B13: 8982 | C13: 9050 | D13: 9128 | E13: 9144 | F13: 8964 | G13: 8968 | H13: 9088 | I13: 9506 | J13: 10094 | K13: 10568 | L13: 12100 | M13: 12048 | N13: =M13/$M$5*100 -> 32.44466 | O13: މާލެ އަތޮޅު (ކ)
A14: North Ari Atoll (AA) | B14: 1988 | C14: 1988 | D14: 1988 | E14: 1988 | F14: 2156 | G14: 2216 | H14: 2244 | I14: 2454 | J14: 2488 | K14: 2488 | L14: 2538 | M14: 2224 | N14: =M14/$M$5*100 -> 5.9891205 | O14: އަރިއަތޮޅު އުތުރުބުރި (އއ)
A15: South Ari Atoll (ADh) | B15: 3538 | C15: 3586 | D15: 3818 | E15: 3818 | F15: 3818 | G15: 3862 | H15: 3982 | I15: 3982 | J15: 4036 | K15: 4056 | L15: 4056 | M15: 4350 | N15: =M15/$M$5*100 -> 11.714332 | O15: އަރިއަތޮޅު ދެކުނުބުރި (އދ)
A16: Felidhu Atoll (V) | B16: 350 | C16: 350 | D16: 350 | E16: 402 | F16: 402 | G16: 402 | H16: 402 | I16: 434 | J16: 434 | K16: 434 | L16: 614 | M16: 614 | N16: =M16/$M$5*100 -> 1.6534712 | O16: ފެލިދެ އަތޮޅު (ވ)
A17: Mulakatholhu (M) | B17: 400 | C17: 400 | D17: 400 | E17: 400 | F17: 400 | G17: 400 | H17: 400 | I17: 400 | J17: 400 | K17: 400 | L17: 400 | M17: 440 | N17: =M17/$M$5*100 -> 1.1848979 | O17: މުލަކަތޮޅު (މ)
A18: North Nilandhe Atoll (F) | B18: 250 | C18: 250 | D18: 250 | E18: 250 | F18: 250 | G18: 250 | H18: 250 | I18: 250 | J18: 250 | K18: 250 | L18: 250 | M18: 250 | N18: =M18/$M$5*100 -> 0.67323746 | O18: ނިލަންދެ އަތޮޅު އުތުރުބުރި (ފ)
A19: South Nilandhe Atoll (D) | B19: 436 | C19: 436 | D19: 436 | E19: 590 | F19: 590 | G19: 590 | H19: 778 | I19: 962 | J19: 1512 | K19: 1754 | L19: 2798 | M19: 2806 | N19: =M19/$M$5*100 -> 7.5564173 | O19: ނިލަންދެ އަތޮޅު ދެކުނުބުރި (ދ)
... A23: South Huvadhu Atoll (GDh) | B23: 0 | C23: 0 | D23: 200 | E23: 200 | F23: 200 | G23: 200 | H23: 550 | I23: 550 | J23: 550 | K23: 550 | L23: 550 | M23: 550 | N23: =M23/$M$5*100 -> 1.4811224 | O23: ހުވަދު އަތޮޅު ދެކުނުބުރި (ގދ)
A24: Addu Atoll (S) | B24: 830 | C24: 830 | D24: 830 | E24: 830 | F24: 830 | G24: 826 | H24: 826 | I24: 826 | J24: 826 | K24: 826 | L24: 926 | M24: 926 | N24: =M24/$M$5*100 -> 2.4936716 | O24: އައްޑު އަތޮޅު (ސ) | AA24: number of resorts
A25: Source: Ministry of Tourism | O25: cmwzirUT cfoa IrcTcsinim :ctWrwf ivcaed utWmUluAwm | AA25: 2017 | AB25: 2018 | AC25: 2019 | AD25: 2020
Y26: HA | Z26: =M6 -> 394 | AA26: 3 | AB26: 3 | AC26: 3 | AD26: 2
Y27: HDh | Z27: =M7 -> 118 | AA27: 0 | AB27: 1 | AC27: 1 | AD27: 1
Y28: Sh | Z28: =M8 -> 457 | AA28: 2 | AB28: 2 | AC28: 2 | AD28: 2
Y29: N | Z29: =M9 -> 1436 | AA29: 6 | AB29: 7 | AC29: 7 | AD29: 7
Y30: R | Z30: =M10 -> 3288 | AA30: 6 | AB30: 8 | AC30: 13 | AD30: 13
Y31: B | Z31: =M11 -> 3104 | AA31: 13 | AB31: 15 | AC31: 16 | AD31: 16
Y32: Lh | Z32: =M12 -> 2468 | AA32: 8 | AB32: 9 | AC32: 10 | AD32: 10
Y33: K | Z33: =M13 -> 12048 | AA33: 45 | AB33: 47 | AC33: 52 | AD33: 50
Y34: AA | Z34: =M14 -> 2224 | AA34: 13 | AB34: 13 | AC34: 13 | AD34: 11
Y35: ADh | Z35: =M15 -> 4350 | AA35: 17 | AB35: 17 | AC35: 17 | AD35: 17
Y36: V | Z36: =M16 -> 614 | AA36: 2 | AB36: 2 | AC36: 3 | AD36: 3
Y37: M | Z37: =M17 -> 440 | AA37: 2 | AB37: 2 | AC37: 2 | AD37: 2
... Y44: S | Z44: =M24 -> 926 | AA44: 2 | AB44: 2 | AC44: 3 | AD44: 3
Z45: =SUM(Z26:Z44) -> 37134 | AA45: =SUM(AA26:AA44) -> 135 | AB45: =SUM(AB26:AB44) -> 145 | AC45: =SUM(AC26:AC44) -> 164 | AD45: =SUM(AD26:AD44) -> 159

Sheet 10.13
A1: ތާވަލު 10.13: ޤައުމުތަކުގެ ގޮތުން ރާއްޖެއައި ފަތުރުވެރިންގެ ޢަދަދު، މަސްމަހުގެ ގޮތުން، 2020
A2: Table 10.13 : MONTHLY DISTRIBUTION OF TOURIST ARRIVALS BY NATIONALITY, 2020
A4: Country of Nationality | B4: Total | C4: Jan | D4: Feb | E4: Mar | F4: Apr | G4: May | H4: Jun | I4: Jul | J4: Aug | K4: Sep | L4: Oct | M4: Nov | N4: Dec | O4: ވަޒަންވެރިވެފައިވާ ޤައުމު
A5: Total | B5: =SUM(C5:N5) -> 555494 | C5: =C6+C50+C73+C78+C85+C89+C100+C101 -> 173347 | D5: =D6+D50+D73+D78+D85+D89+D100+D101 -> 149785 | E5: =E6+E50+E73+E78+E85+E89+E100+E101 -> 59630 | F5: =F6+F50+F73+F78+F85+F89+F100+F101 -> 13 | G5: =G6+G50+G73+G78+G85+G89+G100+G101 -> 41 | H5: =H6+H50+H73+H78+H85+H89+H100+H101 -> 1 | I5: =I6+I50+I73+I78+I85+I89+I100+I101 -> 1752 | J5: =J6+J50+J73+J78+J85+J89+J100+J101 -> 7636 | ... N5: =N6+N50+N73+N78+N85+N89+N100+N101 -> 96412 | O5: ޖުމްލަ
A6: Europe | B6: =SUM(C6:N6) -> 348349 | C6: =C7+C21+C29+C38+C46 -> 94725 | D6: =D7+D21+D29+D38+D46 -> 102348 | E6: =E7+E21+E29+E38+E46 -> 42015 | F6: =F7+F21+F29+F38+F46 -> 0 | G6: =G7+G21+G29+G38+G46 -> 37 | H6: =H7+H21+H29+H38+H46 -> 1 | I6: =I7+I21+I29+I38+I46 -> 1044 | J6: =J7+J21+J29+J38+J46 -> 3828 | ... N6: =N7+N21+N29+N38+N46 -> 63487 | O6: ޔޫރަޕް
A7: Central/Eastern Europe | B7: =SUM(C7:N7) -> 120383 | C7: =SUM(C8:C20) -> 28280 | D7: =SUM(D8:D20) -> 23141 | E7: =SUM(E8:E20) -> 12233 | F7: =SUM(F8:F20) -> 0 | G7: =SUM(G8:G20) -> 23 | H7: =SUM(H8:H20) -> 0 | I7: =SUM(I8:I20) -> 240 | J7: =SUM(J8:J20) -> 1197 | ... N7: =SUM(N8:N20) -> 31062 | O7: މެދު އިރުމަތީ ޔޫރަޕް
A8: Belarus | B8: =SUM(C8:N8) -> 1754 | C8: 417 | D8: 304 | E8: 187 | F8: 0 | G8: 0 | H8: 0 | I8: 6 | J8: 26 | K8: 21 | L8: 148 | M8: 245 | N8: 400 | O8: ބެލަރުސް
A9: Bulgaria | B9: =SUM(C9:N9) -> 4057 | C9: 941 | D9: 1072 | E9: 285 | F9: 0 | G9: 0 | H9: 0 | I9: 0 | J9: 10 | K9: 18 | L9: 166 | M9: 244 | N9: 1321 | O9: ބަލްގޭރިއާ
A10: Czech Republic | B10: =SUM(C10:N10) -> 7282 | C10: 1390 | D10: 2150 | E10: 813 | F10: 0 | G10: 22 | H10: 0 | I10: 36 | J10: 118 | K10: 162 | L10: 289 | M10: 580 | N10: 1722 | O10: ޗެކް ރިޕަބްލިކް
A11: Hungary | B11: =SUM(C11:N11) -> 5813 | C11: 2225 | D11: 1856 | E11: 655 | F11: 0 | G11: 0 | H11: 0 | I11: 44 | J11: 71 | K11: 26 | L11: 104 | M11: 118 | N11: 714 | O11: ހަންގޭރީ
A12: Kazakhstan | B12: =SUM(C12:N12) -> 6470 | C12: 1756 | D12: 346 | E12: 669 | F12: 0 | G12: 0 | H12: 0 | I12: 10 | J12: 113 | K12: 146 | L12: 265 | M12: 326 | N12: 2839 | O12: ކަޒަކިސްތާން
A13: Latvia | B13: =SUM(C13:N13) -> 718 | C13: 167 | D13: 202 | E13: 84 | F13: 0 | G13: 0 | H13: 0 | I13: 0 | J13: 3 | K13: 5 | L13: 22 | M13: 40 | N13: 195 | O13: ލެޓްވިއާ
A14: Lithuania | B14: =SUM(C14:N14) -> 1186 | C14: 223 | D14: 324 | E14: 139 | F14: 0 | G14: 0 | H14: 0 | I14: 0 | J14: 9 | K14: 4 | L14: 16 | M14: 80 | N14: 391 | O14: ލިތުއާނާ
A15: Poland | B15: =SUM(C15:N15) -> 7108 | C15: 2429 | D15: 2287 | E15: 821 | F15: 0 | G15: 0 | H15: 0 | I15: 29 | J15: 99 | K15: 162 | L15: 146 | M15: 278 | N15: 857 | O15: ޕޮލަންޑް
A16: Romania | B16: =SUM(C16:N16) -> 6800 | C16: 2026 | D16: 1482 | E16: 509 | F16: 0 | G16: 0 | H16: 0 | I16: 17 | J16: 29 | K16: 42 | L16: 160 | M16: 447 | N16: 2088 | O16: ރޮމޭނިއާ
A17: Russia | B17: =SUM(C17:N17) -> 61387 | C17: 12531 | D17: 9690 | E17: 6728 | F17: 0 | G17: 0 | H17: 0 | I17: 52 | J17: 423 | K17: 2065 | L17: 5995 | M17: 8580 | N17: 15323 | O17: ރަޝިއާ
A18: Slovakia | B18: =SUM(C18:N18) -> 4498 | C18: 934 | D18: 1514 | E18: 440 | F18: 0 | G18: 1 | H18: 0 | I18: 6 | J18: 21 | K18: 15 | L18: 115 | M18: 239 | N18: 1213 | O18: ސްލޮވޭކިއާ
A19: Ukraine | B19: =SUM(C19:N19) -> 10343 | C19: 2434 | D19: 1389 | E19: 732 | F19: 0 | G19: 0 | H19: 0 | I19: 30 | J19: 252 | K19: 218 | L19: 1033 | M19: 1245 | N19: 3010 | O19: ޔޫކްރެއިން
A20: Others | B20: =SUM(C20:N20) -> 2967 | C20: 807 | D20: 525 | E20: 171 | F20: 0 | G20: 0 | H20: 0 | I20: 10 | J20: 23 | K20: 45 | L20: 122 | M20: 275 | N20: 989 | O20: އެހެނިހެން | V20: Jan | W20: Feb | X20: Mar | Y20: Apr | Z20: May | AA20: Jun | AB20: Jul | AC20: Aug | AD20: Sep | AE20: Oct | AF20: Nov | AG20: Dec
A21: Northern Europe | B21: =SUM(C21:N21) -> 67822 | C21: =SUM(C22:C28) -> 15264 | D21: =SUM(D22:D28) -> 21059 | E21: =SUM(E22:E28) -> 8978 | F21: =SUM(F22:F28) -> 0 | G21: =SUM(G22:G28) -> 0 | H21: =SUM(H22:H28) -> 1 | I21: =SUM(I22:I28) -> 307 | J21: =SUM(J22:J28) -> 795 | ... N21: =SUM(N22:N28) -> 16005 | O21: އުތުރު ޔޫރަޕް | U21: Total | V21: =C5 -> 173347 | W21: =D5 -> 149785 | X21: =E5 -> 59630 | Y21: =F5 -> 13 | Z21: =G5 -> 41 | AA21: =H5 -> 1 | AB21: =I5 -> 1752 | AC21: =J5 -> 7636 | ... AG21: =N5 -> 96412 | AH21: =SUM(V21:AG21) -> 555494
A22: Denmark | B22: =SUM(C22:N22) -> 3938 | C22: 1121 | D22: 1849 | E22: 460 | F22: 0 | G22: 0 | H22: 0 | I22: 28 | J22: 13 | K22: 29 | L22: 89 | M22: 76 | N22: 273 | O22: ޑެންމާކް | U22: Europe | V22: =C7+C21+C29+C38+C46 -> 94725 | W22: =D7+D21+D29+D38+D46 -> 102348 | X22: =E7+E21+E29+E38+E46 -> 42015 | Y22: =F7+F21+F29+F38+F46 -> 0 | Z22: =G7+G21+G29+G38+G46 -> 37 | AA22: =H7+H21+H29+H38+H46 -> 1 | AB22: =I7+I21+I29+I38+I46 -> 1044 | AC22: =J7+J21+J29+J38+J46 -> 3828 | ... AG22: =N7+N21+N29+N38+N46 -> 63487 | AH22: =SUM(V22:AG22) -> 348349
A23: Finland | B23: =SUM(C23:N23) -> 2128 | C23: 771 | D23: 864 | E23: 263 | F23: 0 | G23: 0 | H23: 0 | I23: 4 | J23: 4 | K23: 7 | L23: 36 | M23: 46 | N23: 133 | O23: ފިންލޭންޑް | U23: Asia | V23: =C50 -> 58762 | W23: =D50 -> 31785 | X23: =E50 -> 10953 | Y23: =F50 -> 12 | Z23: =G50 -> 4 | AA23: 0 | AB23: =I50 -> 122 | AC23: =J50 -> 545 | AD23: =K50 -> 712 | AE23: =L50 -> 2127 | AF23: =M50 -> 8558 | AG23: =N50 -> 20699 | AH23: =SUM(V23:AG23) -> 134279
A24: Ireland | B24: =SUM(C24:N24) -> 1688 | C24: 392 | D24: 413 | E24: 184 | F24: 0 | G24: 0 | H24: 0 | I24: 12 | J24: 22 | K24: 23 | L24: 77 | M24: 112 | N24: 453 | O24: އަޔަލެންޑް | U24: Other continents | V24: =V21-V22-V23 -> 19860 | W24: =W21-W22-W23 -> 15652 | X24: =X21-X22-X23 -> 6662 | Y24: =Y21-Y22-Y23 -> 1 | Z24: =Z21-Z22-Z23 -> 0 | AA24: =AA21-AA22-AA23 -> 0 | AB24: =AB21-AB22-AB23 -> 586 | AC24: =AC21-AC22-AC23 -> 3263 | ... AG24: =AG21-AG22-AG23 -> 12226 | AH24: =SUM(V24:AG24) -> 72866
A25: Norway | B25: =SUM(C25:N25) -> 1624 | C25: 435 | D25: 875 | E25: 179 | F25: 0 | G25: 0 | H25: 0 | I25: 0 | J25: 15 | K25: 5 | L25: 14 | M25: 21 | N25: 80 | O25: ނޯވޭ
A26: Sweden | B26: =SUM(C26:N26) -> 5613 | C26: 1783 | D26: 2210 | E26: 592 | F26: 0 | G26: 0 | H26: 0 | I26: 6 | J26: 25 | K26: 36 | L26: 219 | M26: 120 | N26: 622 | O26: ސްވިޑެން
A27: United Kingdom | B27: =SUM(C27:N27) -> 52720 | C27: 10734 | D27: 14796 | E27: 7288 | F27: 0 | G27: 0 | H27: 1 | I27: 256 | J27: 715 | K27: 628 | L27: 1780 | M27: 2091 | N27: 14431 | O27: ޔުނައިޓެޑް ކިންގްޑަމް
A28: Others | B28: =SUM(C28:N28) -> 111 | C28: 28 | D28: 52 | E28: 12 | F28: 0 | G28: 0 | H28: 0 | I28: 1 | J28: 1 | K28: 0 | L28: 1 | M28: 3 | N28: 13 | O28: އެހެނިހެން
A29: Southern Europe | B29: =SUM(C29:N29) -> 63150 | C29: =SUM(C30:C37) -> 24902 | D29: =SUM(D30:D37) -> 24809 | E29: =SUM(E30:E37) -> 5700 | F29: =SUM(F30:F37) -> 0 | G29: =SUM(G30:G37) -> 1 | H29: =SUM(H30:H37) -> 0 | I29: =SUM(I30:I37) -> 153 | J29: =SUM(J30:J37) -> 939 | ... N29: =SUM(N30:N37) -> 3432 | O29: ދެކުނު ޔޫރަޕް
A30: Croatia | B30: =SUM(C30:N30) -> 929 | C30: 433 | D30: 225 | E30: 115 | F30: 0 | G30: 0 | H30: 0 | I30: 4 | J30: 6 | K30: 7 | L30: 9 | M30: 45 | N30: 85 | O30: ކްރޮއޭޝިއާ
A31: Greece | B31: =SUM(C31:N31) -> 871 | C31: 245 | D31: 254 | E31: 102 | F31: 0 | G31: 0 | H31: 0 | I31: 8 | J31: 61 | K31: 24 | L31: 29 | M31: 36 | N31: 112 | O31: ގްރީސް
A32: Italy | B32: =SUM(C32:N32) -> 46690 | C32: 20766 | D32: 19849 | E32: 3996 | F32: 0 | G32: 1 | H32: 0 | I32: 44 | J32: 513 | K32: 72 | L32: 137 | M32: 267 | N32: 1045 | O32: އިޓަލީ
A33: Portugal | B33: =SUM(C33:N33) -> 3206 | C33: 665 | D33: 1038 | E33: 352 | F33: 0 | G33: 0 | H33: 0 | I33: 12 | J33: 165 | K33: 150 | L33: 208 | M33: 162 | N33: 454 | O33: ޕޯޗުގަލް
A34: Serbia | B34: =SUM(C34:N34) -> 1613 | C34: 396 | D34: 498 | E34: 122 | F34: 0 | G34: 0 | H34: 0 | I34: 10 | J34: 140 | K34: 51 | L34: 75 | M34: 108 | N34: 213 | O34: ސަރބިއާ
A35: Slovenia | B35: =SUM(C35:N35) -> 1561 | C35: 405 | D35: 892 | E35: 126 | F35: 0 | G35: 0 | H35: 0 | I35: 2 | J35: 36 | K35: 0 | L35: 10 | M35: 18 | N35: 72 | O35: ސްލޮވޭނިއާ
A36: Spain | B36: =SUM(C36:N36) -> 6778 | C36: 1557 | D36: 1633 | E36: 713 | F36: 0 | G36: 0 | H36: 0 | I36: 62 | J36: 5 | K36: 466 | L36: 608 | M36: 492 | N36: 1242 | O36: ސްޕެއިން
A37: Others | B37: =SUM(C37:N37) -> 1502 | C37: 435 | D37: 420 | E37: 174 | F37: 0 | G37: 0 | H37: 0 | I37: 11 | J37: 13 | K37: 16 | L37: 143 | M37: 81 | N37: 209 | O37: އެހެނިހެން
A38: Western Europe | B38: =SUM(C38:N38) -> 91696 | C38: =SUM(C39:C45) -> 24416 | D38: =SUM(D39:D45) -> 32016 | E38: =SUM(E39:E45) -> 14672 | F38: =SUM(F39:F45) -> 0 | G38: =SUM(G39:G45) -> 13 | H38: =SUM(H39:H45) -> 0 | I38: =SUM(I39:I45) -> 298 | J38: =SUM(J39:J45) -> 771 | ... N38: =SUM(N39:N45) -> 12282 | O38: ހުޅަނގު ޔޫރަޕް
A39: Austria | B39: =SUM(C39:N39) -> 8103 | C39: 2774 | D39: 3005 | E39: 1138 | F39: 0 | G39: 0 | H39: 0 | I39: 3 | J39: 65 | K39: 51 | L39: 136 | M39: 240 | N39: 691 | O39: އޮސްޓްރިއާ
A40: Belgium | B40: =SUM(C40:N40) -> 2921 | C40: 695 | D40: 1026 | E40: 418 | F40: 0 | G40: 0 | H40: 0 | I40: 9 | J40: 9 | K40: 19 | L40: 63 | M40: 125 | N40: 557 | O40: ބެލްޖިއަމް
A41: France | B41: =SUM(C41:N41) -> 28031 | C41: 6955 | D41: 10787 | E41: 4042 | F41: 0 | G41: 1 | H41: 0 | I41: 58 | J41: 301 | K41: 279 | L41: 1093 | M41: 517 | N41: 3998 | O41: ފްރާންސް
A42: Germany | B42: =SUM(C42:N42) -> 36435 | C42: 9859 | D42: 11698 | E42: 6671 | F42: 0 | G42: 11 | H42: 0 | I42: 133 | J42: 306 | K42: 362 | L42: 949 | M42: 2083 | N42: 4363 | O42: ޖަރުމަނީ
A43: Netherlands | B43: =SUM(C43:N43) -> 3258 | C43: 1021 | D43: 1094 | E43: 472 | F43: 0 | G43: 1 | H43: 0 | I43: 16 | J43: 45 | K43: 55 | L43: 72 | M43: 120 | N43: 362 | O43: ނެދަލެންޑްސް
A44: Switzerland | B44: =SUM(C44:N44) -> 12517 | C44: 3036 | D44: 4264 | E44: 1871 | F44: 0 | G44: 0 | H44: 0 | I44: 79 | J44: 42 | K44: 64 | L44: 165 | M44: 786 | N44: 2210 | O44: ސްވިޓްޒަލެންޑް | S44: ..
A45: Others | B45: =SUM(C45:N45) -> 431 | C45: 76 | D45: 142 | E45: 60 | F45: 0 | G45: 0 | H45: 0 | I45: 0 | J45: 3 | K45: 1 | L45: 12 | M45: 36 | N45: 101 | O45: އެހެނިހެން
A46: East/Mediterranean Europe | B46: =SUM(C46:N46) -> 5298 | C46: =SUM(C47:C49) -> 1863 | D46: =SUM(D47:D49) -> 1323 | E46: =SUM(E47:E49) -> 432 | F46: =SUM(F47:F49) -> 0 | G46: =SUM(G47:G49) -> 0 | H46: =SUM(H47:H49) -> 0 | I46: =SUM(I47:I49) -> 46 | J46: =SUM(J47:J49) -> 126 | ... N46: =SUM(N47:N49) -> 706 | O46: އިރުމަތީ ޔޫރަޕް
A47: Israel | B47: =SUM(C47:N47) -> 1782 | C47: 480 | D47: 519 | E47: 154 | F47: 0 | G47: 0 | H47: 0 | I47: 8 | J47: 47 | K47: 122 | L47: 138 | M47: 78 | N47: 236 | O47: އިސްރާއީލް
A48: Turkey | B48: =SUM(C48:N48) -> 3164 | C48: 1327 | D48: 737 | E48: 257 | F48: 0 | G48: 0 | H48: 0 | I48: 34 | J48: 74 | K48: 118 | L48: 157 | M48: 121 | N48: 339 | O48: ތުރުކީ
A49: Others | B49: =SUM(C49:N49) -> 352 | C49: 56 | D49: 67 | E49: 21 | F49: 0 | G49: 0 | H49: 0 | I49: 4 | J49: 5 | K49: 5 | L49: 22 | M49: 41 | N49: 131 | O49: އެހެނިހެން
A50: Asia | B50: =SUM(C50:N50) -> 134279 | C50: =C51+C57+C66 -> 58762 | D50: =D51+D57+D66 -> 31785 | E50: =E51+E57+E66 -> 10953 | F50: =F51+F57+F66 -> 12 | G50: =G51+G57+G66 -> 4 | H50: =H51+H57+H66 -> 0 | I50: =I51+I57+I66 -> 122 | J50: =J51+J57+J66 -> 545 | ... N50: =N51+N57+N66 -> 20699 | O50: އޭޝިއާ
A51: North East Asia | B51: =SUM(C51:N51) -> 51319 | C51: =SUM(C52:C56) -> 38543 | D51: =SUM(D52:D56) -> 9652 | E51: =SUM(E52:E56) -> 2383 | F51: =SUM(F52:F56) -> 0 | G51: =SUM(G52:G56) -> 0 | H51: =SUM(H52:H56) -> 0 | I51: =SUM(I52:I56) -> 27 | J51: =SUM(J52:J56) -> 56 | ... N51: =SUM(N52:N56) -> 372 | O51: އިރު އުތުރު އޭޝިއާ
A52: China | B52: =SUM(C52:N52) -> 34245 | C52: 31744 | D52: 1647 | E52: 498 | F52: 0 | G52: 0 | H52: 0 | I52: 16 | J52: 34 | K52: 33 | L52: 41 | M52: 61 | N52: 171 | O52: ޗައިނާ
A53: Japan | B53: =SUM(C53:N53) -> 8479 | C53: 2808 | D53: 4052 | E53: 1442 | F53: 0 | G53: 0 | H53: 0 | I53: 6 | J53: 16 | K53: 14 | L53: 19 | M53: 27 | N53: 95 | O53: ޖަޕާން
A54: Korea | B54: =SUM(C54:N54) -> 5895 | C54: 2721 | D54: 2847 | E54: 154 | F54: 0 | G54: 0 | H54: 0 | I54: 4 | J54: 4 | K54: 14 | L54: 26 | M54: 38 | N54: 87 | O54: ކޮރެއާ
A55: Taiwan | B55: =SUM(C55:N55) -> 2628 | C55: 1226 | D55: 1093 | E55: 277 | F55: 0 | G55: 0 | H55: 0 | I55: 1 | J55: 2 | K55: 2 | L55: 3 | M55: 6 | N55: 18 | O55: ޓައިވާން
A56: Others | B56: =SUM(C56:N56) -> 72 | C56: 44 | D56: 13 | E56: 12 | F56: 0 | G56: 0 | H56: 0 | I56: 0 | J56: 0 | K56: 0 | L56: 1 | M56: 1 | N56: 1 | O56: އެހެނިހެން
A57: South East Asia | B57: =SUM(C57:N57) -> 12746 | C57: =SUM(C58:C65) -> 4198 | D57: =SUM(D58:D65) -> 4901 | E57: =SUM(E58:E65) -> 2482 | F57: =SUM(F58:F65) -> 0 | G57: =SUM(G58:G65) -> 0 | H57: =SUM(H58:H65) -> 0 | I57: =SUM(I58:I65) -> 33 | J57: =SUM(J58:J65) -> 117 | ... N57: =SUM(N58:N65) -> 531 | O57: އިރު ދެކުނު އޭޝިއާ
A58: Indonesia | B58: =SUM(C58:N58) -> 857 | C58: 292 | D58: 267 | E58: 141 | F58: 0 | G58: 0 | H58: 0 | I58: 9 | J58: 10 | K58: 6 | L58: 19 | M58: 55 | N58: 58 | O58: އިންޑޮނޭޝިއާ
A59: Malaysia | B59: =SUM(C59:N59) -> 2946 | C59: 908 | D59: 1252 | E59: 714 | F59: 0 | G59: 0 | H59: 0 | I59: 1 | J59: 4 | K59: 10 | L59: 5 | M59: 9 | N59: 43 | O59: މެލޭޝިއާ
A60: Myanmar | B60: =SUM(C60:N60) -> 171 | C60: 89 | D60: 57 | E60: 17 | F60: 0 | G60: 0 | H60: 0 | I60: 0 | J60: 0 | K60: 3 | L60: 2 | M60: 1 | N60: 2 | O60: މިޔަންމާ
A61: Philippines | B61: =SUM(C61:N61) -> 1756 | C61: 483 | D61: 496 | E61: 159 | F61: 0 | G61: 0 | H61: 0 | I61: 13 | J61: 78 | K61: 35 | L61: 92 | M61: 120 | N61: 280 | O61: ފިލިޕިންސް
A62: Singapore | B62: =SUM(C62:N62) -> 2117 | C62: 692 | D62: 688 | E62: 640 | F62: 0 | G62: 0 | H62: 0 | I62: 4 | J62: 4 | K62: 5 | L62: 6 | M62: 29 | N62: 49 | O62: ސިންގަޕޯ
A63: Thailand | B63: =SUM(C63:N63) -> 3468 | C63: 939 | D63: 1704 | E63: 673 | F63: 0 | G63: 0 | H63: 0 | I63: 2 | J63: 15 | K63: 11 | L63: 18 | M63: 33 | N63: 73 | O63: ތައިލެންޑް
A64: Vietnam | B64: =SUM(C64:N64) -> 1264 | C64: 744 | D64: 371 | E64: 100 | F64: 0 | G64: 0 | H64: 0 | I64: 3 | J64: 6 | K64: 2 | L64: 5 | M64: 10 | N64: 23 | O64: ވިއެޓްނާމް
A65: Others | B65: =SUM(C65:N65) -> 167 | C65: 51 | D65: 66 | E65: 38 | F65: 0 | G65: 0 | H65: 0 | I65: 1 | J65: 0 | K65: 2 | L65: 3 | M65: 3 | N65: 3 | O65: އެހެނިހެން
A66: South Asia | B66: =SUM(C66:N66) -> 70214 | C66: =SUM(C67:C72) -> 16021 | D66: =SUM(D67:D72) -> 17232 | E66: =SUM(E67:E72) -> 6088 | F66: =SUM(F67:F72) -> 12 | G66: =SUM(G67:G72) -> 4 | H66: =SUM(H67:H72) -> 0 | I66: =SUM(I67:I72) -> 62 | J66: =SUM(J67:J72) -> 372 | ... N66: =SUM(N67:N72) -> 19796 | O66: ދެކުނު އޭޝިއާ
A67: Bangladesh | B67: =SUM(C67:N67) -> 1139 | C67: 391 | D67: 296 | E67: 58 | F67: 11 | G67: 3 | H67: 0 | I67: 31 | J67: 27 | K67: 38 | L67: 73 | M67: 69 | N67: 142 | O67: ބަންގްލަދެޝް
A68: India | B68: =SUM(C68:N68) -> 62931 | C68: 13845 | D68: 15521 | E68: 5496 | F68: 1 | G68: 1 | H68: 0 | I68: 2 | J68: 115 | K68: 308 | L68: 1396 | M68: 7609 | N68: 18637 | O68: އިންޑިއާ
A69: Iran | B69: =SUM(C69:N69) -> 642 | C69: 84 | D69: 62 | E69: 6 | F69: 0 | G69: 0 | H69: 0 | I69: 24 | J69: 56 | K69: 74 | L69: 129 | M69: 73 | N69: 134 | O69: އިރާން
A70: Pakistan | B70: =SUM(C70:N70) -> 2861 | C70: 568 | D70: 470 | E70: 176 | F70: 0 | G70: 0 | H70: 0 | I70: 3 | J70: 146 | K70: 145 | L70: 243 | M70: 358 | N70: 752 | O70: ޕާކިސްތާން
A71: Sri Lanka | B71: =SUM(C71:N71) -> 2268 | C71: 1003 | D71: 773 | E71: 324 | F71: 0 | G71: 0 | H71: 0 | I71: 0 | J71: 22 | K71: 3 | L71: 30 | M71: 34 | N71: 79 | O71: ސްރީ ލަންކާ
A72: Others | B72: =SUM(C72:N72) -> 373 | C72: 130 | D72: 110 | E72: 28 | F72: 0 | G72: 0 | H72: 0 | I72: 2 | J72: 6 | K72: 7 | L72: 16 | M72: 22 | N72: 52 | O72: އެހެނިހެން
A73: Africa | B73: =SUM(C73:N73) -> 6458 | C73: =SUM(C74:C77) -> 1536 | D73: =SUM(D74:D77) -> 1118 | E73: =SUM(E74:E77) -> 658 | F73: =SUM(F74:F77) -> 0 | G73: =SUM(G74:G77) -> 0 | H73: =SUM(H74:H77) -> 0 | I73: =SUM(I74:I77) -> 55 | J73: =SUM(J74:J77) -> 163 | ... N73: =SUM(N74:N77) -> 1996 | O73: އެފްރިކާ
A74: Algeria | B74: =SUM(C74:N74) -> 431 | C74: 104 | D74: 106 | E74: 104 | F74: 0 | G74: 0 | H74: 0 | I74: 1 | J74: 11 | K74: 5 | L74: 11 | M74: 21 | N74: 68 | O74: އަލްޖީރިއާ
A75: Morocco | B75: =SUM(C75:N75) -> 748 | C75: 164 | D75: 199 | E75: 103 | F75: 0 | G75: 0 | H75: 0 | I75: 17 | J75: 38 | K75: 26 | L75: 31 | M75: 40 | N75: 130 | O75: މޮރޮކޯ
A76: South Africa | B76: =SUM(C76:N76) -> 2685 | C76: 807 | D76: 338 | E76: 279 | F76: 0 | G76: 0 | H76: 0 | I76: 27 | J76: 48 | K76: 31 | L76: 56 | M76: 171 | N76: 928 | O76: ދެކުނު އެފްރިކާ
A77: Others | B77: =SUM(C77:N77) -> 2594 | C77: 461 | D77: 475 | E77: 172 | F77: 0 | G77: 0 | H77: 0 | I77: 10 | J77: 66 | K77: 97 | L77: 172 | M77: 271 | N77: 870 | O77: އެހެނިހެން
A78: America | B78: =SUM(C78:N78) -> 32060 | C78: =SUM(C79:C84) -> 8078 | D78: =SUM(D79:D84) -> 7460 | E78: =SUM(E79:E84) -> 3183 | F78: =SUM(F79:F84) -> 0 | G78: =SUM(G79:G84) -> 0 | H78: =SUM(H79:H84) -> 0 | I78: =SUM(I79:I84) -> 255 | J78: =SUM(J79:J84) -> 970 | ... N78: =SUM(N79:N84) -> 4929 | O78: އެމެރިކާ
A79: Argentina | B79: =SUM(C79:N79) -> 956 | C79: 350 | D79: 334 | E79: 160 | F79: 0 | G79: 0 | H79: 0 | I79: 0 | J79: 7 | K79: 12 | L79: 31 | M79: 30 | N79: 32 | O79: އަރޖެންޓީނާ
A80: Brazil | B80: =SUM(C80:N80) -> 5497 | C80: 1036 | D80: 1038 | E80: 498 | F80: 0 | G80: 0 | H80: 0 | I80: 22 | J80: 168 | K80: 444 | L80: 540 | M80: 891 | N80: 860 | O80: ބްރެޒިލް
A81: Canada | B81: =SUM(C81:N81) -> 3872 | C81: 1140 | D81: 1007 | E81: 414 | F81: 0 | G81: 0 | H81: 0 | I81: 22 | J81: 76 | K81: 73 | L81: 143 | M81: 254 | N81: 743 | O81: ކެނެޑާ
A82: Mexico | B82: =SUM(C82:N82) -> 512 | C82: 111 | D82: 135 | E82: 113 | F82: 0 | G82: 0 | H82: 0 | I82: 1 | J82: 5 | K82: 17 | L82: 42 | M82: 26 | N82: 62 | O82: މެކްސިކޯ
A83: United States | B83: =SUM(C83:N83) -> 19759 | C83: 5051 | D83: 4543 | E83: 1820 | F83: 0 | G83: 0 | H83: 0 | I83: 189 | J83: 674 | K83: 935 | L83: 1449 | M83: 2093 | N83: 3005 | O83: ޔުނައިޓެޑް ސްޓޭޓްސް
A84: Others | B84: =SUM(C84:N84) -> 1464 | C84: 390 | D84: 403 | E84: 178 | F84: 0 | G84: 0 | H84: 0 | I84: 21 | J84: 40 | K84: 38 | L84: 71 | M84: 96 | N84: 227 | O84: އެހެނިހެން
A85: Oceania | B85: =SUM(C85:N85) -> 7964 | C85: =SUM(C86:C88) -> 2926 | D85: =SUM(D86:D88) -> 2260 | E85: =SUM(E86:E88) -> 1468 | F85: =SUM(F86:F88) -> 0 | G85: =SUM(G86:G88) -> 0 | H85: =SUM(H86:H88) -> 0 | I85: =SUM(I86:I88) -> 29 | J85: =SUM(J86:J88) -> 62 | ... N85: =SUM(N86:N88) -> 728 | O85: އޯޝިއާނާ
A86: Australia | B86: =SUM(C86:N86) -> 7220 | C86: 2689 | D86: 2040 | E86: 1388 | F86: 0 | G86: 0 | H86: 0 | I86: 17 | J86: 49 | K86: 61 | L86: 160 | M86: 209 | N86: 607 | O86: އޮސްޓްރޭލިއާ
A87: New Zealand | B87: =SUM(C87:N87) -> 719 | C87: 227 | D87: 210 | E87: 80 | F87: 0 | G87: 0 | H87: 0 | I87: 12 | J87: 11 | K87: 5 | L87: 27 | M87: 27 | N87: 120 | O87: ނިއުޒިލެންޑް
A88: Others | B88: =SUM(C88:N88) -> 25 | C88: 10 | D88: 10 | E88: 0 | F88: 0 | G88: 0 | H88: 0 | I88: 0 | J88: 2 | K88: 0 | L88: 2 | M88: 0 | N88: 1 | O88: އެހެނިހެން
A89: Middle East | B89: =SUM(C89:N89) -> 26286 | C89: =SUM(C90:C99) -> 7297 | D89: =SUM(D90:D99) -> 4793 | E89: =SUM(E90:E99) -> 1346 | F89: =SUM(F90:F99) -> 1 | G89: =SUM(G90:G99) -> 0 | H89: =SUM(H90:H99) -> 0 | I89: =SUM(I90:I99) -> 247 | J89: =SUM(J90:J99) -> 2066 | ... N89: =SUM(N90:N99) -> 4557 | O89: މެދު އިރުމަތީ
A90: Egypt | B90: =SUM(C90:N90) -> 2543 | C90: 280 | D90: 286 | E90: 158 | F90: 1 | G90: 0 | H90: 0 | I90: 29 | J90: 179 | K90: 232 | L90: 398 | M90: 439 | N90: 541 | O90: އިޖިޕްޓް
A91: Jordan | B91: =SUM(C91:N91) -> 750 | C91: 114 | D91: 119 | E91: 35 | F91: 0 | G91: 0 | H91: 0 | I91: 1 | J91: 20 | K91: 22 | L91: 83 | M91: 98 | N91: 258 | O91: ޖޯޑްން
A92: Kuwait | B92: =SUM(C92:N92) -> 2816 | C92: 585 | D92: 1252 | E92: 99 | F92: 0 | G92: 0 | H92: 0 | I92: 2 | J92: 40 | K92: 97 | L92: 141 | M92: 233 | N92: 367 | O92: ކުވެއިތު
A93: Lebanon | B93: =SUM(C93:N93) -> 1049 | C93: 94 | D93: 161 | E93: 41 | F93: 0 | G93: 0 | H93: 0 | I93: 12 | J93: 34 | K93: 43 | L93: 85 | M93: 144 | N93: 435 | O93: ލެބަނާން
A94: Oman | B94: =SUM(C94:N94) -> 440 | C94: 103 | D94: 107 | E94: 26 | F94: 0 | G94: 0 | H94: 0 | I94: 0 | J94: 10 | K94: 17 | L94: 30 | M94: 47 | N94: 100 | O94: އޮމާން
A95: Qatar | B95: =SUM(C95:N95) -> 1530 | C95: 239 | D95: 300 | E95: 103 | F95: 0 | G95: 0 | H95: 0 | I95: 3 | J95: 25 | K95: 35 | L95: 68 | M95: 181 | N95: 576 | O95: ޤަތަރު
A96: Saudi Arabia | B96: =SUM(C96:N96) -> 7578 | C96: 4992 | D96: 1705 | E96: 662 | F96: 0 | G96: 0 | H96: 0 | I96: 4 | J96: 31 | K96: 34 | L96: 27 | M96: 35 | N96: 88 | O96: ސައުދީ އަރަބިއްޔާ
A97: Syrian Arab Republic | B97: =SUM(C97:N97) -> 433 | C97: 84 | D97: 65 | E97: 23 | F97: 0 | G97: 0 | H97: 0 | I97: 9 | J97: 19 | K97: 28 | L97: 36 | M97: 56 | N97: 113 | O97: ސީރިއަން އަރަބް ރިޕަބްލިކް
A98: United Arab Emirates | B98: =SUM(C98:N98) -> 7368 | C98: 506 | D98: 511 | E98: 115 | F98: 0 | G98: 0 | H98: 0 | I98: 167 | J98: 1627 | K98: 1041 | L98: 843 | M98: 1033 | N98: 1525 | O98: ޔުނައިޓެޑް އަރަބް އެމަރެޓްސް
A99: Others | B99: =SUM(C99:N99) -> 1779 | C99: 300 | D99: 287 | E99: 84 | F99: 0 | G99: 0 | H99: 0 | I99: 20 | J99: 81 | K99: 78 | L99: 111 | M99: 264 | N99: 554 | O99: އެހެނިހެން
A100: UN Passpoert holders | B100: =SUM(C100:N100) -> 21 | C100: 11 | D100: 5 | E100: 3 | F100: 0 | G100: 0 | H100: 0 | I100: 0 | J100: 0 | K100: 0 | L100: 1 | M100: 1 | N100: 0 | O100: ޔޫ އެން ޕާސްޕޯޓު ހޯލްޑަރސް
A101: Others Not Stated | B101: =SUM(C101:N101) -> 77 | C101: 12 | D101: 16 | E101: 4 | F101: 0 | G101: 0 | H101: 0 | I101: 0 | J101: 2 | K101: 3 | L101: 7 | M101: 17 | N101: 16 | O101: އެހެނިހެން
...

Sheet 10.14
B1: ތާވަލު 10.14: ރިސޯޓްތަކުގެ އެނދުގެ ޖާގައާއި ބައިނަލްއަޤަވާމީ ވައިގެ ބަނދަރާއިހުރި ދުރުމިން، 2013 - 2020
B2: Table 10.14 BED CAPACITY OF TOURIST RESORTS AND THE DISTANCE FROM MALE' INTERNATIONAL AIRPORT, 2013 - 2020
B4: Resorts | C4: Island Name | D4: Year of Initial | E4: Initial Bed | F4: Distance from | K4: Bed Capacity (end year)* | U4: % Share
D5: Operation | E5: Capacity | F5: Airport (in Km) | G5: 2007 | H5: 2008 | I5: 2009 | J5: 2010 | K5: 2011 | L5: 2012 | M5: 2013 | N5: 2014 | O5: 2015 | P5: 2016 | Q5: 2017 | R5: 2018 | S5: 2019 | T5: 2020 | U5: in 2020
B6: All Resorts | D6: - | E6: - | F6: - | G6: =G24+G39+G56+G67+G121+G135+G154+G158+G161+G163+G7+G189 -> 18724 | H6: =H24+H39+H56+H67+H121+H135+H154+H158+H161+H163+H7+H189+H16 -> 19556 | I6: =I24+I39+I56+I67+I121+I135+I154+I158+I161+I163+I7+I189+I16+I178 -> 20638 | J6: =J24+J39+J56+J67+J121+J135+J154+J158+J161+J163+J7+J189+J16+J178 -> 21046 | K6: =K24+K39+K56+K67+K121+K135+K154+K158+K161+K163+K7+K189+K16+K178+K175+K185 -> 21816 | L6: =L24+L39+L56+L67+L121+L135+L154+L158+L161+L163+L7+L189+L16+L178+L175+L185+L13 -> 22585 | M6: =M7+M13+M16+M24+M39+M56+M67+M121+M135+M154+M158+M161+M163+M175+M178+M185+M189+M173 -> 23487 | N6: =N7+N13+N16+N24+N39+N56+N67+N121+N135+N154+N158+N161+N163+N175+N178+N185+N189+N173 -> 24031 | O6: =O7+O13+O16+O24+O39+O56+O67+O121+O135+O154+O158+O161+O163+O175+O178+O185+O189+O173 -> 24877 | P6: =P7+P13+P16+P24+P39+P56+P67+P121+P135+P154+P158+P161+P163+P175+P178+P185+P189+P173 -> 26933 | Q6: =Q7+Q13+Q16+Q24+Q39+Q56+Q67+Q121+Q135+Q154+Q158+Q161+Q163+Q175+Q178+Q185+Q189+Q173 -> 29977 | R6: =R7+R13+R16+R24+R39+R56+R67+R121+R135+R154+R158+R161+R163+R175+R178+R185+R189+R173+R11 -> 31721 | S6: =S7+S13+S16+S24+S39+S56+S67+S121+S135+S154+S158+S161+S163+S175+S178+S185+S189+S173+S11 -> 37016 | T6: =T7+T13+T16+T24+T39+T56+T67+T121+T135+T154+T158+T161+T163+T175+T178+T185+T189+T173+T11 -> 37134 | U6: =T6/T$6*100 -> 100
B7: North Thiladhunmathi Atoll (HA) | D7: - | E7: - | F7: - | G7: =SUM(G8:G10) -> 390 | H7: =SUM(H8:H10) -> 432 | I7: =SUM(I8:I10) -> 432 | J7: =SUM(J8:J10) -> 456 | K7: =SUM(K8:K10) -> 456 | L7: =SUM(L8:L10) -> 456 | M7: =SUM(M8:M10) -> 456 | N7: =SUM(N8:N10) -> 464 | ... T7: =SUM(T8:T10) -> 394 | U7: =T7/T$6*100 -> 1.0610222
A8: 1 | B8: Alidhoo Island Resort | C8: Alidhoo | D8: 2007 | E8: 66 | F8: 300 | G8: 200 | H8: 200 | I8: 200 | J8: 200 | K8: 200 | L8: 200 | M8: 200 | N8: 200 | O8: 200 | P8: 200 | Q8: 200 | R8: 200 | S8: 200 | T8: 0 | U8: =T8/T$6*100 -> 0
A9: 2 | B9: Hideaway Beach Resort and Spa at Dhonakulhi Island Maldives | C9: Dhonakulhi | D9: 2005 | E9: 50 | F9: 250 | G9: 90 | H9: 90 | I9: 90 | J9: 90 | K9: 90 | L9: 90 | M9: 90 | N9: 90 | O9: 90 | P9: 90 | Q9: 220 | R9: 220 | S9: 220 | T9: 220 | U9: =T9/T$6*100 -> 0.59244897
A10: 3 | B10: JA Manafaru | C10: Manafaru | D10: 2007 | E10: 100 | F10: 337 | G10: 100 | H10: 142 | I10: 142 | J10: 166 | K10: 166 | L10: 166 | M10: 166 | N10: 174 | O10: 174 | P10: 174 | Q10: 174 | R10: 174 | S10: 174 | T10: 174 | U10: =T10/T$6*100 -> 0.46857328
B11: North Thiladhunmathi Atoll (H.Dh) | D11: - | E11: - | F11: - | G11: - | H11: - | I11: - | J11: - | K11: - | L11: - | M11: - | N11: - | O11: - | P11: - | Q11: - | R11: =SUM(R12) -> 118 | S11: =SUM(S12) -> 118 | T11: =SUM(T12) -> 118 | U11: =T11/T$6*100 -> 0.31776808
A12: 4 | B12: Hondaafushi Island Resort | C12: Hondaafushi | D12: 2018 | E12: 118 | F12: 291 | M12: - | N12: - | O12: - | P12: - | Q12: - | R12: 118 | S12: 118 | T12: 118 | U12: =T12/T$6*100 -> 0.31776808
B13: North Miladhunmadulu Atoll (Sh) | D13: - | E13: - | F13: - | G13: =SUM(G15) -> 0 | H13: =SUM(H15) -> 0 | I13: =SUM(I15) -> 0 | J13: =SUM(J15) -> 0 | K13: =SUM(K15) -> 0 | L13: =SUM(L15) -> 97 | M13: =SUM(M15) -> 159 | N13: =SUM(N15) -> 159 | ... P13: =SUM(P15) -> 159 | Q13: =SUM(Q14:Q15) -> 227 | R13: =SUM(R14:R15) -> 227 | S13: =SUM(S14:S15) -> 457 | T13: =SUM(T14:T15) -> 457 | U13: =T13/T$6*100 -> 1.2306781
A14: 5 | B14: Sirru Fen Fushi | C14: Gaakoshibee | D14: 2017 | E14: 68 | F14: 240 | M14: - | N14: - | O14: - | P14: - | Q14: 68 | R14: 68 | S14: 298 | T14: 298 | U14: =T14/T$6*100 -> 0.80249906
A15: 6 | B15: JW Marriott Maldives Resort & Spa | C15: Vagaru | D15: 2012 | E15: 97 | F15: - | G15: - | H15: - | I15: - | J15: - | K15: - | L15: 97 | M15: 159 | N15: 159 | O15: 159 | P15: 159 | Q15: 159 | R15: 159 | S15: 159 | T15: 159 | U15: =T15/T$6*100 -> 0.42817903
B16: South Miladhunmadulu Atoll (N) | D16: - | E16: - | F16: - | G16: =SUM(G19:G23) -> 0 | H16: =SUM(H19:H23) -> 400 | I16: =SUM(I19:I23) -> 490 | J16: =SUM(J19:J23) -> 542 | K16: =SUM(K19:K23) -> 542 | L16: =SUM(L19:L23) -> 542 | M16: =SUM(M17:M23) -> 796 | N16: =SUM(N17:N23) -> 796 | O16: =SUM(O17:O23) -> 796 | P16: =SUM(P17:P23) -> 832 | Q16: =SUM(Q17:Q23) -> 1176 | R16: =SUM(R17:R23) -> 1388 | S16: =SUM(S17:S23) -> 1398 | T16: =SUM(T17:T23) -> 1436 | U16: =T16/T$6*100 -> 3.867076
A17: 7 | B17: Cheval Blanc Randheli | C17: Randheli | D17: 2013 | E17: 120 | F17: 169 | G17: - | H17: - | I17: - | J17: - | K17: - | L17: - | M17: 120 | N17: 120 | O17: 120 | P17: 120 | Q17: 120 | R17: 120 | S17: 120 | T17: 120 | U17: =T17/T$6*100 -> 0.32315398
A18: 8 | B18: Mövenpick Resort Kuredhivaru Maldives | C18: Kuredhivaru | D18: 2018 | E18: 212 | F18: na | M18: - | N18: - | O18: - | P18: - | Q18: - | R18: 212 | S18: 222 | T18: 222 | U18: =T18/T$6*100 -> 0.59783487
A19: 9 | B19: Noku Maldives | C19: Kudafunafaru | D19: 2008 | E19: 100 | F19: 180 | G19: - | H19: 100 | I19: 100 | J19: 100 | K19: 100 | L19: 100 | M19: 100 | N19: 100 | O19: 100 | P19: 100 | Q19: 100 | R19: 100 | S19: 100 | T19: 100 | U19: =T19/T$6*100 -> 0.26929499
A20: 10 | B20: Robinson Club Noonu | C20: Orivaru | D20: 2017 | E20: - | F20: na | M20: - | N20: - | O20: - | P20: - | Q20: 300 | R20: 300 | S20: 300 | T20: 300 | U20: =T20/T$6*100 -> 0.80788496
A21: 11 | B21: Soneva Jani | C21: Medhufaru | D21: 2016 | E21: 36 | F21: 170 | G21: - | H21: - | I21: - | J21: - | K21: - | L21: - | M21: - | N21: - | O21: - | P21: 36 | Q21: 74 | R21: 74 | S21: 74 | T21: 112 | U21: =T21/T$6*100 -> 0.30161038
A22: 12 | B22: The Sun Siyam Iru Fushi Maldives | C22: Medhafushi | D22: 2008 | E22: 200 | F22: 238 | G22: - | H22: 300 | I22: 390 | J22: 442 | K22: 442 | L22: 442 | M22: 442 | N22: 442 | O22: 442 | P22: 442 | Q22: 448 | R22: 448 | S22: 448 | T22: 448 | U22: =T22/T$6*100 -> 1.2064415
A23: 13 | B23: Velaa Private Island | C23: Fushivelavaru | D23: 2013 | E23: 100 | F23: 186 | G23: - | H23: - | I23: - | J23: - | K23: - | L23: - | M23: 134 | N23: 134 | O23: 134 | P23: 134 | Q23: 134 | R23: 134 | S23: 134 | T23: 134 | U23: =T23/T$6*100 -> 0.36085528
B24: North Maalhosmadulu (R) | D24: - | E24: - | F24: - | G24: =SUM(G25) -> 470 | H24: =SUM(H25) -> 470 | I24: =SUM(I25) -> 470 | J24: =SUM(J25) -> 470 | K24: =SUM(K25) -> 470 | L24: =SUM(L25) -> 470 | M24: =SUM(M25) -> 470 | N24: =SUM(N25:N37) -> 656 | O24: =SUM(O25:O37) -> 680 | P24: =SUM(P25:P37) -> 810 | Q24: =SUM(Q25:Q37) -> 1616 | R24: =SUM(R25:R37) -> 1960 | S24: =SUM(S25:S38) -> 3324 | T24: =SUM(T25:T38) -> 3288 | U24: =T24/T$6*100 -> 8.8544191
A25: 14 | B25: Adhaaran Select Meedhupparu | C25: Meedhupparu | D25: 2000 | E25: 430 | F25: 130.3 | G25: 470 | H25: 470 | I25: 470 | J25: 470 | K25: 470 | L25: 470 | M25: 470 | N25: 470 | O25: 470 | P25: 470 | Q25: 470 | R25: 470 | S25: 470 | T25: 470 | U25: =T25/T$6*100 -> 1.2656864
A26: 15 | B26: Brennia Kottefaru | C26: Kottefaru | D26: 2020 | E26: 158 | T26: 158 | U26: =T26/T$6*100 -> 0.42548608
A27: 16 | B27: Carpe Diem Beach Resort and Spa Maldives | C27: Huruvalhi | D27: 2018 | E27: 244 | F27: na | M27: - | N27: - | O27: - | P27: - | Q27: - | R27: 244 | S27: 244 | T27: 244 | U27: =T27/T$6*100 -> 0.65707977
A28: 17 | B28: Dhigali Maldives | C28: Dhigali | D28: 2017 | E28: 358 | F28: na | M28: - | N28: - | O28: - | P28: - | Q28: 358 | R28: 358 | S28: 358 | T28: 362 | U28: =T28/T$6*100 -> 0.97484785
A29: 18 | B29: Emerald Maldives Resort & Spa Fasmendhoo | C29: Fasmendhoo | D29: 2019 | E29: 266 | F29: - | G29: - | H29: - | I29: - | J29: - | K29: - | L29: - | M29: - | N29: - | O29: - | P29: - | Q29: - | R29: - | S29: 266 | T29: 266 | U29: =T29/T$6*100 -> 0.71632466
A30: 19 | B30: Faarufushi Maldives | C30: Faarufushi | D30: 2019 | E30: 160 | F30: - | G30: - | H30: - | I30: - | J30: - | K30: - | L30: - | M30: - | N30: - | O30: - | P30: - | Q30: - | R30: - | S30: 160 | T30: 160 | U30: =T30/T$6*100 -> 0.43087198
A31: 20 | B31: Furaveri Island Resort & Spa | C31: Furaveri | D31: 2016 | E31: 130 | F31: 155 | G31: - | H31: - | I31: - | J31: - | K31: - | L31: - | M31: - | N31: - | O31: - | P31: 130 | Q31: 202 | R31: 202 | S31: 202 | T31: 214 | U31: =T31/T$6*100 -> 0.57629127
A32: 21 | B32: Heritance Aarah | C32: Aarah | D32: 2019 | E32: 300 | F32: - | G32: - | H32: - | I32: - | J32: - | K32: - | L32: - | M32: - | N32: - | O32: - | P32: - | Q32: - | R32: - | S32: 300 | T32: 300 | U32: =T32/T$6*100 -> 0.80788496
A33: 22 | B33: Inter Continental Maldives Maamunagau | C33: Maamunagau | D33: 2019 | E33: 194 | F33: - | G33: - | H33: - | I33: - | J33: - | K33: - | L33: - | M33: - | N33: - | O33: - | P33: - | Q33: - | R33: - | S33: 194 | T33: 194 | U33: =T33/T$6*100 -> 0.52243227
A34: 23 | B34: Joali Muravandhoo (Muravandhoo) | C34: Muravandhoo | D34: 2018 | E34: 100 | F34: na | M34: - | N34: - | O34: - | P34: - | Q34: - | R34: 100 | S34: 160 | T34: 160 | U34: =T34/T$6*100 -> 0.43087198
A35: 24 | B35: Kudafushi Resort & Spa | C35: Kudafushi | D35: 2017 | E35: 214 | F35: na | M35: - | N35: - | O35: - | P35: - | Q35: 214 | R35: 214 | S35: 214 | T35: 214 | U35: =T35/T$6*100 -> 0.57629127
A36: 25 | B36: Loama Resort Maldives at Maamigili | C36: Maamigili | D36: 2014 | E36: 40 | F36: 177 | G36: - | H36: - | I36: - | J36: - | K36: - | L36: - | M36: - | N36: 186 | O36: 210 | P36: 210 | Q36: 210 | R36: 210 | S36: 210 | T36: 0 | U36: =T36/T$6*100 -> 0
A37: 26 | B37: Reethi Faru Resort | C37: Filaidhoo | D37: 2017 | E37: 162 | F37: na | M37: - | N37: - | O37: - | P37: - | Q37: 162 | R37: 162 | S37: 328 | T37: 328 | U37: =T37/T$6*100 -> 0.88328755
A38: 27 | B38: You & Me By Cocoon | C38: Uthurumaafaru | D38: 2019 | E38: 218 | F38: - | G38: - | H38: - | I38: - | J38: - | K38: - | L38: - | M38: - | N38: - | O38: - | P38: - | Q38: - | R38: - | S38: 218 | T38: 218 | U38: =T38/T$6*100 -> 0.58706307
B39: South Maalhosmadulu (B) | D39: - | E39: - | F39: - | G39: =SUM(G40:G55) -> 1240 | H39: =SUM(H40:H55) -> 1240 | I39: =SUM(I40:I55) -> 1240 | J39: =SUM(J40:J55) -> 1398 | K39: =SUM(K40:K55) -> 1398 | L39: =SUM(L40:L55) -> 1660 | M39: =SUM(M40:M55) -> 1704 | N39: =SUM(N40:N55) -> 1704 | ... T39: =SUM(T40:T55) -> 3104 | U39: =T39/T$6*100 -> 8.3589164
A40: 28 | B40: Anantara Kihavah Villas | C40: Kihavah Haruvalhi | D40: 2010 | E40: 110 | F40: 125 | G40: - | H40: - | I40: - | J40: 110 | K40: 110 | L40: 164 | M40: 172 | N40: 172 | O40: 172 | P40: 172 | Q40: 172 | R40: 178 | S40: 178 | T40: 178 | U40: =T40/T$6*100 -> 0.47934507
A41: 29 | B41: Coco Palm Dhunikolhu | C41: Dhunikolhu | D41: 1998 | E41: 192 | F41: 124 | G41: 200 | H41: 200 | I41: 200 | J41: 200 | K41: 200 | L41: 200 | M41: 200 | N41: 200 | O41: 196 | P41: 196 | Q41: 196 | R41: 196 | S41: 196 | T41: 196 | U41: =T41/T$6*100 -> 0.52781817
A42: 30 | B42: Dhigufaru Island Resort | C42: Dhigufaruvinagandu | D42: 2016 | E42: 80 | F42: 121 | G42: - | H42: - | I42: - | J42: - | K42: - | L42: - | M42: - | N42: - | O42: - | P42: 80 | Q42: 80 | R42: 80 | S42: 80 | T42: 170 | U42: =T42/T$6*100 -> 0.45780148
A43: 31 | B43: Dreamland - The Unique Sea & Lake Resort / Spa | C43: Hirundhoo | D43: 2018 | E43: 180 | F43: na | M43: - | N43: - | O43: - | P43: - | Q43: - | R43: 180 | S43: 180 | T43: 180 | U43: =T43/T$6*100 -> 0.48473097
A44: 32 | B44: Dusit Thani Maldives | C44: Mudhdhoo | D44: 2012 | E44: 20 | F44: 120 | G44: - | H44: - | I44: - | J44: - | K44: - | L44: 208 | M44: 208 | N44: 208 | O44: 208 | P44: 208 | Q44: 208 | R44: 208 | S44: 208 | T44: 208 | U44: =T44/T$6*100 -> 0.56013357
A45: 33 | B45: Finolhu Baa Atoll Maldives | C45: Kanufushi | D45: 2016 | E45: 272 | F45: 132 | G45: - | H45: - | I45: - | J45: - | K45: - | L45: - | M45: - | N45: - | O45: - | P45: 272 | Q45: 272 | R45: 272 | S45: 272 | T45: 272 | U45: =T45/T$6*100 -> 0.73248236
A46: 34 | B46: Four Seasons Private Island Maldives at Voavah | C46: Voavah | D46: 2016 | E46: 26 | F46: 135 | G46: - | H46: - | I46: - | J46: - | K46: - | L46: - | M46: - | N46: - | O46: - | P46: 26 | Q46: 26 | R46: 26 | S46: 26 | T46: 26 | U46: =T46/T$6*100 -> 0.070016696
A47: 35 | B47: Four Seasons Resort Maldives at Landaa Giraavaru | C47: Landaa Giraavaru | D47: 2006 | E47: 206 | F47: 120 | G47: 206 | H47: 206 | I47: 206 | J47: 206 | K47: 206 | L47: 206 | M47: 206 | N47: 206 | O47: 206 | P47: 244 | Q47: 244 | R47: 244 | S47: 244 | T47: 244 | U47: =T47/T$6*100 -> 0.65707977
A48: 36 | B48: Kihaad Resort | C48: Kihaadhuffaru | D48: 1999 | E48: 200 | F48: 104.6 | G48: 200 | H48: 200 | I48: 200 | J48: 200 | K48: 200 | L48: 200 | M48: 236 | N48: 236 | O48: 236 | P48: 236 | Q48: 236 | R48: 236 | S48: 236 | T48: 236 | U48: =T48/T$6*100 -> 0.63553617
A49: 37 | B49: Milaidhoo Island Maldives | C49: Milaidhoo | D49: 2016 | E49: 30 | F49: 128 | G49: - | H49: - | I49: - | J49: - | K49: - | L49: - | M49: - | N49: - | O49: - | P49: 88 | Q49: 100 | R49: 100 | S49: 100 | T49: 100 | U49: =T49/T$6*100 -> 0.26929499
A50: 38 | B50: Reethi Beach Resort | C50: Fonimagoodhoo | D50: 1998 | E50: 200 | F50: 104.6 | G50: 200 | H50: 200 | I50: 200 | J50: 248 | K50: 248 | L50: 248 | M50: 248 | N50: 248 | O50: 248 | P50: 248 | Q50: 248 | R50: 248 | S50: 248 | T50: 248 | U50: =T50/T$6*100 -> 0.66785156
A51: 39 | B51: Royal Island Resort & Spa | C51: Horubadhoo | D51: 2001 | E51: 304 | F51: 110 | G51: 304 | H51: 304 | I51: 304 | J51: 304 | K51: 304 | L51: 304 | M51: 304 | N51: 304 | O51: 304 | P51: 304 | Q51: 304 | R51: 304 | S51: 304 | T51: 304 | U51: =T51/T$6*100 -> 0.81865676
A52: 40 | B52: Soneva Fushi By Six Senses | C52: Kunfunadhoo | D52: 1983 | E52: 50 | F52: 104.6 | G52: 130 | H52: 130 | I52: 130 | J52: 130 | K52: 130 | L52: 130 | M52: 130 | N52: 130 | O52: 130 | P52: 130 | Q52: 228 | R52: 228 | S52: 228 | T52: 286 | U52: =T52/T$6*100 -> 0.77018366
A53: 41 | B53: The Nautilus Maldives | C53: Thiladhoo | D53: 2019 | E53: 24 | F53: na | M53: - | N53: - | O53: - | P53: - | Q53: - | R53: - | S53: 24 | T53: 62 | U53: =T53/T$6*100 -> 0.16696289
A54: 42 | B54: The Westin Maldives Miriandhoo Resort | C54: Miriandhoo | D54: 2018 | E54: 134 | F54: na | M54: - | N54: - | O54: - | P54: - | Q54: - | R54: 134 | S54: 146 | T54: 146 | U54: =T54/T$6*100 -> 0.39317068
A55: 43 | B55: Vakkaru Maldives | C55: Vakkaru | D55: 2017 | E55: - | F55: - | M55: - | N55: - | O55: - | P55: - | Q55: 248 | R55: 248 | S55: 248 | T55: 248 | U55: =T55/T$6*100 -> 0.66785156
B56: Faadhippolhu (Lh) | D56: - | E56: - | F56: - | G56: =SUM(G62:G66) -> 1276 | H56: =SUM(H62:H66) -> 1294 | I56: =SUM(I62:I66) -> 1336 | J56: =SUM(J62:J66) -> 1336 | K56: =SUM(K62:K66) -> 1336 | L56: =SUM(L62:L66) -> 1336 | M56: =SUM(M57:M66) -> 1476 | N56: =SUM(N57:N66) -> 1636 | O56: =SUM(O57:O66) -> 1636 | P56: =SUM(P57:P66) -> 2138 | Q56: =SUM(Q57:Q66) -> 2250 | R56: =SUM(R57:R66) -> 2284 | S56: =SUM(S57:S66) -> 2440 | T56: =SUM(T57:T66) -> 2468 | U56: =T56/T$6*100 -> 6.6462002
A57: 44 | B57: Atmosphere Kanifushi Maldives | C57: Kanifushi | D57: 2013 | E57: 140 | F57: 133 | G57: - | H57: - | I57: - | J57: - | K57: - | L57: - | M57: 140 | N57: 300 | O57: 300 | P57: 300 | Q57: 300 | R57: 300 | S57: 300 | T57: 300 | U57: =T57/T$6*100 -> 0.80788496
A58: 45 | B58: Cocoon Maldives | C58: Ookolhu Finolhu | D58: 2016 | E58: 302 | F58: 122 | G58: - | H58: - | I58: - | J58: - | K58: - | L58: - | M58: - | N58: - | O58: - | P58: 302 | Q58: 302 | R58: 302 | S58: 302 | T58: 302 | U58: =T58/T$6*100 -> 0.81327086
A59: 46 | B59: Fushifaru Maldives | C59: Fushifaru | D59: 2017 | E59: 98 | F59: na | M59: - | N59: - | O59: - | P59: - | Q59: 98 | R59: 98 | S59: 98 | T59: 126 | U59: =T59/T$6*100 -> 0.33931168
A60: 47 | B60: Hurawalhi Island Resort | C60: Hurawalhi | D60: 2016 | E60: 180 | F60: 148 | G60: - | H60: - | I60: - | J60: - | K60: - | L60: - | M60: - | N60: - | O60: - | P60: 180 | Q60: 180 | R60: 180 | S60: 180 | T60: 180 | U60: =T60/T$6*100 -> 0.48473097
A61: 48 | B61: Innahura Maldives Resort | C61: Innahuraa | D61: 2019 | E61: 156 | F61: na | M61: - | N61: - | O61: - | P61: - | Q61: - | R61: - | S61: 156 | T61: 156 | U61: =T61/T$6*100 -> 0.42010018
A62: 49 | B62: Kanuhura | C62: Lh. Kanuhuraa | D62: 1999 | E62: 200 | F62: 125.5 | G62: 200 | H62: 200 | I62: 200 | J62: 200 | K62: 200 | L62: 200 | M62: 200 | N62: 200 | O62: 200 | P62: 200 | Q62: 192 | R62: 192 | S62: 192 | T62: 192 | U62: =T62/T$6*100 -> 0.51704637
A63: 50 | B63: Komandoo Maldive Island Resort | C63: Lh. Komandoo | D63: 1998 | E63: 90 | F63: 128.7 | G63: 120 | H63: 120 | I63: 120 | J63: 120 | K63: 120 | L63: 120 | M63: 120 | N63: 120 | O63: 120 | P63: 130 | Q63: 130 | R63: 130 | S63: 130 | T63: 130 | U63: =T63/T$6*100 -> 0.35008348
A64: 51 | B64: Kudadoo Maldives Private island | C64: Lh. Kudadhoo | D64: 2018 | E64: 34 | F64: na | M64: - | N64: - | O64: - | P64: - | Q64: - | R64: 34 | S64: 34 | T64: 34 | U64: =T64/T$6*100 -> 0.091560295
A65: 52 | B65: Kuredhdhu Island Resort | C65: Lh. Kuredhdhu | D65: 1978 | E65: 18 | F65: 128.7 | G65: 740 | H65: 746 | I65: 768 | J65: 768 | K65: 768 | L65: 768 | M65: 768 | N65: 768 | O65: 768 | P65: 778 | Q65: 778 | R65: 778 | S65: 778 | T65: 778 | U65: =T65/T$6*100 -> 2.095115
A66: 53 | B66: Palm Beach Resort & Spa Maldives | C66: Lh. Madhiriguraidhoo | D66: 1999 | E66: 200 | F66: 128.7 | G66: 216 | H66: 228 | I66: 248 | J66: 248 | K66: 248 | L66: 248 | M66: 248 | N66: 248 | O66: 248 | P66: 248 | Q66: 270 | R66: 270 | S66: 270 | T66: 270 | U66: =T66/T$6*100 -> 0.72709646
B67: Male' Atoll (K) | D67: - | E67: - | F67: - | G67: =SUM(G68:G120) -> 8420 | H67: =SUM(H68:H120) -> 8610 | I67: =SUM(I68:I120) -> 8678 | J67: =SUM(J68:J120) -> 8754 | K67: =SUM(K68:K120) -> 8824 | L67: =SUM(L68:L120) -> 8828 | M67: =SUM(M68:M120) -> 8964 | N67: =SUM(N68:N120) -> 8968 | ... T67: =SUM(T68:T120) -> 12048 | U67: =T67/T$6*100 -> 32.44466
A68: 54 | B68: Adhaaran Club Rannaalhi | C68: K. Rannalhi | D68: 1978 | E68: 34 | F68: 34 | G68: 232 | H68: 256 | I68: 256 | J68: 256 | K68: 256 | L68: 256 | M68: 256 | N68: 256 | O68: 256 | P68: 256 | Q68: 260 | R68: 260 | S68: 260 | T68: 260 | U68: =T68/T$6*100 -> 0.70016696
A69: 55 | B69: Adhaaran Prestige Vaadhu | C69: K. Vaadhu | D69: 1978 | E69: 18 | F69: 8 | G69: 66 | H69: 66 | I69: 100 | J69: 100 | K69: 100 | L69: 100 | M69: 100 | N69: 100 | O69: 100 | P69: 100 | Q69: 100 | R69: 100 | S69: 100 | T69: 100 | U69: =T69/T$6*100 -> 0.26929499
A70: 56 | B70: Adhaaran Select Hudhuranfushi | C70: K. Lhohifushi | D70: 1979 | E70: 40 | F70: 22.5 | G70: 354 | H70: 354 | I70: 354 | J70: 354 | K70: 354 | L70: 354 | M70: 354 | N70: 354 | O70: 354 | P70: 354 | Q70: 404 | R70: 404 | S70: 404 | T70: 404 | U70: =T70/T$6*100 -> 1.0879517
A71: 57 | B71: Anantara Resort & Spa Maldives | C71: K. Dhigufinolhu | D71: 1980 | E71: 24 | F71: 40 | G71: 220 | H71: 220 | I71: 220 | J71: 220 | K71: 220 | L71: 220 | M71: 220 | N71: 220 | O71: 220 | P71: 220 | Q71: 226 | R71: 226 | S71: 226 | T71: 226 | U71: =T71/T$6*100 -> 0.60860667
A72: 58 | B72: Angsana Resort & Spa Maldives - Ihuru | C72: K. Ihuru | D72: 1978 | E72: 20 | F72: 17 | G72: 90 | H72: 90 | I72: 90 | J72: 90 | K72: 90 | L72: 90 | M72: 90 | N72: 90 | O72: 90 | P72: 90 | Q72: 90 | R72: 90 | S72: 90 | T72: 90 | U72: =T72/T$6*100 -> 0.24236549
A73: 59 | B73: Asdhu Sun Island | C73: K. Asdhu | D73: 1981 | E73: 36 | F73: 32 | G73: 60 | H73: 60 | I73: 60 | J73: 60 | K73: 60 | L73: 60 | M73: 60 | N73: 60 | O73: 60 | P73: 60 | Q73: 60 | R73: 60 | S73: 60 | T73: 0 | U73: =T73/T$6*100 -> 0
A74: 60 | B74: Bandos Maldives | C74: K. Bandos | D74: 1972 | E74: 220 | F74: 8 | G74: 450 | H74: 450 | I74: 450 | J74: 450 | K74: 450 | L74: 450 | M74: 450 | N74: 430 | O74: 430 | P74: 430 | Q74: 430 | R74: 430 | S74: 430 | T74: 430 | U74: =T74/T$6*100 -> 1.1579684
A75: 61 | B75: Banyan Tree Maldives Vabbinfaru | C75: K. Vabbinfaru | D75: 1977 | E75: 24 | F75: 12 | G75: 96 | H75: 96 | I75: 96 | J75: 96 | K75: 96 | L75: 96 | M75: 96 | N75: 96 | O75: 96 | P75: 96 | Q75: 96 | R75: 96 | S75: 96 | T75: 96 | U75: =T75/T$6*100 -> 0.25852319
A76: 62 | B76: Baros Maldives | C76: K. Baros | D76: 1973 | E76: 56 | F76: 16 | G76: 150 | H76: 150 | I76: 150 | J76: 150 | K76: 150 | L76: 150 | M76: 150 | N76: 150 | O76: 150 | P76: 150 | Q76: 150 | R76: 150 | S76: 150 | T76: 150 | U76: =T76/T$6*100 -> 0.40394248
A77: 63 | B77: Biyaadhu Island Resort | C77: K. Biyaadhoo | D77: 1982 | E77: 192 | F77: 18 | G77: 192 | H77: 192 | I77: 192 | J77: 192 | K77: 192 | L77: 192 | M77: 192 | N77: 192 | O77: 192 | P77: 192 | Q77: 192 | R77: 192 | S77: 192 | T77: 192 | U77: =T77/T$6*100 -> 0.51704637
A78: 64 | B78: Centara Ras Fushi Resort & Spa | C78: K. Giraavaru | D78: 1980 | E78: 40 | F78: 11.3 | G78: 132 | H78: 132 | I78: 132 | J78: 132 | K78: 132 | L78: 132 | M78: 220 | N78: 220 | O78: 220 | P78: 220 | Q78: 280 | R78: 280 | S78: 280 | T78: 280 | U78: =T78/T$6*100 -> 0.75402596
